Workbook

Sheet MATRIZ ENERO 2026
A1: CONCEPTOS | B1: CANTIDAD | C1: VALOR TOTAL
A2: SIN ACUSE | B2: =GETPIVOTDATA("Cuenta de SIN ACUSE",'SIN ACUSES'!$A$3) -> 148 | C2: =GETPIVOTDATA("Suma de Total",'SIN ACUSES'!$A$3) -> 3.8742962e+08
A3: 1 ACUSE | B3: =GETPIVOTDATA("Cuenta de 1 ACUSE",'1 ACUSE'!$A$3) -> 110 | C3: =GETPIVOTDATA("Suma de Total",'1 ACUSE'!$A$3) -> 8.8028017e+08
A4: 2 ACUSES | B4: =GETPIVOTDATA("Cuenta de 2 ACUSE",'2 ACUSES'!$A$3) -> 25 | C4: =GETPIVOTDATA("Suma de Total",'2 ACUSES'!$A$3) -> 2.9529969e+08
A5: 3 ACUSES | B5: =GETPIVOTDATA("Cuenta de 3 ACUSE",'3 ACUSES'!$A$3) -> 187 | C5: =GETPIVOTDATA("Suma de Total",'3 ACUSES'!$A$3) -> 8.1045732e+08
A6: RECHAZADAS | B6: =GETPIVOTDATA("Cuenta de RECHAZADA",'RECHAZADAS '!$A$3) -> 20 | C6: =GETPIVOTDATA("Suma de Total",'RECHAZADAS '!$A$3) -> 4.9694482e+09
A7: PAGAS EN SISTEMA | B7: =GETPIVOTDATA("Cuenta de YA PAGA EN SISTEMA",'PAGAS EN SISTEMA'!$A$3) -> 510 | C7: =GETPIVOTDATA("Suma de Total",'PAGAS EN SISTEMA'!$A$3) -> 4.9694482e+09
B8: =SUM(B2:B7) -> 1000
A10: Tipo de documento | B10: CUFE/CUDE | C10: Folio | D10: Columna1 | E10: Prefijo | F10: Fecha Emisión | G10: Fecha Recepción | H10: NIT Emisor | I10: Nombre Emisor | J10: NIT Receptor | K10: Nombre Receptor | L10: IVA | M10: ICA | N10: IPC | O10: Total | P10: Estado | Q10: Grupo | R10: 1 ACUSE | S10: 2 ACUSE | T10: 3 ACUSE | U10: RECHAZADA | V10: SIN ACUSE | W10: YA PAGA EN SISTEMA | X10: OBSERVACIONES
A11: Factura electrónica | B11: 93074bd740e997c307276fd40785578d26c7149dc6b0d390ff1974e2c5f279a631512f4baded1b8c191af974e7426fa0 | C11: 104623 | D11: =C11-C12 -> -1 | E11: FVE | F11: 06-01-2026 | G11: 06-01-2026 06:51:28 | H11: 900800595 | I11: Provexpress SAS | J11: 900453990 | K11: Fundacion Educativa Colegio Militar Inocencio Chinca Y Su Campus Deportivo | L11: 362673.14 | M11: 0 | N11: 0 | O11: 2271479.1 | P11: Aprobado con notificación | Q11: Emitido | V11: X
A12: Factura electrónica | B12: fe8bb6ec891cf48d8975d938ab00cd2b348b0f748ba29dff5a0fe901ac0fad276781cdc6dabcba91f8833e4adf81bed8 | C12: 104624 | D12: =C12-C13 -> -1 | E12: FVE | F12: 06-01-2026 | G12: 06-01-2026 06:51:33 | H12: 900800595 | I12: Provexpress SAS | J12: 901662739 | K12: Improve Learning SAS | L12: 0 | M12: 0 | N12: 0 | O12: 19962970 | P12: Aprobado con notificación | Q12: Emitido | R12: X
A13: Factura electrónica | B13: 43042fb18294caecd13113422e319846f9c8933dd7316e622324e1c8aae2bc4c1996956121f1462cbdb413faec394a2c | C13: 104625 | D13: =C13-C14 -> -1 | E13: FVE | F13: 06-01-2026 | G13: 06-01-2026 06:51:37 | H13: 900800595 | I13: Provexpress SAS | J13: 830095970 | K13: Distribuidora Y Editora Richmond SAS | L13: 0 | M13: 0 | N13: 0 | O13: 19962970 | P13: Aprobado con notificación | Q13: Emitido | R13: X
A14: Factura electrónica | B14: fe8e0145c40fedcc05a33a04d3a33746824766e163a02d2f2af536217dd3fed77f8431553fcf56eb667d7ca087f3d314 | C14: 104626 | D14: =C14-C15 -> -1 | E14: FVE | F14: 06-01-2026 | G14: 06-01-2026 07:06:50 | H14: 900800595 | I14: Provexpress SAS | J14: 900682841 | K14: Educactiva SAS | L14: 0 | M14: 0 | N14: 0 | O14: 39925940 | P14: Aprobado con notificación | Q14: Emitido | R14: X
A15: Factura electrónica | B15: f463a8aad17f5efc459b4375599b8f48e70411eef7fe456f56fed4a4b644fd9c4a3f13254744d420d0dcc28bac8a949b | C15: 104627 | D15: =C15-C16 -> -1 | E15: FVE | F15: 06-01-2026 | G15: 06-01-2026 07:06:54 | H15: 900800595 | I15: Provexpress SAS | J15: 800024265 | K15: Editorial Santillana SAS | L15: 0 | M15: 0 | N15: 0 | O15: 19962970 | P15: Aprobado con notificación | Q15: Emitido | T15: X
A16: Factura electrónica | B16: dcfba34922f9686abaac32c632009603e447274533d0288c6349667455ee3c93b0c3d55d6fcb999915887ec1d03d3dde | C16: 104628 | D16: =C16-C17 -> -1 | E16: FVE | F16: 06-01-2026 | G16: 06-01-2026 07:06:59 | H16: 900800595 | I16: Provexpress SAS | J16: 800125872 | K16: Keralty SAS | L16: 373204.65 | M16: 0 | N16: 0 | O16: 2337439.6 | P16: Aprobado con notificación | Q16: Emitido | W16: X | X16: PAGA EN EL SISTEMA 27/02/2026
A17: Factura electrónica | B17: b60ba283e3653a668d1a062efda350e75177d7a5418581d079093e09c43c215411b03a513fcd1970a8ae3d68856c525c | C17: 104629 | D17: =C17-C18 -> -1 | E17: FVE | F17: 06-01-2026 | G17: 06-01-2026 07:07:03 | H17: 900800595 | I17: Provexpress SAS | J17: 800125872 | K17: Keralty SAS | L17: 54253.17 | M17: 0 | N17: 0 | O17: 339796.17 | P17: Aprobado con notificación | Q17: Emitido | R17: X
A18: Factura electrónica | B18: 8bb13292ed57504f59b6dd32fe3c1167386d3d3a550bb983be77e3d82c8c52eabed53a35e670da7b286cd7f8553a5c25 | C18: 104630 | D18: =C18-C19 -> -1 | E18: FVE | F18: 06-01-2026 | G18: 06-01-2026 07:07:09 | H18: 900800595 | I18: Provexpress SAS | J18: 800125872 | K18: Keralty SAS | L18: 0 | M18: 0 | N18: 0 | O18: 1865317.4 | P18: Aprobado con notificación | Q18: Emitido | W18: X | X18: PAGA EN EL SISTEMA 27/02/2026
A19: Factura electrónica | B19: 94199b1deb41ac67f09fc244a0d5cff33bd57526447092b061a65f2ef454b083e7cd952ea326fb3a647088bf884322ab | C19: 104631 | D19: =C19-C20 -> -1 | E19: FVE | F19: 06-01-2026 | G19: 06-01-2026 07:07:13 | H19: 900800595 | I19: Provexpress SAS | J19: 800149384 | K19: Clinica Colsanitas SA | L19: 461452.24 | M19: 0 | N19: 0 | O19: 2890148.2 | P19: Aprobado con notificación | Q19: Emitido | R19: X
A20: Factura electrónica | B20: 123fb4dc2236a0301dfe2afab6c2a7ecf9bc7e4e235e3fd48c36092bfb54710a1f1349d4e619f5ec160dc0a6e085b494 | C20: 104632 | D20: =C20-C21 -> -1 | E20: FVE | F20: 06-01-2026 | G20: 06-01-2026 07:07:17 | H20: 900800595 | I20: Provexpress SAS | J20: 800149384 | K20: Clinica Colsanitas SA | L20: 2786643.7 | M20: 0 | N20: 0 | O20: 17453190 | P20: Aprobado con notificación | Q20: Emitido | W20: X | X20: PAGA EN SISTEMA 03/03/2026
A21: Factura electrónica | B21: 08ef3ff49ec6b065c3c6257354597af1d5c4ce3c66fba50d180291e92ad68a276716488a50f2cbe079cbc1ca50810690 | C21: 104633 | D21: =C21-C22 -> -1 | E21: FVE | F21: 06-01-2026 | G21: 06-01-2026 07:07:23 | H21: 900800595 | I21: Provexpress SAS | J21: 800149384 | K21: Clinica Colsanitas SA | L21: 245161.18 | M21: 0 | N21: 0 | O21: 1535483.2 | P21: Aprobado con notificación | Q21: Emitido | W21: X | X21: PAGA EN SISTEMA 03/03/2026
A22: Factura electrónica | B22: f5bde27d37557c9c090b30582c8ecc936ec72c611addfb3b62d676875af59214852e26918d8ed6cd321a37df485edb04 | C22: 104634 | D22: =C22-C23 -> -1 | E22: FVE | F22: 06-01-2026 | G22: 06-01-2026 07:07:27 | H22: 900800595 | I22: Provexpress SAS | J22: 800149384 | K22: Clinica Colsanitas SA | L22: 3203986.5 | M22: 0 | N22: 0 | O22: 20067074 | P22: Aprobado con notificación | Q22: Emitido | W22: X | X22: PAGA EN SISTEMA 03/03/2026
A23: Factura electrónica | B23: f00d2280f33fedf81a2037625549256568358830a6b08bcaaa9c34b2ca94aa821525bccb1aa9f97353a248c595bf87a4 | C23: 104635 | D23: =C23-C24 -> -1 | E23: FVE | F23: 06-01-2026 | G23: 06-01-2026 07:07:31 | H23: 900800595 | I23: Provexpress SAS | J23: 800149384 | K23: Clinica Colsanitas SA | L23: 980644.72 | M23: 0 | N23: 0 | O23: 6141932.7 | P23: Aprobado con notificación | Q23: Emitido | W23: X | X23: PAGA EN SISTEMA 03/03/2026
A24: Factura electrónica | B24: cb8840377dfb85915c7f912b8590e2a38bccb027232de1b397507a138031dc6b9aa3704d36144a09d379368806aa9ab3 | C24: 104636 | D24: =C24-C25 -> -1 | E24: FVE | F24: 06-01-2026 | G24: 06-01-2026 07:07:36 | H24: 900800595 | I24: Provexpress SAS | J24: 800149384 | K24: Clinica Colsanitas SA | L24: 103020.47 | M24: 0 | N24: 0 | O24: 645233.47 | P24: Aprobado con notificación | Q24: Emitido | W24: X | X24: PAGA EN SISTEMA 03/03/2026
A25: Factura electrónica | B25: a91b5f70e0de3354a0dfe3a44b5c5fe4b2e1bc3fd486f558f969a550843c8b9a24f63bc4f97a861d9df1243f19aa0622 | C25: 104637 | D25: =C25-C26 -> -1 | E25: FVE | F25: 06-01-2026 | G25: 06-01-2026 07:22:47 | H25: 900800595 | I25: Provexpress SAS | J25: 800149384 | K25: Clinica Colsanitas SA | L25: 373204.65 | M25: 0 | N25: 0 | O25: 2337439.6 | P25: Aprobado con notificación | Q25: Emitido | W25: X | X25: PAGA EN SISTEMA 03/03/2026
A26: Factura electrónica | B26: fe89b2af2b8522fccfb038194d6defebe93c0a3d32ee838cda4df2be101b2a71373a4ef1c3d916562dd9707cad8fb7a9 | C26: 104638 | D26: =C26-C27 -> -1 | E26: FVE | F26: 06-01-2026 | G26: 06-01-2026 07:22:52 | H26: 900800595 | I26: Provexpress SAS | J26: 800149384 | K26: Clinica Colsanitas SA | L26: 373204.65 | M26: 0 | N26: 0 | O26: 2337439.6 | P26: Aprobado con notificación | Q26: Emitido | W26: X | X26: PAGA EN SISTEMA 03/03/2026
A27: Factura electrónica | B27: 2ddb946c757d00f326058ae6525a094f9d2594ed7ee93cd2e151da61d46fe32e380304feea502b05452e6b9e1f79220a | C27: 104639 | D27: =C27-C28 -> -1 | E27: FVE | F27: 06-01-2026 | G27: 06-01-2026 07:22:57 | H27: 900800595 | I27: Provexpress SAS | J27: 800185773 | K27: Optica Colsanitas SAS | L27: 373204.65 | M27: 0 | N27: 0 | O27: 2337439.6 | P27: Aprobado con notificación | Q27: Emitido | W27: X | X27: PAGA EN SISTEMA 02/03/2026
A28: Factura electrónica | B28: 73f4c12f6bae2fabbd6c3b03947b8ae552cff4e6a5cd1da4e23d3e3d540b61a1fa995defad0d0e481d186d97e2d90a02 | C28: 104640 | D28: =C28-C29 -> -1 | E28: FVE | F28: 06-01-2026 | G28: 06-01-2026 07:23:01 | H28: 900800595 | I28: Provexpress SAS | J28: 860078828 | K28: Compañia De Medicina Prepagada Colsanitas SA | L28: 0 | M28: 0 | N28: 0 | O28: 7390248 | P28: Aprobado con notificación | Q28: Emitido | W28: X | X28: PAGA EN EL SISTEMA 27/02/2026
A29: Factura electrónica | B29: bd84cc834d8531837bb4c601a6b65bf624b904af73e32fb52d6e6fc98a178af80b1ecff368e0eb6b8254583a20096f52 | C29: 104641 | D29: =C29-C30 -> -1 | E29: FVE | F29: 06-01-2026 | G29: 06-01-2026 07:23:06 | H29: 900800595 | I29: Provexpress SAS | J29: 901493815 | K29: Versania Psicosocial Ita SAS | L29: 35764.84 | M29: 0 | N29: 0 | O29: 224000.84 | P29: Aprobado con notificación | Q29: Emitido | T29: X
A30: Factura electrónica | B30: 9165aa2948dc7f7685e0aec43193bada13fe383418f4bedcca9cdeaaf01a20171d6220ccdec430142e6ccc3ac45fd7e4 | C30: 104642 | D30: =C30-C31 -> -1 | E30: FVE | F30: 06-01-2026 | G30: 06-01-2026 07:23:11 | H30: 900800595 | I30: Provexpress SAS | J30: 901485933 | K30: Versania Primera Infancia SAS | L30: 373204.65 | M30: 0 | N30: 0 | O30: 2337439.6 | P30: Aprobado con notificación | Q30: Emitido | V30: X
A31: Factura electrónica | B31: 03f28dafd3dbed1b2c0b824fe85cfa30c5f788139cd3ec4f4fa4eb6048a6de6216046f36ed8e780bbb7cd906edf493f7 | C31: 104643 | D31: =C31-C32 -> -1 | E31: FVE | F31: 06-01-2026 | G31: 06-01-2026 07:23:16 | H31: 900800595 | I31: Provexpress SAS | J31: 830015429 | K31: Salud Ocupacional Sanitas SAS | L31: 0 | M31: 0 | N31: 0 | O31: 4197080.2 | P31: Aprobado con notificación | Q31: Emitido | W31: X | X31: PAGA EN SISTEMA 24/02/2026
A32: Factura electrónica | B32: 1f3c07dd53894bdc21299c529550e2f92aefb200e42877b0ea72546c46c3e02e721232007923318e4426822ea636a215 | C32: 104644 | D32: =C32-C33 -> -1 | E32: FVE | F32: 06-01-2026 | G32: 06-01-2026 07:23:20 | H32: 900800595 | I32: Provexpress SAS | J32: 900022253 | K32: Oftalmosanitas Cali SAS | L32: 57783.75 | M32: 0 | N32: 0 | O32: 361908.75 | P32: Aprobado con notificación | Q32: Emitido | W32: X | X32: PAGA EN SISTEMA 02/03/2026
A33: Factura electrónica | B33: 92303dca04433da38ff8161e03dfa04240cac2808e3a08b77b5d1d6d744c544f12ea9f5b371296395185c3c157c1e5f8 | C33: 104645 | D33: =C33-C34 -> -1 | E33: FVE | F33: 06-01-2026 | G33: 06-01-2026 07:23:25 | H33: 900800595 | I33: Provexpress SAS | J33: 800251440 | K33: Entidad Promotora De Salud Sanitas SAS | L33: 52064.94 | M33: 0 | N33: 0 | O33: 326090.94 | P33: Aprobado con notificación | Q33: Emitido | W33: X | X33: PAGA EN EL SISTEMA 27/02/2026
A34: Factura electrónica | B34: 00e5c221b2161c5e5eeb9a8f365ab3daf0a1dd3c76e44aa317c31511ba0d6e7312506b65604ea9f0f6a4b014d9b57fee | C34: 104646 | D34: =C34-C35 -> -1 | E34: FVE | F34: 06-01-2026 | G34: 06-01-2026 07:23:29 | H34: 900800595 | I34: Provexpress SAS | J34: 901041691 | K34: Centros Medicos Colsanitas S A S | L34: 1017956.2 | M34: 0 | N34: 0 | O34: 6375620.2 | P34: Aprobado con notificación | Q34: Emitido | W34: X | X34: PAGA EN SISTEMA 02/03/2026
A35: Factura electrónica | B35: 3f815376c2f36bcfa0e5c61d64819ec50b42e817157f1e0de0aa1840d7556ab3966474252f1a248ed5cd6b1612fd47db | C35: 104647 | D35: =C35-C36 -> -1 | E35: FVE | F35: 06-01-2026 | G35: 06-01-2026 07:23:35 | H35: 900800595 | I35: Provexpress SAS | J35: 901041691 | K35: Centros Medicos Colsanitas S A S | L35: 508978.08 | M35: 0 | N35: 0 | O35: 3187810.1 | P35: Aprobado con notificación | Q35: Emitido | W35: X | X35: PAGA EN SISTEMA 02/03/2026
A36: Factura electrónica | B36: f49a27d55ffd21f4c84dd47bf754b010cbe78dd20cb9286afc6974937712fe889a53bcaf330457420a089b63cc5822fc | C36: 104648 | D36: =C36-C37 -> -1 | E36: FVE | F36: 06-01-2026 | G36: 06-01-2026 07:38:46 | H36: 900800595 | I36: Provexpress SAS | J36: 900123408 | K36: Compañia De Inversiones Textiles De Moda SAS Texmoda SAS | L36: 342000 | M36: 0 | N36: 0 | O36: 2142000 | P36: Aprobado con notificación | Q36: Emitido | W36: X | X36: PAGA EN SISTEMA 02/03/2026
A37: Factura electrónica | B37: 4016019bc78adc60418353a1ae240ba5ffb72d21d88f1ba887516392e14e085aecb142da6bc93b7e5de2573b0ea1424e | C37: 104649 | D37: =C37-C38 -> -1 | E37: FVE | F37: 06-01-2026 | G37: 06-01-2026 07:38:51 | H37: 900800595 | I37: Provexpress SAS | J37: 900123408 | K37: Compañia De Inversiones Textiles De Moda SAS Texmoda SAS | L37: 96212.2 | M37: 0 | N37: 0 | O37: 602592.2 | P37: Aprobado con notificación | Q37: Emitido | W37: X | X37: PAGA EN SISTEMA 02/03/2026
A38: Factura electrónica | B38: 4157c16dba2959dc4e408697df8fac6a315b5ed30cb67ecf2815104dd24d14c8df531883fca20187bbb62ef1430012c9 | C38: 104650 | D38: =C38-C39 -> -1 | E38: FVE | F38: 06-01-2026 | G38: 06-01-2026 07:38:55 | H38: 900800595 | I38: Provexpress SAS | J38: 860516806 | K38: Permoda Ltda | L38: 271924.2 | M38: 0 | N38: 0 | O38: 1703104.2 | P38: Aprobado con notificación | Q38: Emitido | W38: x | X38: PAGA EN SISTEMA 24/02/2026
A39: Factura electrónica | B39: 378273d8e97e63e12480033faec2a078621c28b36dd2bb847aecda2f7cf1a1a1b5625bb3c317be1337ec9ba3b0c4fd46 | C39: 104651 | D39: =C39-C40 -> -1 | E39: FVE | F39: 06-01-2026 | G39: 06-01-2026 07:39:00 | H39: 900800595 | I39: Provexpress SAS | J39: 860003020 | K39: Banco Bilbao Vizcaya Argentaria Colombia SA | L39: 43701.9 | M39: 0 | N39: 0 | O39: 273711.9 | P39: Aprobado con notificación | Q39: Emitido | W39: X | X39: PAGA EN SISTEMA 13/02/2026
A40: Factura electrónica | B40: 3057c8dfcd8529d4a91df5068b9c80f853017f2c469d333866b2bc770bd948cfe65c6a7bfc372c17c4d1ef5c8f15014d | C40: 104652 | D40: =C40-C41 -> -1 | E40: FVE | F40: 06-01-2026 | G40: 06-01-2026 07:39:05 | H40: 900800595 | I40: Provexpress SAS | J40: 900532450 | K40: Atlantic Quantum Innovations S A S | L40: 595976.8 | M40: 0 | N40: 0 | O40: 3732696.8 | P40: Aprobado con notificación | Q40: Emitido | W40: X | X40: FACTURA PAGA EN EL SISTEMA 23/01/2026
A41: Factura electrónica | B41: 19d3984f41bc5a189a9d34e1ecbc61f7f7fadf13d53f575749f6c5e9f5594563eeca944c2ec62ffb3c20a6813906a5b6 | C41: 104653 | D41: =C41-C42 -> -1 | E41: FVE | F41: 06-01-2026 | G41: 06-01-2026 07:39:09 | H41: 900800595 | I41: Provexpress SAS | J41: 822001390 | K41: Junta De Calificacion De Invalidez Regional Meta | L41: 0 | M41: 0 | N41: 0 | O41: 4105108 | P41: Aprobado con notificación | Q41: Emitido | W41: X | X41: FACTURA PAGA EN EL SISTEMA 30/12/2024
A42: Factura electrónica | B42: b9d96c5b54cc02559f9d1fc3c10302ce74c98372a3a890151c8d1cfc65bc1b6088d02aad10d5513b1e7139195a6b3511 | C42: 104654 | D42: =C42-C43 -> -1 | E42: FVE | F42: 06-01-2026 | G42: 06-01-2026 07:39:14 | H42: 900800595 | I42: Provexpress SAS | J42: 901101746 | K42: Kaizen Group Ingenieria SAS | L42: 39900 | M42: 0 | N42: 0 | O42: 249900 | P42: Aprobado con notificación | Q42: Emitido | W42: X | X42: PAGA EN EL SISTEMA 26/02/2026
A43: Factura electrónica | B43: 071958b45923371a824df9465b7586eda39a974fe73c7d90cdba8e6174fd9a216d8dfd09a6733ef21421301a4d8c2ba5 | C43: 104655 | D43: =C43-C44 -> -1 | E43: FVE | F43: 06-01-2026 | G43: 06-01-2026 07:39:18 | H43: 900800595 | I43: Provexpress SAS | J43: 901101746 | K43: Kaizen Group Ingenieria SAS | L43: 239400 | M43: 0 | N43: 0 | O43: 1499400 | P43: Aprobado con notificación | Q43: Emitido | T43: x
A44: Factura electrónica | B44: 51116859516037c3ce25a30be695ce1fd358baa3a00ef8799c512ea26f00510d1677f43fb24cf14e101e5889df976a61 | C44: 104656 | D44: =C44-C45 -> -1 | E44: FVE | F44: 06-01-2026 | G44: 06-01-2026 07:39:23 | H44: 900800595 | I44: Provexpress SAS | J44: 901101746 | K44: Kaizen Group Ingenieria SAS | L44: 292600 | M44: 0 | N44: 0 | O44: 1832600 | P44: Aprobado con notificación | Q44: Emitido | T44: x
A45: Factura electrónica | B45: 05f7ac8b70e2d5dfdcf27a4e29986bf9f8228af05e2bd1222ce30caa177c5e90c40ff96b240fc9685cc01a051ff86c30 | C45: 104657 | D45: =C45-C46 -> -1 | E45: FVE | F45: 06-01-2026 | G45: 06-01-2026 07:39:27 | H45: 900800595 | I45: Provexpress SAS | J45: 901754581 | K45: Aquamech System SAS | L45: 53200 | M45: 0 | N45: 0 | O45: 333200 | P45: Aprobado con notificación | Q45: Emitido | W45: x | X45: PAGA EN SISTEMA 16/02/2026
A46: Factura electrónica | B46: a8cc0e2a68c234a12a18aae4b223bce3c85a35e96fba8908074d3e3f5cf88e52c8e27b95f402465ba2b9d6a66a90cf69 | C46: 104658 | D46: =C46-C47 -> -1 | E46: FVE | F46: 06-01-2026 | G46: 06-01-2026 07:39:31 | H46: 900800595 | I46: Provexpress SAS | J46: 900050036 | K46: Cushman & WaKefield Colombia SAS | L46: 20954.34 | M46: 0 | N46: 0 | O46: 131240.34 | P46: Aprobado con notificación | Q46: Emitido | W46: X | X46: FACTURA PAGA EN EL SISTEMA 16/02/2026
A47: Factura electrónica | B47: 8a71632241857ddb5b63f15d5ee3d3c058767a2c5b98f06ac9dcebed003a5df5194de3f7dacb331d51a10828fb339e75 | C47: 104659 | D47: =C47-C48 -> -1 | E47: FVE | F47: 06-01-2026 | G47: 06-01-2026 07:54:42 | H47: 900800595 | I47: Provexpress SAS | J47: 830130106 | K47: Soenergy International Colombia SAS | L47: 846282.42 | M47: 0 | N47: 0 | O47: 5300400.4 | P47: Aprobado con notificación | Q47: Emitido | V47: X
A48: Factura electrónica | B48: d4b92554cb0cd44b7185116623f877afb750e50a735442c223e72cceb9bc9d07df4a9f4754b506d89c6b925057f43a29 | C48: 104660 | D48: =C48-C49 -> -1 | E48: FVE | F48: 06-01-2026 | G48: 06-01-2026 07:54:47 | H48: 900800595 | I48: Provexpress SAS | J48: 860013570 | K48: Caja De Compensacion Familiar Cafam | L48: 827462.92 | M48: 0 | N48: 0 | O48: 5182530.9 | P48: Aprobado con notificación | Q48: Emitido | W48: X | X48: PAGA EN SISTEMA 16/02/2026
A49: Factura electrónica | B49: a0639ee0e2ef5169a0b7c14a905d3b02db4e957f0fc37342aca9205924b1aa868cc1c8d5a46eb7f990d570d8c105cc5e | C49: 104661 | D49: =C49-C50 -> -1 | E49: FVE | F49: 06-01-2026 | G49: 06-01-2026 07:54:52 | H49: 900800595 | I49: Provexpress SAS | J49: 901371316 | K49: Onboard Logistics Colombia SAS | L49: 17100 | M49: 0 | N49: 0 | O49: 5854100 | P49: Aprobado con notificación | Q49: Emitido | U49: x | X49: NC
A50: Factura electrónica | B50: 870b65a03c04d36c77ed4ce2424462d335e3eb6e256efe9d38650bb5c86c13de50f66d6a8a7fc27eaab42da93a7f78db | C50: 104662 | D50: =C50-C51 -> -1 | E50: FVE | F50: 06-01-2026 | G50: 06-01-2026 07:54:56 | H50: 900800595 | I50: Provexpress SAS | J50: 901371316 | K50: Onboard Logistics Colombia SAS | L50: 74100 | M50: 0 | N50: 0 | O50: 464100 | P50: Aprobado con notificación | Q50: Emitido | R50: X
A51: Factura electrónica | B51: 81937cb671203a679c681e644baef4c492369fe0b97334b7c96baba9454073b7cb98ee6eb1b93b6b50dbf0ca60335baf | C51: 104663 | D51: =C51-C52 -> -1 | E51: FVE | F51: 06-01-2026 | G51: 06-01-2026 07:55:01 | H51: 900800595 | I51: Provexpress SAS | J51: 800198693 | K51: Señales Ltda | L51: 777100 | M51: 0 | N51: 0 | O51: 4867100 | P51: Aprobado con notificación | Q51: Emitido | W51: x | X51: PAGA EN SISTEMA 27/02/2026
A52: Factura electrónica | B52: 3c44b7c31ea269d2b0fd7e3b3f69f995b938991c45cb12d3c1845cc4f55f61322d441a3821ac88da53c573881fbb1360 | C52: 104664 | D52: =C52-C53 -> -1 | E52: FVE | F52: 06-01-2026 | G52: 06-01-2026 07:55:06 | H52: 900800595 | I52: Provexpress SAS | J52: 800207192 | K52: Syntofarma S A | L52: 1425000 | M52: 0 | N52: 0 | O52: 8925000 | P52: Aprobado con notificación | Q52: Emitido | W52: X | X52: PAGA EN SISTEMA 02/03/2026
A53: Factura electrónica | B53: 3b5e8a135795d5862148cd9b4a5d43e0762da45a37af733e761d4ea00c7a6039f0dc77c680ffd8556edd566be8b653e2 | C53: 104665 | D53: =C53-C54 -> -1 | E53: FVE | F53: 06-01-2026 | G53: 06-01-2026 07:55:10 | H53: 900800595 | I53: Provexpress SAS | J53: 901248246 | K53: Excellence Logging Latin America Limited, Sucursal Colombiana | L53: 29715.6 | M53: 0 | N53: 0 | O53: 248197.6 | P53: Aprobado con notificación | Q53: Emitido | W53: X | X53: PAGA EN SISTEMA 23/02/2026
A54: Factura electrónica | B54: 4e4f58884cb3abb46c264ba1892827e0f49962283f8af6258b7303219570f2854d786d6f1afaeba6b868d0f3f3511be6 | C54: 104666 | D54: =C54-C55 -> -1 | E54: FVE | F54: 06-01-2026 | G54: 06-01-2026 07:55:14 | H54: 900800595 | I54: Provexpress SAS | J54: 901248246 | K54: Excellence Logging Latin America Limited, Sucursal Colombiana | L54: 201580.08 | M54: 0 | N54: 0 | O54: 1368104.1 | P54: Aprobado con notificación | Q54: Emitido | W54: X | X54: PAGA EN SISTEMA 23/02/2026
A55: Factura electrónica | B55: 7c250a53b02f3c7d447b638139230593864e4528d5706f1481c24593e29ec516dcf3e6cc62aa59b2a325e005b8bac587 | C55: 104667 | D55: =C55-C56 -> -1 | E55: FVE | F55: 06-01-2026 | G55: 06-01-2026 07:55:19 | H55: 900800595 | I55: Provexpress SAS | J55: 900943048 | K55: Pwc Contadores Y Auditores SAS | L55: 31507.7 | M55: 0 | N55: 0 | O55: 197337.7 | P55: Aprobado con notificación | Q55: Emitido | V55: X
A56: Factura electrónica | B56: 606e9372d749ca685a60d1b33eddf38416704bb47bd3fd5b2e593986f6ff36c27aeb5f5ea1cbf59eae1316008cf4b7c5 | C56: 104668 | D56: =C56-C57 -> -1 | E56: FVE | F56: 06-01-2026 | G56: 06-01-2026 07:55:23 | H56: 900800595 | I56: Provexpress SAS | J56: 900943048 | K56: Pwc Contadores Y Auditores SAS | L56: 26774.8 | M56: 0 | N56: 0 | O56: 167694.8 | P56: Aprobado con notificación | Q56: Emitido
A57: Factura electrónica | B57: b648f5e6903e9f049d9ebc705d584e123e6dda80dc5ad5b82d36339fbfaab019442fafd42493df43c930a1a6b637c987 | C57: 104669 | D57: =C57-C58 -> -1 | E57: FVE | F57: 06-01-2026 | G57: 06-01-2026 07:55:28 | H57: 900800595 | I57: Provexpress SAS | J57: 900943048 | K57: Pwc Contadores Y Auditores SAS | L57: 22668.9 | M57: 0 | N57: 0 | O57: 141978.9 | P57: Aprobado con notificación | Q57: Emitido | V57: X
A58: Factura electrónica | B58: e99d14aeeda89138215fe49a7e166c4675738dcc70612f865ce7f6157f324e7e9c122f06a2197dfff65cff04b5edc980 | C58: 104670 | D58: =C58-C59 -> -1 | E58: FVE | F58: 06-01-2026 | G58: 06-01-2026 08:10:49 | H58: 900800595 | I58: Provexpress SAS | J58: 900943048 | K58: Pwc Contadores Y Auditores SAS | L58: 22668.9 | M58: 0 | N58: 0 | O58: 141978.9 | P58: Aprobado con notificación | Q58: Emitido | V58: X
A59: Factura electrónica | B59: 045db8fc27d5652af58842caba0db536d7389773810a07ef4dd4c0b88615a17ac11f1433cbf45e0f3b5efa01acd31df6 | C59: 104671 | D59: =C59-C60 -> -1 | E59: FVE | F59: 06-01-2026 | G59: 06-01-2026 08:10:53 | H59: 900800595 | I59: Provexpress SAS | J59: 900943048 | K59: Pwc Contadores Y Auditores SAS | L59: 29945.9 | M59: 0 | N59: 0 | O59: 187555.9 | P59: Aprobado con notificación | Q59: Emitido | V59: X
A60: Factura electrónica | B60: 9aa24df2ea1aee81b4cd4d9b5a21a4f971b29962882f6ae8c47f3541b1c758bb998774b1204cb686f9184a3e0a2f70db | C60: 104672 | D60: =C60-C61 -> -1 | E60: FVE | F60: 06-01-2026 | G60: 06-01-2026 08:10:58 | H60: 900800595 | I60: Provexpress SAS | J60: 800028326 | K60: Novasoft S A S | L60: 551190 | M60: 0 | N60: 0 | O60: 3452190 | P60: Aprobado con notificación | Q60: Emitido | W60: X | X60: PAGA EN SISTEMA 29/01/2026
A61: Factura electrónica | B61: b972a9f9dd408814142f955308e904914ead5fd511dd082a1442f3b63f0d7bddd50f84dbcc428dbea39a8f4eb3a11176 | C61: 104673 | D61: =C61-C62 -> -1 | E61: FVE | F61: 06-01-2026 | G61: 06-01-2026 08:11:03 | H61: 900800595 | I61: Provexpress SAS | J61: 900179369 | K61: Confipetrol SAS | L61: 578322 | M61: 0 | N61: 0 | O61: 3622122 | P61: Aprobado con notificación | Q61: Emitido | T61: X
A62: Factura electrónica | B62: 0169c3cdd0e93d0ee9b4b08bcf6e75b85062158894ce3a73134bddb1f2e209d7d5d4202b6be50bfe292cd7204d4be397 | C62: 104674 | D62: =C62-C63 -> -1 | E62: FVE | F62: 06-01-2026 | G62: 06-01-2026 08:11:07 | H62: 900800595 | I62: Provexpress SAS | J62: 800028326 | K62: Novasoft S A S | L62: 66310 | M62: 0 | N62: 0 | O62: 415310 | P62: Aprobado con notificación | Q62: Emitido | W62: X | X62: PAGA EN SISTEMA 29/01/2026
A63: Factura electrónica | B63: 2a4168ee60ea5189d119245a094bfaeda41dce127680d162c080ae7d1feed7f20492e7c9420e25852aea6a95096afaf9 | C63: 104675 | D63: =C63-C64 -> -1 | E63: FVE | F63: 06-01-2026 | G63: 06-01-2026 08:11:12 | H63: 900800595 | I63: Provexpress SAS | J63: 805017818 | K63: Grivan Ingenieria SA | L63: 0 | M63: 0 | N63: 0 | O63: 21953666 | P63: Aprobado con notificación | Q63: Emitido | W63: x | X63: FACTURA PAGA EN EL SISTEMA 11/02/2026
A64: Factura electrónica | B64: 7deb8cfbbd1bb84d56ef76e6a513f36d231e18e75c032c852962d7ec7c24b41d158534d159edc9bd4c1b6986f7fb383a | C64: 104676 | D64: =C64-C65 -> -1 | E64: FVE | F64: 06-01-2026 | G64: 06-01-2026 08:11:17 | H64: 900800595 | I64: Provexpress SAS | J64: 900179369 | K64: Confipetrol SAS | L64: 330410 | M64: 0 | N64: 0 | O64: 2069410 | P64: Aprobado con notificación | Q64: Emitido | T64: X
A65: Factura electrónica | B65: 14e0d76e3752aa84939486d93bca895e158cc02b9c382d6f4439299eabb79b33b20bc8049e1e86b3c5482ee9cc812b00 | C65: 104677 | D65: =C65-C66 -> -1 | E65: FVE | F65: 06-01-2026 | G65: 06-01-2026 08:11:21 | H65: 900800595 | I65: Provexpress SAS | J65: 860005813 | K65: Deloitte & Touche SAS | L65: 122899.1 | M65: 0 | N65: 0 | O65: 789819.1 | P65: Aprobado con notificación | Q65: Emitido | W65: X | X65: PAGA EN SISTEMA 24/02/2026
A66: Factura electrónica | B66: 46a4800ac0bc40df9dce19e7b4bb288fbe07102adc21acf6c7d86d35f57f0dcb3cc338f1578d83b82401924945e5dedd | C66: 104678 | D66: =C66-C67 -> -1 | E66: FVE | F66: 06-01-2026 | G66: 06-01-2026 08:28:14 | H66: 900800595 | I66: Provexpress SAS | J66: 860005813 | K66: Deloitte & Touche SAS | L66: 142453.5 | M66: 0 | N66: 0 | O66: 1074903.5 | P66: Aprobado con notificación | Q66: Emitido | W66: X | X66: PAGA EN SISTEMA 24/02/2026
A67: Factura electrónica | B67: 131479e3fa2acf2203cbe86a1454f70c5641619a88cc4632eb698d86141bd04b82a9c8c38994a70d2c050d514174d86c | C67: 104679 | D67: =C67-C68 -> -1 | E67: FVE | F67: 06-01-2026 | G67: 06-01-2026 08:28:10 | H67: 900800595 | I67: Provexpress SAS | J67: 800013879 | K67: Ecomarket SAS | L67: 67454.75 | M67: 0 | N67: 0 | O67: 422479.75 | P67: Aprobado con notificación | Q67: Emitido | W67: x | X67: FACTURA PAGA EN EL SISTEMA 09/02/2026
A68: Factura electrónica | B68: 80a738b006bb9d7a940eaaad8d653aff2f07305be621e15ce00fa7b04ea19f82edc5aa97cdde1a291086ebe23ffa642e | C68: 104680 | D68: =C68-C69 -> -1 | E68: FVE | F68: 06-01-2026 | G68: 06-01-2026 08:28:11 | H68: 900800595 | I68: Provexpress SAS | J68: 800019102 | K68: Interasesores Asesores Empresariales Administrativos SA | L68: 53619.9 | M68: 0 | N68: 0 | O68: 335829.9 | P68: Aprobado con notificación | Q68: Emitido | W68: X | X68: PAGA EN SISTEMA 9/02/2026
A69: Factura electrónica | B69: 3e01f3f6fe2598b885dfdcf9b2b6ca46034d3b8734860c290d1d525259cbffb042ed0db81ef3ce65da2c793bd12f68de | C69: 104681 | D69: =C69-C70 -> -1 | E69: FVE | F69: 06-01-2026 | G69: 06-01-2026 08:28:15 | H69: 900800595 | I69: Provexpress SAS | J69: 860513970 | K69: Comercializadora Internacional Milpa SA | L69: 265478.45 | M69: 0 | N69: 0 | O69: 1677253.4 | P69: Aprobado con notificación | Q69: Emitido | W69: x | X69: PAGA EN SISTEMA 30/01/2026
A70: Factura electrónica | B70: 920ab4a8931633dbd77bb5d1c736ee1296ed219d443f811f0362661c42260cbcca6d1d4b37f87d50e7b21b537972e44d | C70: 104682 | D70: =C70-#REF! -> #REF! | E70: FVE | F70: 06-01-2026 | G70: 06-01-2026 08:28:12 | H70: 900800595 | I70: Provexpress SAS | J70: 890300918 | K70: Sager SAS | L70: 4880720 | M70: 0 | N70: 0 | O70: 30568720 | P70: Aprobado con notificación | Q70: Emitido | T70: X
A71: Factura electrónica | B71: dfdf2235ece6e36bbe3014654bc6d337d57a64038d2207e7c5d7105cc6ab28c35b7209f9f67ffc3c259e7bbc79bbe884 | C71: 104684 | D71: =C71-C72 -> -1 | E71: FVE | F71: 06-01-2026 | G71: 06-01-2026 08:43:15 | H71: 900800595 | I71: Provexpress SAS | J71: 830507705 | K71: Reliability Maintenance Services SAS | L71: 66120 | M71: 0 | N71: 0 | O71: 414120 | P71: Aprobado con notificación | Q71: Emitido | W71: X | X71: FACTURA PAGA EN EL SISTEMA 18/02/2026
A72: Factura electrónica | B72: 8193b91a67dd0941060a57b76a5b3448a37d70180fa67917042d5cf6a0b54be4cb600460ce73746db8eccc4bafeeefcf | C72: 104685 | D72: =C72-C73 -> -1 | E72: FVE | F72: 06-01-2026 | G72: 06-01-2026 08:43:28 | H72: 900800595 | I72: Provexpress SAS | J72: 800256769 | K72: Patrimonios Autonomos Aval Fiduciaria SA | L72: 163020 | M72: 0 | N72: 0 | O72: 1021020 | P72: Aprobado con notificación | Q72: Emitido | W72: x | X72: FACTURA PAGA EN EL SISTEMA 09/02/2026
A73: Factura electrónica | B73: 0d9d73f8607fec097bf05074a00a6442b5fb489431af3f9c5787feebc1e7b2b4528cdf4183830db516947e61c80d1c13 | C73: 104686 | D73: =C73-C74 -> -1 | E73: FVE | F73: 06-01-2026 | G73: 06-01-2026 08:43:11 | H73: 900800595 | I73: Provexpress SAS | J73: 800256769 | K73: Patrimonios Autonomos Aval Fiduciaria SA | L73: 830680 | M73: 0 | N73: 0 | O73: 5202680 | P73: Aprobado con notificación | Q73: Emitido | W73: x | X73: FACTURA PAGA EN EL SISTEMA 09/02/2026
A74: Factura electrónica | B74: a5f000fb0c7170fc581b9beedd92c13a3e87ebb5033fe6ff5755d5271a9dc3b8f178260aefe87bac6e302936701e41c0 | C74: 104687 | D74: =C74-C75 -> 4 | E74: FVE | F74: 06-01-2026 | G74: 06-01-2026 08:59:07 | H74: 900800595 | I74: Provexpress SAS | J74: 800256769 | K74: Patrimonios Autonomos Aval Fiduciaria SA | L74: 383040 | M74: 0 | N74: 0 | O74: 2399040 | P74: Aprobado con notificación | Q74: Emitido | W74: x | X74: FACTURA PAGA EN EL SISTEMA 09/02/2026
A75: Factura electrónica | B75: 4c88d442d6b4e06800288e027be80dd15e67aca3168f48f7194defe2a9f1ad80cce79d25cd8d634412b1cdcf283b10c6 | C75: 104683 | D75: =C75-C76 -> -6 | E75: FVE | F75: 06-01-2026 | G75: 06-01-2026 08:59:09 | H75: 900800595 | I75: Provexpress SAS | J75: 900078730 | K75: Transchiquinquira SA | L75: 99469.94 | M75: 0 | N75: 0 | O75: 622995.94 | P75: Aprobado con notificación | Q75: Emitido | V75: X
A76: Factura electrónica | B76: 3ffd68fe3db41121e60d48a7266e0804472f5d2694c76a875b0e1d106faed5299c9e64ddd4f9fcf995aebbbd0933ee85 | C76: 104689 | D76: =C76-C77 -> -1 | E76: FVE | F76: 06-01-2026 | G76: 06-01-2026 08:59:12 | H76: 900800595 | I76: Provexpress SAS | J76: 900477127 | K76: Business And Quality Services SAS | L76: 91164.8 | M76: 0 | N76: 0 | O76: 891284.8 | P76: Aprobado con notificación | Q76: Emitido | W76: X | X76: PAGA EN SISTEMA 16/02/2026
A77: Factura electrónica | B77: 743db5dd921803dbf5b9ea44689b1d98cf9037da05a0bc54654bdf7b9d2b3135a3255b105b16b8f7a13b014ade009d54 | C77: 104690 | D77: =C77-C78 -> -1 | E77: FVE | F77: 06-01-2026 | G77: 06-01-2026 09:00:05 | H77: 900800595 | I77: Provexpress SAS | J77: 900750483 | K77: Selecta Compañia De Cereales SAS | L77: 79672.36 | M77: 0 | N77: 0 | O77: 622112.36 | P77: Aprobado con notificación | Q77: Emitido | W77: X | X77: PAGA EN SISTEMA 11/02/2026
A78: Factura electrónica | B78: 5e7c663ebbf958b21af8337beaa15ac3ea8be7e53a20d10f6d1811cb2ec2d50d235b8b8b560a351b30ff6ba2a6e2d926 | C78: 104691 | D78: =C78-C79 -> -1 | E78: FVE | F78: 06-01-2026 | G78: 06-01-2026 09:34:41 | H78: 900800595 | I78: Provexpress SAS | J78: 830072107 | K78: Edificio Reserva De La Alameda | L78: 0 | M78: 0 | N78: 0 | O78: 240000 | P78: Aprobado con notificación | Q78: Emitido | W78: x | X78: FACTURA PAGA EN EL SISTEMA 02/02/2026
A79: Factura electrónica | B79: ae0d79e45ee97ff93fc5a313e736643a98fc2a8c73a560d463001d64e01967566ff3e0117902d97d0d5bd46efc861e58 | C79: 104692 | D79: =C79-C80 -> -1 | E79: FVE | F79: 06-01-2026 | G79: 06-01-2026 09:34:39 | H79: 900800595 | I79: Provexpress SAS | J79: 900179369 | K79: Confipetrol SAS | L79: 357732 | M79: 0 | N79: 0 | O79: 2240532 | P79: Aprobado con notificación | Q79: Emitido | T79: X
A80: Factura electrónica | B80: 23793cde41314d491fd36f75e99c02c70805726b3027504822a71339d5eaa96babb051c034bc4eefd09c01225ec3e231 | C80: 104693 | D80: =C80-C81 -> -1 | E80: FVE | F80: 06-01-2026 | G80: 06-01-2026 09:34:52 | H80: 900800595 | I80: Provexpress SAS | J80: 901006430 | K80: Datalaft SAS | L80: 1911618.1 | M80: 0 | N80: 0 | O80: 11972766 | P80: Aprobado con notificación | Q80: Emitido
A81: Factura electrónica | B81: f3f0cc38c1efa6f39f27f678cabfa48597029e4a9f0d78156330452ab528ab449ff9917d5eb4e7f949aaac4e08c36ed0 | C81: 104694 | D81: =C81-C82 -> -1 | E81: FVE | F81: 06-01-2026 | G81: 06-01-2026 09:34:53 | H81: 900800595 | I81: Provexpress SAS | J81: 830110141 | K81: Risk Consulting Colombia SAS | L81: 1869452.2 | M81: 0 | N81: 0 | O81: 11708674 | P81: Aprobado con notificación | Q81: Emitido | T81: X
A82: Factura electrónica | B82: bbe3b1261ce048f3998bbe8c829ad27a0ec8b5f0576266c56f6b3ada4e9aa306f143e28944ee3f69a344e2d4ca9db72f | C82: 104695 | D82: =C82-C83 -> -1 | E82: FVE | F82: 06-01-2026 | G82: 06-01-2026 09:48:00 | H82: 900800595 | I82: Provexpress SAS | J82: 860040407 | K82: Plazoleta Bazzani SAS | L82: 280440 | M82: 0 | N82: 0 | O82: 1756440 | P82: Aprobado con notificación | Q82: Emitido | W82: x | X82: FACTURA PAGA EN EL SISTEMA 13/02/2026
A83: Factura electrónica | B83: 82ceaa408b8b1cf56dcd8331fdf91b7ec4a5b85b9d6f28478b86949aebbd741e5d9ecf4c33e6a5fcead94a07e055d2ec | C83: 104696 | D83: =C83-C84 -> -1 | E83: FVE | F83: 06-01-2026 | G83: 06-01-2026 09:48:33 | H83: 900800595 | I83: Provexpress SAS | J83: 901281572 | K83: Bold Co SAS | L83: 3629000 | M83: 0 | N83: 0 | O83: 22729000 | P83: Aprobado con notificación | Q83: Emitido | T83: x
A84: Factura electrónica | B84: 9780860da5c27148eac8d0be3d070c3680f7b7a02b8f94010829963a260733a71c6a7bd1bd3dbbac7fa452cd6319a1a0 | C84: 104697 | D84: =C84-C85 -> -1 | E84: FVE | F84: 06-01-2026 | G84: 06-01-2026 09:48:31 | H84: 900800595 | I84: Provexpress SAS | J84: 901281572 | K84: Bold Co SAS | L84: 3131200 | M84: 0 | N84: 0 | O84: 19611200 | P84: Aprobado con notificación | Q84: Emitido | T84: X
A85: Factura electrónica | B85: 801cc567e9f821b061f5194774c7b264b863ab5c900126d27e66f5776b12ce264b3b14aabf7c71a8356897367b9f1df8 | C85: 104698 | D85: =C85-C86 -> -1 | E85: FVE | F85: 06-01-2026 | G85: 06-01-2026 09:48:37 | H85: 900800595 | I85: Provexpress SAS | J85: 830015970 | K85: Campo Alto Acesalud SAS | L85: 68400 | M85: 0 | N85: 0 | O85: 428400 | P85: Aprobado con notificación | Q85: Emitido | W85: x | X85: FACTURA PAGA EN EL SISTEMA 09/02/2026
A86: Factura electrónica | B86: e4dddcb3776b44a54e05b5ffa5ce4dae5c6321be743153e21797d791d87718f8288553eb9f7f6055f8f01ecf41673dae | C86: 104699 | D86: =C86-C87 -> -1 | E86: FVE | F86: 06-01-2026 | G86: 06-01-2026 09:48:38 | H86: 900800595 | I86: Provexpress SAS | J86: 900006563 | K86: Latinoamericana Suministros Y Carga SAS | L86: 131745.91 | M86: 0 | N86: 0 | O86: 882182.91 | P86: Aprobado con notificación | Q86: Emitido | W86: x | X86: PAGA EN SISTEMA 24/02/2026
A87: Factura electrónica | B87: 20987e4a4a8b2de6feb61f22b9f3a84451b5b1acc3b18da035823b6682929d706dd47bd60eef33251e24c538f7619249 | C87: 104700 | D87: =C87-C88 -> -1 | E87: FVE | F87: 06-01-2026 | G87: 06-01-2026 10:14:01 | H87: 900800595 | I87: Provexpress SAS | J87: 900677304 | K87: Fundacion National Center For State Courts-Ncsc Colombia | L87: 0 | M87: 0 | N87: 0 | O87: 945000 | P87: Aprobado con notificación | Q87: Emitido | W87: X | X87: FACTURA PAGA EN EL SISTEMA 6/01/2026
A88: Factura electrónica | B88: b23d2df7b28bed6bfcab32640a76597ced9248e2ca042f993bd93f3364738e8001f7ba3b124a8eb73706fb58241598a8 | C88: 104701 | D88: =C88-C89 -> -1 | E88: FVE | F88: 06-01-2026 | G88: 06-01-2026 10:44:17 | H88: 900800595 | I88: Provexpress SAS | J88: 830084232 | K88: Fundacion Panamericana Para El Desarrollo Colombia Fupad Col | L88: 0 | M88: 0 | N88: 0 | O88: 3526050 | P88: Aprobado con notificación | Q88: Emitido | W88: X | X88: FACTURA PAGA EN EL SISTEMA 16/01/2026
A89: Factura electrónica | B89: 6bc317532db727c4edc5839f6e23a35c2885210d4c5314fff9f416c24407f61e13bd773766ebb66e979cbd1c4638b67d | C89: 104702 | D89: =C89-C90 -> -1 | E89: FVE | F89: 06-01-2026 | G89: 06-01-2026 10:44:22 | H89: 900800595 | I89: Provexpress SAS | J89: 860536003 | K89: Agencia De Aduanas Abc Repecev SAS Nivel 1 | L89: 334400 | M89: 0 | N89: 0 | O89: 2094400 | P89: Aprobado con notificación | Q89: Emitido | W89: x | X89: FACTURA PAGA EN EL SISTEMA 4/02/2026
A90: Factura electrónica | B90: fa9771a53f840a5f75be65d6d46c059b68b4901e8f3facfa06a3649a9025547e9a2a01836cd2fa8b4ce99b0a4231b33a | C90: 104703 | D90: =C90-C91 -> -1 | E90: FVE | F90: 06-01-2026 | G90: 06-01-2026 10:44:26 | H90: 900800595 | I90: Provexpress SAS | J90: 900356278 | K90: Digital Copy Soluciones Digitales SAS | L90: 628900 | M90: 0 | N90: 0 | O90: 3938900 | P90: Aprobado con notificación | Q90: Emitido | W90: x | X90: PAGA EN SISTEMA 03/02/2026
A91: Factura electrónica | B91: 62e45e8b9f9b95f3ae737b82c61eb7af5b6f57d2e8e0e6b7c27623e48d40533beee2f444e2b0f33362645dc9a08d48b5 | C91: 104704 | D91: =C91-C92 -> -1 | E91: FVE | F91: 06-01-2026 | G91: 06-01-2026 10:44:31 | H91: 900800595 | I91: Provexpress SAS | J91: 860010371 | K91: Corporacion Organizacion El Minuto De Dios-OMD- | L91: 1063116 | M91: 0 | N91: 0 | O91: 7002156 | P91: Aprobado con notificación | Q91: Emitido | W91: X | X91: PAGA EN SISTEMA 12/02/2026
A92: Factura electrónica | B92: 70efe99efe7c0f690b82c0748ccd2029f6b0e48ab8e33e73301e1259c9e543078305a2a4f06d035726035ddcca7ef3b9 | C92: 104705 | D92: =C92-C93 -> -1 | E92: FVE | F92: 06-01-2026 | G92: 06-01-2026 10:44:36 | H92: 900800595 | I92: Provexpress SAS | J92: 830075451 | K92: Pinturas Tito Pabon SAS | L92: 689643 | M92: 0 | N92: 0 | O92: 4319343 | P92: Aprobado con notificación | Q92: Emitido | W92: x | X92: PAGA EN SISTEMA 11/02/2026
A93: Factura electrónica | B93: 506453d8f92f56bbd1d43e9cc57ed15bf4114e476e42dadfaad79e2066b4aa088ccf9863607ecae60593fb7996224e63 | C93: 104706 | D93: =C93-C94 -> -1 | E93: FVE | F93: 06-01-2026 | G93: 06-01-2026 10:44:40 | H93: 900800595 | I93: Provexpress SAS | J93: 900134674 | K93: Soluciones Verticales SAS | L93: 0 | M93: 0 | N93: 0 | O93: 7045080 | P93: Aprobado con notificación | Q93: Emitido | V93: X
A94: Factura electrónica | B94: 7591fedfec0d7b61df72f007789c57b9079f2bbd043eabe03a72b9bfeef8c1fa8512d575c486f0c01178352ba52503f2 | C94: 104707 | D94: =C94-C95 -> -1 | E94: FVE | F94: 06-01-2026 | G94: 06-01-2026 10:44:45 | H94: 900800595 | I94: Provexpress SAS | J94: 830061776 | K94: Vehitotal SAS | L94: 247000 | M94: 0 | N94: 0 | O94: 1547000 | P94: Aprobado con notificación | Q94: Emitido | W94: X | X94: FACTURA PAGA EN EL SISTEMA 9/01/2026
A95: Factura electrónica | B95: aa9f175c218b0746c27c253b88131993ab1a4dd18a3599c02850113981af11131b066d9c8f46568ae8eedcb0a53febf1 | C95: 104708 | D95: =C95-C96 -> -1 | E95: FVE | F95: 06-01-2026 | G95: 06-01-2026 10:59:59 | H95: 900800595 | I95: Provexpress SAS | J95: 901380344 | K95: Buk Col SAS | L95: 10260000 | M95: 0 | N95: 0 | O95: 64260000 | P95: Aprobado con notificación | Q95: Emitido | W95: x | X95: FACTURA PAGA EN EL SISTEMA 30/01/2026
A96: Factura electrónica | B96: 7a43e78f787228ec227838d391cd41abed415c9a7fbab0e87c55512186275741561e8cbe96556c7b0a08714369b54062 | C96: 104709 | D96: =C96-C97 -> -1 | E96: FVE | F96: 06-01-2026 | G96: 06-01-2026 11:00:05 | H96: 900800595 | I96: Provexpress SAS | J96: 901380344 | K96: Buk Col SAS | L96: 966720 | M96: 0 | N96: 0 | O96: 6054720 | P96: Aprobado con notificación | Q96: Emitido | W96: x | X96: FACTURA PAGA EN EL SISTEMA 30/01/2026
A97: Factura electrónica | B97: 08b5d4893af47b82fa9a1769192e87f0f4a2d703ff1bc96c940dd3b1abd0dccdbf32a738132763057349e07371a6f12a | C97: 104710 | D97: =C97-C98 -> -1 | E97: FVE | F97: 06-01-2026 | G97: 06-01-2026 11:00:08 | H97: 900800595 | I97: Provexpress SAS | J97: 900463851 | K97: Duty Free Americas San Andres SAS | L97: 442890 | M97: 0 | N97: 0 | O97: 2773890 | P97: Aprobado con notificación | Q97: Emitido | W97: x | X97: FACTURA PAGA EN EL SISTEMA 12/02/2026
A98: Factura electrónica | B98: 9ed6407c3e864627377b4c233750dacc32f9e06412c9f3bf7ce601aac839824796f05c7474ae4190b6eec0314b03ae70 | C98: 104711 | D98: =C98-C99 -> -1 | E98: FVE | F98: 06-01-2026 | G98: 06-01-2026 11:00:13 | H98: 900800595 | I98: Provexpress SAS | J98: 901179692 | K98: FCL Impart SAS | L98: 91200 | M98: 0 | N98: 0 | O98: 571200 | P98: Aprobado con notificación | Q98: Emitido | W98: X | X98: FACTURA PAGA EN EL SISTEMA 13/01/2026
A99: Factura electrónica | B99: b1d4dcf96b0d3975e5ca887c771cb167155f34ef6d0ba55e11174d744057a38f75e88d37245748ff96467d2c56de1555 | C99: 104712 | D99: =C99-C100 -> -1 | E99: FVE | F99: 06-01-2026 | G99: 06-01-2026 11:00:17 | H99: 900800595 | I99: Provexpress SAS | J99: 900482537 | K99: Karcher SAS | L99: 665000 | M99: 0 | N99: 0 | O99: 4165000 | P99: Aprobado con notificación | Q99: Emitido | W99: X | X99: FACTURA PAGA EN EL SISTEMA 19/01/2026
A100: Factura electrónica | B100: 6aaee11bc88967f67c31c705a4da660aa997a97ea806051ed86de20745b217996604621060dd10f9c0aad74391057441 | C100: 104713 | D100: =C100-C101 -> -1 | E100: FVE | F100: 06-01-2026 | G100: 06-01-2026 11:00:22 | H100: 900800595 | I100: Provexpress SAS | J100: 900797309 | K100: Knauf Distribuidora SAS | L100: 351880 | M100: 0 | N100: 0 | O100: 2203880 | P100: Aprobado con notificación | Q100: Emitido | W100: x | X100: PAGA EN SISTEMA 24/02/2026
A101: Factura electrónica | B101: 7b30a72d41ac3712d8897698936fc1aa2ddc5f0886267cfde33baa8a90fb2d4794005899bdc4d1ce3bb5d12521eaa9db | C101: 104714 | D101: =C101-C102 -> -1 | E101: FVE | F101: 06-01-2026 | G101: 06-01-2026 11:00:26 | H101: 900800595 | I101: Provexpress SAS | J101: 890401802 | K101: Prosegur Vigilancia Y Seguridad Privada LTDA | L101: 129200 | M101: 0 | N101: 0 | O101: 809200 | P101: Aprobado con notificación | Q101: Emitido | S101: X
...

Sheet 1 ACUSE
A1: 1 ACUSE | B1: (Varios elementos)
A3: Nombre Receptor | B3: Folio | C3: Cuenta de 1 ACUSE | D3: Suma de Total
A4: Akila S A S | B4: 105537 | C4: 1 | D4: 756840
A5: Total Akila S A S | C5: 1 | D5: 756840
A6: Boticario Colombia S A S | B6: 105186 | C6: 1 | D6: 38679760
B7: 105242 | C7: 1 | D7: 6664000
B8: 105459 | C8: 1 | D8: 7590000
A9: Total Boticario Colombia S A S | C9: 3 | D9: 52933760
A10: Bulkmatic De Colombia SAS | B10: 105594 | C10: 1 | D10: 1035300
A11: Total Bulkmatic De Colombia SAS | C11: 1 | D11: 1035300
A12: Ceramica San Lorenzo Industrial De Colombia SA | B12: 105624 | C12: 1 | D12: 1723726
A13: Total Ceramica San Lorenzo Industrial De Colombia SA | C13: 1 | D13: 1723726
A14: Challenger SAS | B14: 105485 | C14: 1 | D14: 158270
B15: 105555 | C15: 1 | D15: 855729
A16: Total Challenger SAS | C16: 2 | D16: 1013999
A17: Clinica Colsanitas SA | B17: 104631 | C17: 1 | D17: 2890148.2
A18: Total Clinica Colsanitas SA | C18: 1 | D18: 2890148.2
A19: Coala Arquitectura Y Construccion SAS | B19: 105360 | C19: 1 | D19: 407607.83
A20: Total Coala Arquitectura Y Construccion SAS | C20: 1 | D20: 407607.83
A21: Comercializadora Internacional Milpa SA | B21: 105260 | C21: 1 | D21: 8949058.2
B22: 105465 | C22: 1 | D22: 2034031.3
B23: 105584 | C23: 1 | D23: 2490848.5
A24: Total Comercializadora Internacional Milpa SA | C24: 3 | D24: 13473938
A25: Creative Colors SA | B25: 105616 | C25: 1 | D25: 1999200
A26: Total Creative Colors SA | C26: 1 | D26: 1999200
A27: Distribuidora Y Editora Richmond SAS | B27: 104625 | C27: 1 | D27: 19962970
B28: 105189 | C28: 1 | D28: 21122500
B29: 105322 | C29: 1 | D29: 11529841
B30: 105341 | C30: 1 | D30: 6943846.3
A31: Total Distribuidora Y Editora Richmond SAS | C31: 4 | D31: 59559158
A32: Don Maiz SAS | B32: 104878 | C32: 1 | D32: 2543726.6
A33: Total Don Maiz SAS | C33: 1 | D33: 2543726.6
A34: Editorial Santillana SAS | B34: 105238 | C34: 1 | D34: 19876242
B35: 105253 | C35: 1 | D35: 27948158
B36: 105311 | C36: 1 | D36: 38798212
B37: 105345 | C37: 1 | D37: 87650.64
B38: 105356 | C38: 1 | D38: 5301594
A39: Total Editorial Santillana SAS | C39: 5 | D39: 92011856
A40: Educactiva SAS | B40: 104626 | C40: 1 | D40: 39925940
B41: 104745 | C41: 1 | D41: 3841320
B42: 104808 | C42: 1 | D42: 1276777.2
B43: 104951 | C43: 1 | D43: 60818713
B44: 105015 | C44: 1 | D44: 3002762.7
B45: 105190 | C45: 1 | D45: 21122500
B46: 105219 | C46: 1 | D46: 90946336
B47: 105312 | C47: 1 | D47: 35285879
B48: 105344 | C48: 1 | D48: 13313087
B49: 105357 | C49: 1 | D49: 13023736
A50: Total Educactiva SAS | C50: 10 | D50: 2.8255705e+08
A51: Flores De Serrezuela SAS | B51: 104877 | C51: 1 | D51: 738276
B52: 105340 | C52: 1 | D52: 359682.05
A53: Total Flores De Serrezuela SAS | C53: 2 | D53: 1097958.1
A54: Flores Tiba SA | B54: 105398 | C54: 1 | D54: 218781.5
B55: 105399 | C55: 1 | D55: 6902
B56: 105400 | C56: 1 | D56: 6902000
A57: Total Flores Tiba SA | C57: 3 | D57: 7127683.5
A58: Fresenius Medical Care Andina SAS | B58: 105130 | C58: 1 | D58: 207476.5
A59: Total Fresenius Medical Care Andina SAS | C59: 1 | D59: 207476.5
A60: Fresenius Medical Care SAS | B60: 104967 | C60: 1 | D60: 379015
B61: 105407 | C61: 1 | D61: 70574.14
B62: 105508 | C62: 1 | D62: 513187.5
A63: Total Fresenius Medical Care SAS | C63: 3 | D63: 962776.64
A64: Grivan Ingenieria SA | B64: 105221 | C64: 1 | D64: 158865
A65: Total Grivan Ingenieria SA | C65: 1 | D65: 158865
A66: IA4 SAS | B66: 104919 | C66: 1 | D66: 4078846.4
B67: 105212 | C67: 1 | D67: 2627951
A68: Total IA4 SAS | C68: 2 | D68: 6706797.4
A69: Industrias Ivor SA Casa Inglesa | B69: 105275 | C69: 1 | D69: 3282020
A70: Total Industrias Ivor SA Casa Inglesa | C70: 1 | D70: 3282020
A71: IRCC SAS Industria De Restaurantes Casuales SAS | B71: 105119 | C71: 1 | D71: 898450
B72: 105128 | C72: 1 | D72: 11942840
B73: 105177 | C73: 1 | D73: 7461300
B74: 105381 | C74: 1 | D74: 1347556
A75: Total IRCC SAS Industria De Restaurantes Casuales SAS | C75: 4 | D75: 21650146
A76: Kaeser Compresores De Colombia SAS | B76: 105105 | C76: 1 | D76: 2954460.3
B77: 105182 | C77: 1 | D77: 3592507.7
B78: 105468 | C78: 1 | D78: 735064.05
B79: 105469 | C79: 1 | D79: 9368493.8
B80: 105470 | C80: 1 | D80: 1430475.2
B81: 105471 | C81: 1 | D81: 1352012.6
B82: 105472 | C82: 1 | D82: 555083.2
B83: 105473 | C83: 1 | D83: 1208684.1
A84: Total Kaeser Compresores De Colombia SAS | C84: 8 | D84: 21196781
A85: Keralty SAS | B85: 104629 | C85: 1 | D85: 339796.17
A86: Total Keralty SAS | C86: 1 | D86: 339796.17
A87: Lamitech SAS | B87: 105632 | C87: 1 | D87: 993650
A88: Total Lamitech SAS | C88: 1 | D88: 993650
A89: Logytech Mobile SAS | B89: 104949 | C89: 1 | D89: 7694540
B90: 105638 | C90: 1 | D90: 5658603.5
A91: Total Logytech Mobile SAS | C91: 2 | D91: 13353144
A92: Securitas Colombia SA | B92: 104779 | C92: 1 | D92: 5071920
B93: 104815 | C93: 1 | D93: 15676540
B94: 105235 | C94: 1 | D94: 99960
A95: Total Securitas Colombia SA | C95: 3 | D95: 20848420
A96: Thomas Processing & System SAS | B96: 105409 | C96: 1 | D96: 2156280
B97: 105410 | C97: 1 | D97: 1120980
B98: 105411 | C98: 1 | D98: 9639000
B99: 105484 | C99: 1 | D99: 724710
B100: 105502 | C100: 1 | D100: 2786980
B101: 105565 | C101: 1 | D101: 17365670
...

Sheet 2 ACUSES
A1: 2 ACUSE | B1: (Varios elementos)
A3: Nombre Receptor | B3: Folio | C3: Cuenta de 2 ACUSE | D3: Suma de Total
A4: Administradora Clinica La Colina S A S | B4: 104983 | C4: 1 | D4: 286599.6
A5: Total Administradora Clinica La Colina S A S | C5: 1 | D5: 286599.6
A6: Centros Medicos Colsanitas S A S | B6: 105193 | C6: 1 | D6: 1497215.2
B7: 105436 | C7: 1 | D7: 245996.8
A8: Total Centros Medicos Colsanitas S A S | C8: 2 | D8: 1743212
A9: Ceramica San Lorenzo Industrial De Colombia SA | B9: 104875 | C9: 1 | D9: 418180
A10: Total Ceramica San Lorenzo Industrial De Colombia SA | C10: 1 | D10: 418180
A11: Creative Colors SA | B11: 105479 | C11: 1 | D11: 82110
A12: Total Creative Colors SA | C12: 1 | D12: 82110
A13: Don Maiz SAS | B13: 104874 | C13: 1 | D13: 2013361
B14: 105259 | C14: 1 | D14: 6972388.5
A15: Total Don Maiz SAS | C15: 2 | D15: 8985749.5
A16: Esmeraldas De Los Andes SAS | B16: 105141 | C16: 1 | D16: 4069800
A17: Total Esmeraldas De Los Andes SAS | C17: 1 | D17: 4069800
A18: Esmeraldas Mining Services SAS | B18: 104868 | C18: 1 | D18: 877644.04
B19: 105064 | C19: 1 | D19: 2727475.2
B20: 105065 | C20: 1 | D20: 2727475.2
B21: 105066 | C21: 1 | D21: 4091212.9
A22: Total Esmeraldas Mining Services SAS | C22: 4 | D22: 10423807
A23: Industria Nacional De Gaseosas SA | B23: 105179 | C23: 1 | D23: 23819654
B24: 105180 | C24: 1 | D24: 1.0088126e+08
B25: 105181 | C25: 1 | D25: 1.0088126e+08
A26: Total Industria Nacional De Gaseosas SA | C26: 3 | D26: 2.2558217e+08
A27: Prosegur Vigilancia Y Seguridad Privada LTDA | B27: 104714 | C27: 1 | D27: 809200
B28: 104715 | C28: 1 | D28: 5057500
B29: 104716 | C29: 1 | D29: 85680
B30: 104717 | C30: 1 | D30: 2796500
A31: Total Prosegur Vigilancia Y Seguridad Privada LTDA | C31: 4 | D31: 8748880
A32: Salitre Plaza Centro Comercial Propiedad Horizontal | B32: 105611 | C32: 1 | D32: 218971.9
A33: Total Salitre Plaza Centro Comercial Propiedad Horizontal | C33: 1 | D33: 218971.9
A34: The Muzo Foundation | B34: 105331 | C34: 1 | D34: 4536875
B35: 105494 | C35: 1 | D35: 141610
A36: Total The Muzo Foundation | C36: 2 | D36: 4678485
A37: Mercantil Colpatria SA | B37: 105290 | C37: 1 | D37: 884029
A38: Total Mercantil Colpatria SA | C38: 1 | D38: 884029
A39: Estudios Tecnicos SAS | B39: 105071 | C39: 1 | D39: 9418160.5
A40: Total Estudios Tecnicos SAS | C40: 1 | D40: 9418160.5
A41: Metaza SAS | B41: 105633 | C41: 1 | D41: 19759534
A42: Total Metaza SAS | C42: 1 | D42: 19759534
A43: Total general | C43: 25 | D43: 2.9529969e+08

Sheet SIN ACUSES
A1: SIN ACUSE | B1: (Varios elementos)
A3: Etiquetas de fila | B3: Cuenta de SIN ACUSE | C3: Suma de Total
A4: 24K Global Logistics SAS | B4: 1 | C4: 3837750
A5: 104781 | B5: 1 | C5: 3837750
A6: ACI Proyectos SAS | B6: 2 | C6: 938838.6
A7: 105067 | B7: 1 | C7: 391438.6
A8: 105455 | B8: 1 | C8: 547400
A9: Agropecuaria La Trinidad Dos SAS | B9: 1 | C9: 1003067.7
A10: 105640 | B10: 1 | C10: 1003067.7
A11: Ajecolombia SAS | B11: 1 | C11: 1487500
A12: 105644 | B12: 1 | C12: 1487500
A13: Aldeas Infantiles SOS Colombia | B13: 1 | C13: 12155850
A14: 105642 | B14: 1 | C14: 12155850
A15: Aquia SAS | B15: 1 | C15: 1428000
... A137: Plasdecor SAS | B137: 2 | C137: 2036350
A138: 105197 | B138: 1 | C138: 1721000
A139: 105589 | B139: 1 | C139: 315350
A140: Thomas Seguridad Integral Ltda | B140: 1 | C140: 1147452.7
A141: 104785 | B141: 1 | C141: 1147452.7
A142: C I Conquers World Trade SAS | B142: 2 | C142: 1203915.3
A143: 104791 | B143: 1 | C143: 1024760.8
A144: 104839 | B144: 1 | C144: 179154.5
A145: Alto Colombia SAS | B145: 2 | C145: 737697.06
A146: 104807 | B146: 1 | C146: 344350
A147: 105220 | B147: 1 | C147: 393347.06
A148: Compañia De La Hacienda De Misiones SA | B148: 1 | C148: 110908
A149: 104858 | B149: 1 | C149: 110908
A150: Power Systems Services Global SAS | B150: 4 | C150: 3078782.5
... A163: Idemia Identity & Security Sucursal Colombia | B163: 1 | C163: 3120890.7
A164: 105021 | B164: 1 | C164: 3120890.7
A165: Clinica Nuestra Señora De La Paz | B165: 1 | C165: 13276259
A166: 105037 | B166: 1 | C166: 13276259
A167: Industrial Hotelera Y Alimentos SAS Dialimentos SAS | B167: 1 | C167: 328440
A168: 105646 | B168: 1 | C168: 328440
A169: Juan Camilo Velasquez Graciano | B169: 1 | C169: 87661.35
A170: 105474 | B170: 1 | C170: 87661.35
A171: Hospitecnica SAS | B171: 1 | C171: 392938
A172: 105094 | B172: 1 | C172: 392938
A173: Hupecol Operating Co LLC | B173: 1 | C173: 322490
A174: 105099 | B174: 1 | C174: 322490
A175: Interservice SA | B175: 1 | C175: 4998000
A176: 105101 | B176: 1 | C176: 4998000
... A257: Total general | B257: 148 | C257: 3.8742962e+08

Sheet 3 ACUSES
A1: 3 ACUSE | B1: X
A3: Nombre Receptor | B3: Folio | C3: Cuenta de 3 ACUSE | D3: Suma de Total
A4: Adecco Colombia S A | B4: 104934 | C4: 1 | D4: 2353820
A5: Total Adecco Colombia S A | C5: 1 | D5: 2353820
A6: Aei Arquitectura E Interiores SAS | B6: 105250 | C6: 1 | D6: 1999200
A7: Total Aei Arquitectura E Interiores SAS | C7: 1 | D7: 1999200
A8: Applus Norcontrol Colombia Limitada | B8: 104995 | C8: 1 | D8: 293820
A9: Total Applus Norcontrol Colombia Limitada | C9: 1 | D9: 293820
A10: Aquia SAS | B10: 105333 | C10: 1 | D10: 19800
A11: Total Aquia SAS | C11: 1 | D11: 19800
A12: Atlantic Quantum Innovations S A S | B12: 105406 | C12: 1 | D12: 857588.97
B13: 105426 | C13: 1 | D13: 3732696.8
A14: Total Atlantic Quantum Innovations S A S | C14: 2 | D14: 4590285.8
A15: Axure Technologies SA | B15: 104989 | C15: 1 | D15: 6907892.9
B16: 105277 | C16: 1 | D16: 4012680
B17: 105278 | C17: 1 | D17: 2319072
B18: 105513 | C18: 1 | D18: 6425762
B19: 105514 | C19: 1 | D19: 4679400
A20: Total Axure Technologies SA | C20: 5 | D20: 24344807
A21: Bold Co SAS | B21: 104696 | C21: 1 | D21: 22729000
B22: 104697 | C22: 1 | D22: 19611200
A23: Total Bold Co SAS | C23: 2 | D23: 42340200
A24: BR Group SA | B24: 105034 | C24: 1 | D24: 2015793.8
A25: Total BR Group SA | C25: 1 | D25: 2015793.8
A26: Caja Colombiana De Subsidio Familiar Colsubsidio | B26: 105456 | C26: 1 | D26: 788970
B27: 105457 | C27: 1 | D27: 222649
B28: 105572 | C28: 1 | D28: 195914.46
B29: 105579 | C29: 1 | D29: 51765
A30: Total Caja Colombiana De Subsidio Familiar Colsubsidio | C30: 4 | D30: 1259298.5
A31: Caja De Compensacion Familiar Cafam | B31: 105031 | C31: 1 | D31: 23458076
A32: Total Caja De Compensacion Familiar Cafam | C32: 1 | D32: 23458076
A33: Casa De La Valvula SAS | B33: 104956 | C33: 1 | D33: 3314999.7
A34: Total Casa De La Valvula SAS | C34: 1 | D34: 3314999.7
A35: Centros Medicos Colsanitas S A S | B35: 104646 | C35: 1 | D35: 6375620.2
B36: 104647 | C36: 1 | D36: 3187810.1
B37: 104750 | C37: 1 | D37: 163045.47
B38: 104794 | C38: 1 | D38: 3187810.1
B39: 104800 | C39: 1 | D39: 2337439.6
B40: 104801 | C40: 1 | D40: 2337439.6
B41: 104802 | C41: 1 | D41: 7012319
B42: 104998 | C42: 1 | D42: 2337439.6
B43: 104999 | C43: 1 | D43: 3187810.1
B44: 105435 | C44: 1 | D44: 491993.6
A45: Total Centros Medicos Colsanitas S A S | C45: 10 | D45: 30618727
A46: Clinica Colsanitas SA | B46: 104632 | C46: 1 | D46: 17453190
B47: 104633 | C47: 1 | D47: 1535483.2
B48: 104634 | C48: 1 | D48: 20067074
B49: 104635 | C49: 1 | D49: 6141932.7
B50: 104636 | C50: 1 | D50: 645233.47
B51: 104637 | C51: 1 | D51: 2337439.6
B52: 104638 | C52: 1 | D52: 2337439.6
B53: 104751 | C53: 1 | D53: 248531.5
B54: 104795 | C54: 1 | D54: 16362078
B55: 104796 | C55: 1 | D55: 5525249.7
B56: 104898 | C56: 1 | D56: 1405687.5
B57: 104899 | C57: 1 | D57: 57120
B58: 104900 | C58: 1 | D58: 737015.79
... B64: 105561 | C64: 1 | D64: 2337439.6
A65: Total Clinica Colsanitas SA | C65: 19 | D65: 84314959
A66: Clinicos Programas De Atencion Integral SAS IPS | B66: 104770 | C66: 1 | D66: 906899
A67: Total Clinicos Programas De Atencion Integral SAS IPS | C67: 1 | D67: 906899
A68: Colfondos SA Pensiones Y Cesantias | B68: 104972 | C68: 1 | D68: 899640
A69: Total Colfondos SA Pensiones Y Cesantias | C69: 1 | D69: 899640
A70: Colinagro SA | B70: 105264 | C70: 1 | D70: 7723100
B71: 105521 | C71: 1 | D71: 571200
A72: Total Colinagro SA | C72: 2 | D72: 8294300
A73: Colviseg Colombiana De Vigilancia Y Seguridad Ltda | B73: 105293 | C73: 1 | D73: 458150
A74: Total Colviseg Colombiana De Vigilancia Y Seguridad Ltda | C74: 1 | D74: 458150
A75: Compañia De Medicina Prepagada Colsanitas SA | B75: 104894 | C75: 1 | D75: 737015.79
B76: 104895 | C76: 1 | D76: 101879.47
B77: 104896 | C77: 1 | D77: 44616.67
B78: 104897 | C78: 1 | D78: 10188755
B79: 104997 | C79: 1 | D79: 2337439.6
B80: 105000 | C80: 1 | D80: 2337439.6
B81: 105437 | C81: 1 | D81: 245996.8
B82: 105438 | C82: 1 | D82: 245996.8
A83: Total Compañia De Medicina Prepagada Colsanitas SA | C83: 8 | D83: 16239140
A84: Consultec International Sucursal Colombia | B84: 105380 | C84: 1 | D84: 49087.5
A85: Total Consultec International Sucursal Colombia | C85: 1 | D85: 49087.5
A86: Creative Colors SA | B86: 105480 | C86: 1 | D86: 1695214.5
A87: Total Creative Colors SA | C87: 1 | D87: 1695214.5
A88: Doble A Ingenieria SAS | B88: 105150 | C88: 1 | D88: 119000
B89: 105300 | C89: 1 | D89: 1303137.5
A90: Total Doble A Ingenieria SAS | C90: 2 | D90: 1422137.5
A91: Ecologia Y Entorno SAS E.S.P Ecoentorno | B91: 104920 | C91: 1 | D91: 633389.4
A92: Total Ecologia Y Entorno SAS E.S.P Ecoentorno | C92: 1 | D92: 633389.4
A93: Editorial Santillana SAS | B93: 104627 | C93: 1 | D93: 19962970
B94: 104746 | C94: 1 | D94: 3841320
B95: 105192 | C95: 1 | D95: 21122500
A96: Total Editorial Santillana SAS | C96: 3 | D96: 44926790
A97: Eulen Colombia SA | B97: 104924 | C97: 1 | D97: 214200
A98: Total Eulen Colombia SA | C98: 1 | D98: 214200
A99: Farmatodo Colombia SAS | B99: 105244 | C99: 1 | D99: 89297600
A100: Total Farmatodo Colombia SAS | C100: 1 | D100: 89297600
A101: Ferricentros SAS | B101: 104742 | C101: 1 | D101: 2253069
B102: 104743 | C102: 1 | D102: 1836037
B103: 104744 | C103: 1 | D103: 650539.4
A104: Total Ferricentros SAS | C104: 3 | D104: 4739645.4
A105: Flores Tiba SA | B105: 105251 | C105: 1 | D105: 6720000
A106: Total Flores Tiba SA | C106: 1 | D106: 6720000
...

Sheet RECHAZADAS 
A1: RECHAZADA | B1: (Todas)
A3: Etiquetas de fila | B3: Cuenta de RECHAZADA | C3: Suma de Total
A4: 24K Global Logistics SAS | C4: 3837750
A5: 104781 | C5: 3837750
A6: Acciones Y Valores SA Comisionista De Bolsa | C6: 1112310.9
A7: 105269 | C7: 59500
A8: 105270 | C8: 126140
A9: 105271 | C9: 149464
A10: 105446 | C10: 777206.85
A11: ACI Proyectos SAS | C11: 938838.6
A12: 105067 | C12: 391438.6
A13: 105455 | C13: 547400
A14: Adecco Colombia S A | C14: 2635850
A15: 104932 | C15: 110670
... A26: 104983 | C26: 286599.6
A27: Aecsa SAS | B27: 1 | C27: 7370860
A28: 105383 | B28: 1 | C28: 7370860
A29: Aei Arquitectura E Interiores SAS | C29: 1999200
A30: 105250 | C30: 1999200
A31: Agroindustrial De Palma Aceitera SA Sucursal Colombia | C31: 1963500
A32: 104952 | C32: 678300
A33: 105226 | C33: 1285200
A34: Agropecuaria La Trinidad Dos SAS | C34: 1003067.7
A35: 105640 | C35: 1003067.7
A36: Ajecolombia SAS | C36: 1487500
A37: 105644 | C37: 1487500
A38: Akila S A S | C38: 756840
A39: 105537 | C39: 756840
A40: Aldeas Infantiles SOS Colombia | C40: 12155850
... A95: 104708 | C95: 64260000
A96: 104709 | C96: 6054720
A97: Bulkmatic De Colombia SAS | C97: 1035300
A98: 105594 | C98: 1035300
A99: Business And Quality Services SAS | C99: 891284.8
A100: 104689 | C100: 891284.8
A101: Caja Colombiana De Subsidio Familiar Colsubsidio | C101: 12074887
A102: 104922 | C102: 48694.8
A103: 104940 | C103: 4636979
A104: 105265 | C104: 212499.49
A105: 105266 | C105: 183855
A106: 105267 | C106: 163744
A107: 105298 | C107: 5177987.5
A108: 105299 | C108: 391828.92
... A235: 104909 | C235: 20804532
A236: 105355 | C236: 79532464
A237: Cooperativa Empresarial Multiactiva Popular | C237: 1366917.3
A238: 105234 | C238: 796074.3
A239: 105391 | C239: 570843
A240: Cooperativa Multiactiva De Trabajadores Empleados Y Pensionados De Exxon | C240: 1129706.3
A241: 105254 | C241: 1129706.3
A242: Cooperativa Multiactiva Familiar De La Superintendencia Financiera De Colombia | C242: 606900
A243: 105462 | C243: 606900
A244: Cooperativa Nacional De Droguistas Detallistas | C244: 264122880
A245: 104905 | C245: 72504320
A246: 105012 | C246: 155366400
A247: 105509 | C247: 36252160
A248: Coopervision Colombia SAS | C248: 2557895.5
... A318: 105261 | C318: 409925.25
A319: Editorial Santillana SAS | B319: 1 | C319: 1.5758514e+08
A320: 104627 | C320: 19962970
A321: 104746 | C321: 3841320
A322: 105192 | C322: 21122500
A323: 105238 | C323: 19876242
A324: 105253 | C324: 27948158
A325: 105311 | C325: 38798212
A326: 105342 | B326: 1 | C326: 20646495
A327: 105345 | C327: 87650.64
A328: 105356 | C328: 5301594
A329: Educactiva SAS | B329: 1 | C329: 3.0534607e+08
A330: 104626 | C330: 39925940
A331: 104745 | C331: 3841320
A332: 104808 | C332: 1276777.2
A333: 104904 | C333: 1547000
A334: 104951 | C334: 60818713
A335: 105015 | C335: 3002762.7
A336: 105190 | C336: 21122500
A337: 105219 | C337: 90946336
A338: 105312 | C338: 35285879
A339: 105344 | C339: 13313087
A340: 105357 | C340: 13023736
A341: 105354 | B341: 1 | C341: 21242014
A342: Endress+Hauser Colombia SAS | C342: 1833458
A343: 105248 | C343: 1833458
A344: Ensembleiq Inc | C344: 80920
A345: 105425 | C345: 80920
A346: Epiroc Colombia SAS | C346: 107100
A347: 104860 | C347: 107100
A348: Esenttia SA | C348: 13482700
A349: 104718 | C349: 13482700
A350: Esmeraldas De Los Andes SAS | C350: 4069800
A351: 105141 | C351: 4069800
A352: Esmeraldas Mining Services SAS | C352: 10423807
A353: 104868 | C353: 877644.04
... A385: 105631 | C385: 287980
A386: Flores Tiba SA | B386: 1 | C386: 20975367
A387: 105081 | B387: 1 | C387: 7127683.5
A388: 105251 | C388: 6720000
A389: 105398 | C389: 218781.5
A390: 105399 | C390: 6902
A391: 105400 | C391: 6902000
...

Sheet PAGAS EN SISTEMA
A1: YA PAGA EN SISTEMA | B1: (Todas)
A3: Etiquetas de fila | B3: Cuenta de YA PAGA EN SISTEMA | C3: Suma de Total
A4: 24K Global Logistics SAS | C4: 3837750
A5: 104781 | C5: 3837750
A6: Acciones Y Valores SA Comisionista De Bolsa | B6: 4 | C6: 1112310.9
A7: 105269 | B7: 1 | C7: 59500
A8: 105270 | B8: 1 | C8: 126140
A9: 105271 | B9: 1 | C9: 149464
A10: 105446 | B10: 1 | C10: 777206.85
A11: ACI Proyectos SAS | C11: 938838.6
A12: 105067 | C12: 391438.6
A13: 105455 | C13: 547400
A14: Adecco Colombia S A | B14: 2 | C14: 2635850
A15: 104932 | B15: 1 | C15: 110670
A16: 104933 | B16: 1 | C16: 171360
A17: 104934 | C17: 2353820
A18: Adecco Servicios Colombia S A | B18: 6 | C18: 76250440
A19: 104927 | B19: 1 | C19: 15500940
A20: 104928 | B20: 1 | C20: 387940
A21: 104929 | B21: 1 | C21: 5831000
A22: 104930 | B22: 1 | C22: 110670
A23: 104931 | B23: 1 | C23: 49751520
A24: 105160 | B24: 1 | C24: 4668370
A25: Administradora Clinica La Colina S A S | C25: 286599.6
A26: 104983 | C26: 286599.6
A27: Aecsa SAS | C27: 7370860
A28: 105383 | C28: 7370860
A29: Aei Arquitectura E Interiores SAS | C29: 1999200
A30: 105250 | C30: 1999200
A31: Agroindustrial De Palma Aceitera SA Sucursal Colombia | B31: 2 | C31: 1963500
A32: 104952 | B32: 1 | C32: 678300
A33: 105226 | B33: 1 | C33: 1285200
A34: Agropecuaria La Trinidad Dos SAS | C34: 1003067.7
A35: 105640 | C35: 1003067.7
A36: Ajecolombia SAS | C36: 1487500
A37: 105644 | C37: 1487500
A38: Akila S A S | C38: 756840
A39: 105537 | C39: 756840
A40: Aldeas Infantiles SOS Colombia | C40: 12155850
A41: 105642 | C41: 12155850
A42: Angie Tatiana Parra Duran | B42: 1 | C42: 183170.81
A43: 105401 | B43: 1 | C43: 183170.81
A44: Applus Norcontrol Colombia Limitada | C44: 293820
A45: 104995 | C45: 293820
A46: Aquia SAS | C46: 1447800
A47: 105255 | C47: 1428000
A48: 105333 | C48: 19800
A49: Armirene Colombia SAS | B49: 2 | C49: 431970
A50: 105377 | B50: 1 | C50: 42840
A51: 105477 | B51: 1 | C51: 389130
A52: Astaf Auditores Y Consultores Contables SAS | C52: 1071000
A53: 105257 | C53: 1071000
A54: Atlantic Quantum Innovations S A S | B54: 1 | C54: 8322982.6
A55: 104652 | B55: 1 | C55: 3732696.8
A56: 105406 | C56: 857588.97
A57: 105426 | C57: 3732696.8
A58: Autogermana SAS | B58: 2 | C58: 2331995.4
A59: 104851 | B59: 1 | C59: 497146.3
A60: 105487 | B60: 1 | C60: 1834849.1
A61: Automundial SA | B61: 4 | C61: 527170
A62: 105326 | B62: 1 | C62: 21420
A63: 105329 | B63: 1 | C63: 113050
A64: 105574 | B64: 1 | C64: 196350
A65: 105575 | B65: 1 | C65: 196350
A66: Axa Colpatria Seguros SA | B66: 1 | C66: 12173700
A67: 105296 | B67: 1 | C67: 12173700
A68: Axure Technologies SA | C68: 24344807
A69: 104989 | C69: 6907892.9
A70: 105277 | C70: 4012680
A71: 105278 | C71: 2319072
A72: 105513 | C72: 6425762
A73: 105514 | C73: 4679400
A74: Bancolombia SA | B74: 1 | C74: 28838460
A75: 105027 | B75: 1 | C75: 28838460
A76: Bmi Colombia Compañia De Seguros De Vida SA | B76: 1 | C76: 2667435.4
A77: 105653 | B77: 1 | C77: 2667435.4
A78: Bogota Movil Operacion Sur SAS | B78: 2 | C78: 4340950
A79: 104729 | C79: 2550000
A80: 105087 | B80: 1 | C80: 380800
A81: 105145 | B81: 1 | C81: 1410150
A82: Bold Co SAS | C82: 42340200
A83: 104696 | C83: 22729000
A84: 104697 | C84: 19611200
A85: Boticario Colombia S A S | C85: 52933760
A86: 105186 | C86: 38679760
A87: 105242 | C87: 6664000
A88: 105459 | C88: 7590000
A89: BR Group SA | C89: 2015793.8
A90: 105034 | C90: 2015793.8
A91: Brink´S Incorporated Sucursal Colombia | B91: 2 | C91: 2025859.8
A92: 105649 | B92: 1 | C92: 1788629.8
A93: 105650 | B93: 1 | C93: 237230
A94: Buk Col SAS | B94: 2 | C94: 70314720
A95: 104708 | B95: 1 | C95: 64260000
A96: 104709 | B96: 1 | C96: 6054720
A97: Bulkmatic De Colombia SAS | C97: 1035300
A98: 105594 | C98: 1035300
A99: Business And Quality Services SAS | C99: 891284.8
A100: 104689 | C100: 891284.8
A101: Caja Colombiana De Subsidio Familiar Colsubsidio | B101: 7 | C101: 12074887
...
