Workbook

Sheet ACUSES FEBRERO 2026
A1: CONCEPTOS | B1: CANTIDAD | C1: VALOR TOTAL
A2: SIN ACUSE | B2: =GETPIVOTDATA("Cuenta de SIN ACUSE",'SIN ACUSE'!$A$3) -> 837 | C2: =GETPIVOTDATA("Suma de Total",'SIN ACUSE'!$A$3) -> 5.0649327e+09
A3: 1 ACUSE | B3: =GETPIVOTDATA("Cuenta de 1 ACUSE",'1 ACUSE'!$A$3) -> 428 | C3: =GETPIVOTDATA("Suma de Total",'1 ACUSE'!$A$3) -> 3.1963031e+09
A4: 2 ACUSES | B4: =GETPIVOTDATA("Cuenta de 2 ACUSE",'2 ACUSES'!$A$3) -> 69 | C4: =GETPIVOTDATA("Suma de Total",'2 ACUSES'!$A$3) -> 2.0992611e+08
A5: 3 ACUSES | B5: =GETPIVOTDATA("Cuenta de 3 ACUSE",'3 ACUSES'!$A$3) -> 367 | C5: =GETPIVOTDATA("Suma de Total",'3 ACUSES'!$A$3) -> 1.8084457e+09
A6: RECHAZADAS | B6: =GETPIVOTDATA("Cuenta de RECHAZADA",RECHAZADAS!$A$3) -> 49 | C6: =GETPIVOTDATA("Suma de Total",RECHAZADAS!$A$3) -> 1.3613464e+09
A7: PAGAS EN SISTEMA | B7: =GETPIVOTDATA("Cuenta de YA PAGA EN SISTEMA",'PAGAS EN SISTEMA'!$A$1) -> 192 | C7: =GETPIVOTDATA("Suma de Total",'PAGAS EN SISTEMA'!$A$3) -> 1.37082e+09
B8: =SUM(B2:B7) -> 1942 | C8: =SUM(C2:C7) -> 1.3011774e+10
A11: Tipo de documento | B11: CUFE/CUDE | C11: Folio | D11: Columna1 | E11: Prefijo | F11: Fecha Emisión | G11: Fecha Recepción | H11: NIT Emisor | I11: Nombre Emisor | J11: NIT Receptor | K11: Nombre Receptor | L11: IVA | M11: ICA | N11: IPC | O11: Total | P11: Estado | Q11: Grupo | R11: 1 ACUSE | S11: 2 ACUSE | T11: 3 ACUSE | U11: RECHAZADA | V11: SIN ACUSE | W11: YA PAGA EN SISTEMA | X11: OBSERVACIONES
A12: Factura electrónica | B12: 9e8f28c8532435a346538ba8112c8e9068f13434c11d8c912887c24408c7f4329064f57b5ec8611e6d4110c3c9add36c | C12: 105658 | D12: =C12-C13 -> -1 | E12: FVE | F12: 02-02-2026 | G12: 02-02-2026 10:36:58 | H12: 900800595 | I12: Provexpress SAS | J12: 800066001 | K12: Centro Medico Oftalmologico Y Laboratorio Clinico Andrade Narvaez Sociedad Por Acciones Simplificada | L12: 2997725 | M12: 0 | N12: 0 | O12: 18775225 | P12: Aprobado con notificación | Q12: Emitido | T12: X
A13: Factura electrónica | B13: 707f3324c2985d0956872bed06d68c59cbbcc2638add454dd8e804470260abda9217c0fda5fab5326b848f047bdffde2 | C13: 105659 | D13: =C13-C14 -> -1 | E13: FVE | F13: 02-02-2026 | G13: 02-02-2026 10:37:00 | H13: 900800595 | I13: Provexpress SAS | J13: 902022742 | K13: Andetech SAS | L13: 5455447.6 | M13: 0 | N13: 0 | O13: 34168330 | P13: Aprobado con notificación | Q13: Emitido | V13: X
A14: Factura electrónica | B14: 12c3102ff5193eebafe188694748ffe8ea776ea1d0c9c2f7727e5e3dfa2298822f03257462a42aee8c124014adfa3eb0 | C14: 105660 | D14: =C14-C15 -> -1 | E14: FVE | F14: 02-02-2026 | G14: 02-02-2026 10:37:04 | H14: 900800595 | I14: Provexpress SAS | J14: 860007336 | K14: Caja Colombiana De Subsidio Familiar Colsubsidio | L14: 28044 | M14: 0 | N14: 0 | O14: 175644 | P14: Aprobado con notificación | Q14: Emitido | S14: X
A15: Factura electrónica | B15: 1b08143f21a456ff1082112ede1063a3f7d8c3ea4907763df913c754ea8ec578f79e3e9b5388356277e4c1383fae6589 | C15: 105661 | D15: =C15-C16 -> -1 | E15: FVE | F15: 02-02-2026 | G15: 02-02-2026 10:37:08 | H15: 900800595 | I15: Provexpress SAS | J15: 860007336 | K15: Caja Colombiana De Subsidio Familiar Colsubsidio | L15: 12312 | M15: 0 | N15: 0 | O15: 77112 | P15: Aprobado con notificación | Q15: Emitido | S15: X
A16: Factura electrónica | B16: 63b9538b5e0159ebbd1ffa6e1e357cc1d29dac576871d6010504b8a05e121ca2658b020aea59dc17ac247ae82ef86a66 | C16: 105662 | D16: =C16-C17 -> -1 | E16: FVE | F16: 02-02-2026 | G16: 02-02-2026 10:52:04 | H16: 900800595 | I16: Provexpress SAS | J16: 860007336 | K16: Caja Colombiana De Subsidio Familiar Colsubsidio | L16: 126817.02 | M16: 0 | N16: 0 | O16: 794275.02 | P16: Aprobado con notificación | Q16: Emitido | T16: X
A17: Factura electrónica | B17: 6f60d7737f6aba19c01eb2d54215e6eeb490a59ee0e03fd6806319a0e5c7fda7449b71e51bc932bd52cec1da7fee1a72 | C17: 105663 | D17: =C17-C18 -> -1 | E17: FVE | F17: 02-02-2026 | G17: 02-02-2026 10:52:08 | H17: 900800595 | I17: Provexpress SAS | J17: 860007336 | K17: Caja Colombiana De Subsidio Familiar Colsubsidio | L17: 264689.76 | M17: 0 | N17: 0 | O17: 1657793.8 | P17: Aprobado con notificación | Q17: Emitido | T17: X
A18: Factura electrónica | B18: e5f87f40776c53ce481b92ea82dc58f1ec8eead1822c293727d1b2f1e31cb4dff85f6352280730bf33387aadda0f535f | C18: 105664 | D18: =C18-C19 -> -1 | E18: FVE | F18: 02-02-2026 | G18: 02-02-2026 10:52:16 | H18: 900800595 | I18: Provexpress SAS | J18: 860007336 | K18: Caja Colombiana De Subsidio Familiar Colsubsidio | L18: 18667.5 | M18: 0 | N18: 0 | O18: 116917.5 | P18: Aprobado con notificación | Q18: Emitido | T18: X
A19: Factura electrónica | B19: 638230dc821469761880ec6e47a52c85efec3f32e1331ef28129bed38a92e26a3ea0ed9d233c60bb2eb786deeb537bb3 | C19: 105665 | D19: =C19-C20 -> -1 | E19: FVE | F19: 02-02-2026 | G19: 02-02-2026 10:52:18 | H19: 900800595 | I19: Provexpress SAS | J19: 901847883 | K19: IA4 SAS | L19: 242866.74 | M19: 0 | N19: 0 | O19: 1521112.7 | P19: Aprobado con notificación | Q19: Emitido | T19: X
A20: Factura electrónica | B20: d9d17494e29f3e4a96115842453834c51d6696c4b0465a2d0799d7b22eedf8e286403fd54eb786fa32b8f26d5db19d0a | C20: 105666 | D20: =C20-C21 -> -1 | E20: FVE | F20: 02-02-2026 | G20: 02-02-2026 10:52:23 | H20: 900800595 | I20: Provexpress SAS | J20: 901847883 | K20: IA4 SAS | L20: 59395.52 | M20: 0 | N20: 0 | O20: 372003.52 | P20: Aprobado con notificación | Q20: Emitido | T20: X
A21: Factura electrónica | B21: 24d00dded83330c157318855770d7f7e0ef64f063c7bf120b8e4ef2a27b3bd91eff26e3a5363aa4c4f793766ced0ba1a | C21: 105667 | D21: =C21-C22 -> -1 | E21: FVE | F21: 02-02-2026 | G21: 02-02-2026 10:52:29 | H21: 900800595 | I21: Provexpress SAS | J21: 901847883 | K21: IA4 SAS | L21: 122892 | M21: 0 | N21: 0 | O21: 769692 | P21: Aprobado con notificación | Q21: Emitido | T21: X
A22: Factura electrónica | B22: db47bd5edf1223fe8c65e9bf30fb984d67645639a792d0d5ab7a61bcb719ad28ad87c69d3126b3464535c3939f841da2 | C22: 105668 | D22: =C22-C23 -> -1 | E22: FVE | F22: 02-02-2026 | G22: 02-02-2026 10:52:32 | H22: 900800595 | I22: Provexpress SAS | J22: 901847883 | K22: IA4 SAS | L22: 1139155.6 | M22: 0 | N22: 0 | O22: 7134711.6 | P22: Aprobado con notificación | Q22: Emitido | T22: X
A23: Factura electrónica | B23: 8b1b5684580c86fcd3f2b01ce5f29672849fe794109e9086163afa03db77ae2a3e1e3041df9710f58b791aabf9930645 | C23: 105669 | D23: =C23-C24 -> -1 | E23: FVE | F23: 02-02-2026 | G23: 02-02-2026 10:52:38 | H23: 900800595 | I23: Provexpress SAS | J23: 900024398 | K23: Ecologistica SAS Empresa De Servicios Publicos Ecologistica SAS ESP | L23: 645400.17 | M23: 0 | N23: 0 | O23: 4042243.2 | P23: Aprobado con notificación | Q23: Emitido | T23: X
A24: Factura electrónica | B24: 3a78622c2995dc09ad913647615b08d5324b9c83768ff079309240371ae2deeeb21a41ee555d8e9895b3f2e3aa6852cf | C24: 105670 | D24: =C24-C25 -> -1 | E24: FVE | F24: 02-02-2026 | G24: 02-02-2026 10:52:42 | H24: 900800595 | I24: Provexpress SAS | J24: 900024398 | K24: Ecologistica SAS Empresa De Servicios Publicos Ecologistica SAS ESP | L24: 84091.72 | M24: 0 | N24: 0 | O24: 526679.72 | P24: Aprobado con notificación | Q24: Emitido | T24: X
A25: Factura electrónica | B25: ed59b92615a0b014d73fea5d6de691107185efccb62ab2ed00e640e9826c49ea69395192c59d31840915cd0c81b51606 | C25: 105671 | D25: =C25-C26 -> -1 | E25: FVE | F25: 02-02-2026 | G25: 02-02-2026 10:52:48 | H25: 900800595 | I25: Provexpress SAS | J25: 900916121 | K25: Industria Ambiental SAS | L25: 114001.52 | M25: 0 | N25: 0 | O25: 714009.52 | P25: Aprobado con notificación | Q25: Emitido | T25: X
A26: Factura electrónica | B26: 0837e3626c0ea760f585b2852d6becb00f7bd7a3117bdbc0e8114a6088f0d7f9b0e75124cf0fe4a7e8e2be70c297a445 | C26: 105672 | D26: =C26-C27 -> -1 | E26: FVE | F26: 02-02-2026 | G26: 02-02-2026 10:52:53 | H26: 900800595 | I26: Provexpress SAS | J26: 860525156 | K26: Valrex SAS | L26: 252995.45 | M26: 0 | N26: 0 | O26: 1584550.4 | P26: Aprobado con notificación | Q26: Emitido | T26: X
A27: Factura electrónica | B27: 689557710e31241b29ff0b29810eb5e91ba7f4e86b4521ea1bb000450e71d10287452debcac678fa701146a37671be05 | C27: 105673 | D27: =C27-C28 -> -1 | E27: FVE | F27: 02-02-2026 | G27: 02-02-2026 10:52:57 | H27: 900800595 | I27: Provexpress SAS | J27: 860068182 | K27: Credicorp Capital Colombia SA | L27: 2656777.6 | M27: 0 | N27: 0 | O27: 16639818 | P27: Aprobado con notificación | Q27: Emitido | T27: X
A28: Factura electrónica | B28: 840ead6acb50c9fdca1a66de9f36544e849caf077c067a0e0f590be01c86300a002f03259f0236f73a047d0d3ef79a7f | C28: 105674 | D28: =C28-C29 -> -1 | E28: FVE | F28: 02-02-2026 | G28: 02-02-2026 10:53:02 | H28: 900800595 | I28: Provexpress SAS | J28: 860005114 | K28: Messer Colombia SA | L28: 1039812.4 | M28: 0 | N28: 0 | O28: 6512509.4 | P28: Aprobado con notificación | Q28: Emitido | V28: X
A29: Factura electrónica | B29: 1546001ba61f10f718dd48045184e6b034610f9edbabf38cbc750495a97ef8d4d4d768dfdf2deb0eabe1880d66aac007 | C29: 105675 | D29: =C29-C30 -> -1 | E29: FVE | F29: 02-02-2026 | G29: 02-02-2026 10:53:08 | H29: 900800595 | I29: Provexpress SAS | J29: 900478755 | K29: Centak Export Zf SAS | L29: 64899.06 | M29: 0 | N29: 0 | O29: 406473.06 | P29: Aprobado con notificación | Q29: Emitido | R29: X
A30: Factura electrónica | B30: 6a0786df26cdfccae4892807c267eddf4dd74ca2b517df9d4c290650ce5c20fcf45c6368f5ca7e8a344cb29998494184 | C30: 105676 | D30: =C30-C31 -> -1 | E30: FVE | F30: 02-02-2026 | G30: 02-02-2026 11:08:15 | H30: 900800595 | I30: Provexpress SAS | J30: 900396295 | K30: Merquimia Internacional SAS | L30: 64940.1 | M30: 0 | N30: 0 | O30: 406730.1 | P30: Aprobado con notificación | Q30: Emitido | V30: X
A31: Factura electrónica | B31: 407027706781adf9445faa615550f3fdfece7ea9f36e8f20c5a30a79285702a645b6d0513fbbd9fe67fdae7746a2a352 | C31: 105677 | D31: =C31-C32 -> -1 | E31: FVE | F31: 02-02-2026 | G31: 02-02-2026 11:08:24 | H31: 900800595 | I31: Provexpress SAS | J31: 900319696 | K31: Concentrix Cvg Customer Management Colombia SAS | L31: 170240 | M31: 0 | N31: 0 | O31: 1066240 | P31: Aprobado con notificación | Q31: Emitido | T31: X
A32: Factura electrónica | B32: f3e26d4b1bcd0610159e712e6583bd00de33bb44b0f671daad83919f652c8bd2860d2a7cba15fb09408346a39c2a1a39 | C32: 105678 | D32: =C32-C33 -> -1 | E32: FVE | F32: 02-02-2026 | G32: 02-02-2026 11:23:32 | H32: 900800595 | I32: Provexpress SAS | J32: 800149384 | K32: Clinica Colsanitas SA | L32: 16546.72 | M32: 0 | N32: 0 | O32: 103634.72 | P32: Aprobado con notificación | Q32: Emitido | T32: X
A33: Factura electrónica | B33: 5ff121deada184b911a539ad62e8d0068abb3808b64bb52a19f6c67ac7cc47b4539541180fb0953dd5833c3525d48915 | C33: 105679 | D33: =C33-C34 -> -1 | E33: FVE | F33: 02-02-2026 | G33: 02-02-2026 11:23:35 | H33: 900800595 | I33: Provexpress SAS | J33: 800118776 | K33: Transportes Iceberg De Colombia SA | L33: 160710.36 | M33: 0 | N33: 0 | O33: 1006554.4 | P33: Aprobado con notificación | Q33: Emitido | V33: X
A34: Factura electrónica | B34: 0dbd479dd23ff38de826215780052c0f076049d0d6ebd7eb0f7a96133845c7d1978268de0c6e65e70ca5219f14dc4792 | C34: 105680 | D34: =C34-C35 -> -1 | E34: FVE | F34: 02-02-2026 | G34: 02-02-2026 11:23:40 | H34: 900800595 | I34: Provexpress SAS | J34: 860002183 | K34: Axa Colpatria Seguros De Vida SA | L34: 0 | M34: 0 | N34: 0 | O34: 7931301 | P34: Aprobado con notificación | Q34: Emitido | W34: X | X34: FACTURA PAGA EN EL SISTENMA 27/02/2026
A35: Factura electrónica | B35: 27c22922283a71f64b1932e8bbad5362ed84cb6e1e0082b06411a8e47108253a6a5c2facf77962a18ab22ada84a5cfaa | C35: 105681 | D35: =C35-C36 -> -1 | E35: FVE | F35: 02-02-2026 | G35: 02-02-2026 11:23:45 | H35: 900800595 | I35: Provexpress SAS | J35: 900342297 | K35: Comercializadora Arturo Calle SAS | L35: 133000 | M35: 0 | N35: 0 | O35: 833000 | P35: Aprobado con notificación | Q35: Emitido | T35: X
A36: Factura electrónica | B36: 4ccc65bb341a2509401e409cc6d7b4ea22967beecc2ade9ee1a54a91a1f437cfb302a6783d4e57d33348856ce6065656 | C36: 105682 | D36: =C36-C37 -> -1 | E36: FVE | F36: 02-02-2026 | G36: 02-02-2026 11:23:50 | H36: 900800595 | I36: Provexpress SAS | J36: 900342297 | K36: Comercializadora Arturo Calle SAS | L36: 35351.02 | M36: 0 | N36: 0 | O36: 221409.02 | P36: Aprobado con notificación | Q36: Emitido | T36: X
A37: Factura electrónica | B37: 5d86c7299e6cc22ffd8decd615bd620cb197df3f264ea089ebab9206bc64fca5ef00d19746f7159aded148ae01cdde7d | C37: 105683 | D37: =C37-C38 -> -1 | E37: FVE | F37: 02-02-2026 | G37: 02-02-2026 11:23:54 | H37: 900800595 | I37: Provexpress SAS | J37: 860516806 | K37: Permoda Ltda | L37: 232354.8 | M37: 0 | N37: 0 | O37: 1455274.8 | P37: Aprobado con notificación | Q37: Emitido | R37: X
A38: Factura electrónica | B38: 592150ecd90e6b1eeb467f5112942a5232c144343d3d9c22c2f9f453732f5f736c4e52383acee7975912b1806bf07b26 | C38: 105684 | D38: =C38-C39 -> -1 | E38: FVE | F38: 02-02-2026 | G38: 02-02-2026 11:23:59 | H38: 900800595 | I38: Provexpress SAS | J38: 900033883 | K38: Quimicos Integrales SAS | L38: 104500 | M38: 0 | N38: 0 | O38: 654500 | P38: Aprobado con notificación | Q38: Emitido | W38: X | X38: FACTURA PAGA EN EL SISTEMA 04/02/2026
A39: Factura electrónica | B39: 6b5214da75c4751860b35d87ae01932dda62c351cfc9f3a28422c487ab35ca4a93ede5a495f16710a89cbad71cf34586 | C39: 105685 | D39: =C39-C40 -> -1 | E39: FVE | F39: 02-02-2026 | G39: 02-02-2026 11:24:03 | H39: 900800595 | I39: Provexpress SAS | J39: 900475440 | K39: Sulzer Pumps Colombia SAS | L39: 26600 | M39: 0 | N39: 0 | O39: 166600 | P39: Aprobado con notificación | Q39: Emitido | T39: X
A40: Factura electrónica | B40: 1e13eb14028619fc90de9662e215f9ce12de5c8ce1e5b639541e568f58cf12633f2206e33eea93fa0eb94ccd8a2d49bd | C40: 105686 | D40: =C40-C41 -> -1 | E40: FVE | F40: 02-02-2026 | G40: 02-02-2026 11:24:08 | H40: 900800595 | I40: Provexpress SAS | J40: 860066789 | K40: Universidad El Bosque | L40: 1758450 | M40: 0 | N40: 0 | O40: 11013450 | P40: Aprobado con notificación | Q40: Emitido | T40: X
A41: Factura electrónica | B41: 74b25a619e301ca2af617ba0077e0d2df371884fefcfd8750f86b2e812d4e8580083abcaca65c5c18107d69980fcaca8 | C41: 105687 | D41: =C41-C42 -> -1 | E41: FVE | F41: 02-02-2026 | G41: 02-02-2026 11:24:16 | H41: 900800595 | I41: Provexpress SAS | J41: 901117560 | K41: Epiroc Colombia SAS | L41: 81962.2 | M41: 0 | N41: 0 | O41: 513342.2 | P41: Aprobado con notificación | Q41: Emitido | T41: X
A42: Factura electrónica | B42: 1201e487ebd2f98d4e1c72d96053e9f6f0b273e22b336244566e06bdf5d3997d2783e8cf1d6998c8f80f473333715013 | C42: 105688 | D42: =C42-C43 -> -1 | E42: FVE | F42: 02-02-2026 | G42: 02-02-2026 11:24:19 | H42: 900800595 | I42: Provexpress SAS | J42: 901117560 | K42: Epiroc Colombia SAS | L42: 155069.9 | M42: 0 | N42: 0 | O42: 1349079.9 | P42: Aprobado con notificación | Q42: Emitido | T42: X
A43: Factura electrónica | B43: e23c39840855391de9e9858ab8ac7800a4df58054bd581cd490203ba2c5893a4828e65fec205b2ff1fd56fd3207adc6b | C43: 105689 | D43: =C43-C44 -> -1 | E43: FVE | F43: 02-02-2026 | G43: 02-02-2026 11:24:22 | H43: 900800595 | I43: Provexpress SAS | J43: 830111156 | K43: Diseño Y Aplicaciones De Ingenieria Ltda | L43: 42919.48 | M43: 0 | N43: 0 | O43: 268811.48 | P43: Aprobado con notificación | Q43: Emitido | W43: X | X43: FACTURA PAGA EN EL SISTEMA 04/02/2026
A44: Factura electrónica | B44: 69df6faf4b9f17e4c8c3def77eae62718df14a767b8c4ee7857d3b9f92864cf81e360274c52ec4d032f2e8bb36f5b01f | C44: 105690 | D44: =C44-C45 -> -1 | E44: FVE | F44: 02-02-2026 | G44: 02-02-2026 11:24:26 | H44: 900800595 | I44: Provexpress SAS | J44: 900682841 | K44: Educactiva SAS | L44: 481788.89 | M44: 0 | N44: 0 | O44: 3017519.9 | P44: Aprobado con notificación | Q44: Emitido | R44: X
A45: Factura electrónica | B45: 18a307d259606ed358ee3a996f6c34c17ee94a5549679f69f491946df2610dded02b2c0892bdd731e48a565de9fcf1ea | C45: 105691 | D45: =C45-C46 -> -1 | E45: FVE | F45: 02-02-2026 | G45: 02-02-2026 11:24:31 | H45: 900800595 | I45: Provexpress SAS | J45: 830095970 | K45: Distribuidora Y Editora Richmond SAS | L45: 274708.27 | M45: 0 | N45: 0 | O45: 1720541.3 | P45: Aprobado con notificación | Q45: Emitido | V45: X
A46: Factura electrónica | B46: f746c7236a435b537639d20481902a39566d5be88f20d3ac263cc2c6acdea1482d1e10d6f03011e1712b2685bfc59097 | C46: 105692 | D46: =C46-C47 -> -1 | E46: FVE | F46: 02-02-2026 | G46: 02-02-2026 11:39:55 | H46: 900800595 | I46: Provexpress SAS | J46: 800024265 | K46: Editorial Santillana SAS | L46: 1699241.6 | M46: 0 | N46: 0 | O46: 10642619 | P46: Aprobado con notificación | Q46: Emitido | R46: X
A47: Factura electrónica | B47: 9cd87b991c3cd297c08a9bbf053ee5e1ca9133bb6f6c0712eb1f1c72ba3d0e40e34a2ac5c838a3aa834944f166b3c2ae | C47: 105693 | D47: =C47-C48 -> -1 | E47: FVE | F47: 02-02-2026 | G47: 02-02-2026 11:39:55 | H47: 900800595 | I47: Provexpress SAS | J47: 800024265 | K47: Editorial Santillana SAS | L47: 743268.6 | M47: 0 | N47: 0 | O47: 6651505.6 | P47: Aprobado con notificación | Q47: Emitido | U47: X
A48: Factura electrónica | B48: a2f5f23b97db6066f2fdfa576eb86895522544fdd8de3254b3fb83ca13ddbb10a5bdc244e591b873a8efcf186cbea7e6 | C48: 105694 | D48: =C48-C49 -> -1 | E48: FVE | F48: 02-02-2026 | G48: 02-02-2026 11:39:57 | H48: 900800595 | I48: Provexpress SAS | J48: 800024265 | K48: Editorial Santillana SAS | L48: 6296024.9 | M48: 0 | N48: 0 | O48: 39432998 | P48: Aprobado con notificación | Q48: Emitido | U48: X | X48: NC 5905
A49: Factura electrónica | B49: 8a3a5ac4aca5e0e02c347e8fdba64faacd5bbbaea39f8b57a31cdaef31f2e3e2d3bf6cac5d29272cdfb9fa8c4132d59e | C49: 105695 | D49: =C49-C50 -> -1 | E49: FVE | F49: 02-02-2026 | G49: 02-02-2026 11:39:59 | H49: 900800595 | I49: Provexpress SAS | J49: 800024265 | K49: Editorial Santillana SAS | L49: 11865835 | M49: 0 | N49: 0 | O49: 74317600 | P49: Aprobado con notificación | Q49: Emitido | U49: X | X49: NC 5904
A50: Factura electrónica | B50: 3a778bb9c17182fccca781f338cb12fc98e3b54b2c3487040b798643c8ed247b60561d9f79d494f5a5870b76d6825607 | C50: 105696 | D50: =C50-C51 -> -1 | E50: FVE | F50: 02-02-2026 | G50: 02-02-2026 11:40:01 | H50: 900800595 | I50: Provexpress SAS | J50: 800024265 | K50: Editorial Santillana SAS | L50: 7081318.6 | M50: 0 | N50: 0 | O50: 44351417 | P50: Aprobado con notificación | Q50: Emitido | U50: X
A51: Factura electrónica | B51: 5a0eb8f2e3cc78b5678333ae1e083bddbb09ef716e91e4d0541d15f832b8aec2fedeb7e6d910fb4ea44eec5da4832a99 | C51: 105697 | D51: =C51-C52 -> -1 | E51: FVE | F51: 02-02-2026 | G51: 02-02-2026 11:40:04 | H51: 900800595 | I51: Provexpress SAS | J51: 800024265 | K51: Editorial Santillana SAS | L51: 20751597 | M51: 0 | N51: 0 | O51: 1.2997053e+08 | P51: Aprobado con notificación | Q51: Emitido | U51: X | X51: NC 5906
A52: Factura electrónica | B52: 694949ffbd6d6a7682474f4b2405b04102fea3db7a9dcb8b52e0fa4fdff2b94dc3d3b4faacfcd7bb734db893af1e9d35 | C52: 105698 | D52: =C52-C53 -> -1 | E52: FVE | F52: 02-02-2026 | G52: 02-02-2026 11:40:06 | H52: 900800595 | I52: Provexpress SAS | J52: 800024265 | K52: Editorial Santillana SAS | L52: 0 | M52: 0 | N52: 0 | O52: 7666668 | P52: Aprobado con notificación | Q52: Emitido | R52: X
A53: Factura electrónica | B53: 4faf9de62db2ee16b404320b0046cd52cb17dd1d9b1d29b74558e7dbebdb35c43bfd26f8a5f111ec7c353a1f71029bcd | C53: 105699 | D53: =C53-C54 -> -1 | E53: FVE | F53: 02-02-2026 | G53: 02-02-2026 11:40:11 | H53: 900800595 | I53: Provexpress SAS | J53: 800024265 | K53: Editorial Santillana SAS | L53: 369560.45 | M53: 0 | N53: 0 | O53: 25314619 | P53: Aprobado con notificación | Q53: Emitido | R53: X
A54: Factura electrónica | B54: cceff4bdc8c689150fc265afcf68b480a4b3ef9870d077694d025807b4b3b4fe052983a631aec93af4d0b59875bf4d0a | C54: 105700 | D54: =C54-C55 -> -1 | E54: FVE | F54: 02-02-2026 | G54: 02-02-2026 11:40:16 | H54: 900800595 | I54: Provexpress SAS | J54: 800024265 | K54: Editorial Santillana SAS | L54: 0 | M54: 0 | N54: 0 | O54: 38333340 | P54: Aprobado con notificación | Q54: Emitido | R54: X
A55: Factura electrónica | B55: ef237c433cc5268f65732e4aa0dd830772944b6b0b87397ec1975bfb1b8c5e6bba3807680069e62f647faac563229163 | C55: 105701 | D55: =C55-C56 -> -1 | E55: FVE | F55: 02-02-2026 | G55: 02-02-2026 11:40:20 | H55: 900800595 | I55: Provexpress SAS | J55: 800024265 | K55: Editorial Santillana SAS | L55: 2956082.7 | M55: 0 | N55: 0 | O55: 22876309 | P55: Aprobado con notificación | Q55: Emitido | U55: X | X55: NC 5900
A56: Factura electrónica | B56: bc274c8b1201d4c733653c8b18d2604227e18aca778803f06f02f0f3733b0a568c8ec8a341c8500aaa199c9020d1f268 | C56: 105702 | D56: =C56-C57 -> -1 | E56: FVE | F56: 02-02-2026 | G56: 02-02-2026 11:40:25 | H56: 900800595 | I56: Provexpress SAS | J56: 800024265 | K56: Editorial Santillana SAS | L56: 1132238.5 | M56: 0 | N56: 0 | O56: 37035844 | P56: Aprobado con notificación | Q56: Emitido | R56: X
A57: Factura electrónica | B57: f889b915be5b6b2e00a1b3282a177ea3cdaadd6a63c6fa391298ca0df1b3f77f329dad236537ab296e05fba1ceefaa18 | C57: 105703 | D57: =C57-C58 -> -1 | E57: FVE | F57: 02-02-2026 | G57: 02-02-2026 11:55:31 | H57: 900800595 | I57: Provexpress SAS | J57: 800024265 | K57: Editorial Santillana SAS | L57: 3175339.9 | M57: 0 | N57: 0 | O57: 19887655 | P57: Aprobado con notificación | Q57: Emitido | U57: X | X57: NC 5892
A58: Factura electrónica | B58: 27e769dc56e3b50f7133c8f99c9425d0c6e76f8ddbb4d2cd737b67faceae647d835a9c2750344e3627e02c463bc1f271 | C58: 105704 | D58: =C58-C59 -> -1 | E58: FVE | F58: 02-02-2026 | G58: 02-02-2026 11:55:36 | H58: 900800595 | I58: Provexpress SAS | J58: 800024265 | K58: Editorial Santillana SAS | L58: 1342075.3 | M58: 0 | N58: 0 | O58: 8405629.3 | P58: Aprobado con notificación | Q58: Emitido | U58: X | X58: NC 5892
A59: Factura electrónica | B59: c82f8f700c8f4c89ed816fa95560069c98af11db89139e2829f16cf6bd91ff85d7a5a77e27962996cbeba5358a74dbc0 | C59: 105705 | D59: =C59-C60 -> -1 | E59: FVE | F59: 02-02-2026 | G59: 02-02-2026 11:55:41 | H59: 900800595 | I59: Provexpress SAS | J59: 800024265 | K59: Editorial Santillana SAS | L59: 5543406.8 | M59: 0 | N59: 0 | O59: 68656281 | P59: Aprobado con notificación | Q59: Emitido | R59: X
A60: Factura electrónica | B60: ce0b1aab2ef595483b8ba05c0d4677bec26a365efdb498fd122b128a2b78b594a3af1b01c56dd1da68605db0a81f2b8b | C60: 105706 | D60: =C60-C61 -> -1 | E60: FVE | F60: 02-02-2026 | G60: 02-02-2026 11:55:45 | H60: 900800595 | I60: Provexpress SAS | J60: 800024265 | K60: Editorial Santillana SAS | L60: 9352987.7 | M60: 0 | N60: 0 | O60: 58579239 | P60: Aprobado con notificación | Q60: Emitido | U60: X | X60: NC 5896
A61: Factura electrónica | B61: 568d22d35de471fc88a7003b7679f4b2509b320bbe4694d5c51acdc17b3b55c9e24f521e4a268d603109c30493877b39 | C61: 105707 | D61: =C61-C62 -> -1 | E61: FVE | F61: 02-02-2026 | G61: 02-02-2026 11:55:49 | H61: 900800595 | I61: Provexpress SAS | J61: 800024265 | K61: Editorial Santillana SAS | L61: 42204917 | M61: 0 | N61: 0 | O61: 2.6433606e+08 | P61: Aprobado con notificación | Q61: Emitido | U61: X | X61: NC 5901
A62: Factura electrónica | B62: c71aa9dee736e81df490328fb18c7d1b6336ef4c8175a7229bf415ac09ea09f31d492fba41408a1a2cc6177b1fed2c48 | C62: 105708 | D62: =C62-C63 -> -1 | E62: FVE | F62: 02-02-2026 | G62: 02-02-2026 11:55:54 | H62: 900800595 | I62: Provexpress SAS | J62: 800024265 | K62: Editorial Santillana SAS | L62: 5909989.9 | M62: 0 | N62: 0 | O62: 37015200 | P62: Aprobado con notificación | Q62: Emitido | U62: X | X62: NC 5897
A63: Factura electrónica | B63: 7483bb1cd002aff890863c19cb83050dbf3a6ff43af59adec42d8a15bb7e18f9b1cd8c8454b4a18e374d4a07aa874464 | C63: 105709 | D63: =C63-C64 -> -1 | E63: FVE | F63: 02-02-2026 | G63: 02-02-2026 11:55:58 | H63: 900800595 | I63: Provexpress SAS | J63: 800024265 | K63: Editorial Santillana SAS | L63: 1932806.2 | M63: 0 | N63: 0 | O63: 12105470 | P63: Aprobado con notificación | Q63: Emitido | U63: X | X63: NC 5895
A64: Factura electrónica | B64: a19e3825e9d07716cbd64a24f839eb92bc970b8afec6728286aa81db6eee7e17acdb0eb59d8bac39aab482061b506b17 | C64: 105710 | D64: =C64-C65 -> -1 | E64: FVE | F64: 02-02-2026 | G64: 02-02-2026 11:56:03 | H64: 900800595 | I64: Provexpress SAS | J64: 800024265 | K64: Editorial Santillana SAS | L64: 2161495.1 | M64: 0 | N64: 0 | O64: 13537785 | P64: Aprobado con notificación | Q64: Emitido | U64: X | X64: NC 5898
A65: Factura electrónica | B65: addf70e1518f1b81490acb74680929c53ac1cc39dbb0dcd7f3de9d49abe93183128b80d6935751ffd12e919299f1e82d | C65: 105711 | D65: =C65-C66 -> -1 | E65: FVE | F65: 02-02-2026 | G65: 02-02-2026 11:56:12 | H65: 900800595 | I65: Provexpress SAS | J65: 800024265 | K65: Editorial Santillana SAS | L65: 3733100.4 | M65: 0 | N65: 0 | O65: 47336561 | P65: Aprobado con notificación | Q65: Emitido | U65: X | X65: NC 5890
A66: Factura electrónica | B66: 742c6fec88cf4a427ad6745ee806c8b6994a2ee57f5a6f83814622bcf590ebe8b34b414e8236f1cf8ebb5ca3a9442650 | C66: 105712 | D66: =C66-C67 -> -1 | E66: FVE | F66: 02-02-2026 | G66: 02-02-2026 11:56:13 | H66: 900800595 | I66: Provexpress SAS | J66: 800024265 | K66: Editorial Santillana SAS | L66: 6484485.3 | M66: 0 | N66: 0 | O66: 40613355 | P66: Aprobado con notificación | Q66: Emitido | U66: X | X66: NC 5887
A67: Factura electrónica | B67: c1574c4df020f8b14c278f0a12a77925ae0d300e82645cf0da1dbf4fe81c49842c45038298897455d8b0a08e1294d998 | C67: 105713 | D67: =C67-C68 -> -1 | E67: FVE | F67: 02-02-2026 | G67: 02-02-2026 11:56:20 | H67: 900800595 | I67: Provexpress SAS | J67: 800024265 | K67: Editorial Santillana SAS | L67: 7819042.1 | M67: 0 | N67: 0 | O67: 48971895 | P67: Aprobado con notificación | Q67: Emitido | U67: X | X67: NC 5889
A68: Factura electrónica | B68: 9b9affb9cbb84b0cf9dc4b2fa1f6ddde16777701fdc9330a35d7d2623f2957c05a7dff5f0cc8e334167a28f390bf7972 | C68: 105714 | D68: =C68-C69 -> -1 | E68: FVE | F68: 02-02-2026 | G68: 02-02-2026 11:56:37 | H68: 900800595 | I68: Provexpress SAS | J68: 800024265 | K68: Editorial Santillana SAS | L68: 6912482.2 | M68: 0 | N68: 0 | O68: 43293967 | P68: Aprobado con notificación | Q68: Emitido | U68: X | X68: NC 5888
A69: Factura electrónica | B69: f6f526bb0d71cc25ff94c9ede5a767d35e019038e48fa1dc327f9529fc0b85ac068eb618d28308ad224159e2cbb76a65 | C69: 105715 | D69: =C69-C70 -> -1 | E69: FVE | F69: 02-02-2026 | G69: 02-02-2026 12:11:28 | H69: 900800595 | I69: Provexpress SAS | J69: 800024265 | K69: Editorial Santillana SAS | L69: 1543810 | M69: 0 | N69: 0 | O69: 9669126 | P69: Aprobado con notificación | Q69: Emitido | U69: X | X69: NC 5899
A70: Factura electrónica | B70: 17f7a2f5952d1c6c1a3b085f3afe7e8e6e47c5db882bec2e50e2a55b2fd5ffefc72019d6aeea478de244a05073c56f48 | C70: 105716 | D70: =C70-C71 -> -1 | E70: FVE | F70: 02-02-2026 | G70: 02-02-2026 12:11:33 | H70: 900800595 | I70: Provexpress SAS | J70: 800024265 | K70: Editorial Santillana SAS | L70: 2902088.5 | M70: 0 | N70: 0 | O70: 29080978 | P70: Aprobado con notificación | Q70: Emitido | U70: X | X70: NC 5903
A71: Factura electrónica | B71: edfd0dd919fb7b437ffe8f1649288d81b9386d870f326d9531a0845ca9e0031f24f121fd13aae0f886e2028d00fe935a | C71: 105717 | D71: =C71-C72 -> -1 | E71: FVE | F71: 02-02-2026 | G71: 02-02-2026 12:11:38 | H71: 900800595 | I71: Provexpress SAS | J71: 800024265 | K71: Editorial Santillana SAS | L71: 0 | M71: 0 | N71: 0 | O71: 4361896 | P71: Aprobado con notificación | Q71: Emitido | R71: X
A72: Factura electrónica | B72: 33822f3f7463d082e2787abdff3b43854255f6e88f97c9b1caa0559a9f9b8a094db7178ba07dfc63c9027b1500d51a70 | C72: 105718 | D72: =C72-C73 -> -1 | E72: FVE | F72: 02-02-2026 | G72: 02-02-2026 12:11:42 | H72: 900800595 | I72: Provexpress SAS | J72: 800024265 | K72: Editorial Santillana SAS | L72: 369560.45 | M72: 0 | N72: 0 | O72: 2314615.5 | P72: Aprobado con notificación | Q72: Emitido | R72: X
A73: Factura electrónica | B73: 7f3cece727f36d4f0eec73e128bef71e91ea8653c0ecc29d390a10a77ef19ebd75db767b84db8cf09352829f66f25390 | C73: 105719 | D73: =C73-C74 -> -1 | E73: FVE | F73: 02-02-2026 | G73: 02-02-2026 12:11:47 | H73: 900800595 | I73: Provexpress SAS | J73: 800024265 | K73: Editorial Santillana SAS | L73: 0 | M73: 0 | N73: 0 | O73: 37076116 | P73: Aprobado con notificación | Q73: Emitido | R73: X
A74: Factura electrónica | B74: f88ae37c21a83c2c5ab85d5eb7009c952c95461d2de467e974e944dadcf2c3bcb35bb5739f6ce00ff4652af779c86bb6 | C74: 105720 | D74: =C74-C75 -> -1 | E74: FVE | F74: 02-02-2026 | G74: 02-02-2026 12:11:51 | H74: 900800595 | I74: Provexpress SAS | J74: 900935262 | K74: General Business Machines De Colombia SAS | L74: 68868.87 | M74: 0 | N74: 0 | O74: 431336.58 | P74: Aprobado con notificación | Q74: Emitido | W74: X | X74: FACTURA PAGA EN EL SISTEMA 3/02/2026
A75: Factura electrónica | B75: d61072dacdf8ecdf9d7a9b23ea547a47b049204f70fa530031e33674bdaaacc7312229d39e328486d6b216a41e0dc242 | C75: 105721 | D75: =C75-C76 -> -1 | E75: FVE | F75: 02-02-2026 | G75: 02-02-2026 16:22:43 | H75: 900800595 | I75: Provexpress SAS | J75: 900561761 | K75: Ingram Micro S.A.S | L75: 300960 | M75: 0 | N75: 0 | O75: 1884960 | P75: Aprobado con notificación | Q75: Emitido | R75: X
A76: Factura electrónica | B76: aaca6d52be0e23d8c40b0ba399b4a4c1f2eb1c1f1bb02062f70d4b78a7f4f948355f1b4522ce3e298dfbaf12862bc856 | C76: 105722 | D76: =C76-C77 -> -1 | E76: FVE | F76: 02-02-2026 | G76: 02-02-2026 12:12:00 | H76: 900800595 | I76: Provexpress SAS | J76: 901295223 | K76: Cosco Shipping Lines Colombia SAS | L76: 411730 | M76: 0 | N76: 0 | O76: 2578730 | P76: Aprobado con notificación | Q76: Emitido | V76: X
A77: Factura electrónica | B77: 390e296437c459e3309f45b749cf66baacccfc90a27bb53661bd100dd9fc0e7aea8558cfe62918b452534dda234bc4ee | C77: 105723 | D77: =C77-C78 -> -1 | E77: FVE | F77: 02-02-2026 | G77: 02-02-2026 12:12:04 | H77: 900800595 | I77: Provexpress SAS | J77: 900430265 | K77: Logysteel Operador Logistico SAS | L77: 0 | M77: 0 | N77: 0 | O77: 2494500 | P77: Aprobado con notificación | Q77: Emitido | W77: X | X77: FACTURA PAGA EN EL SISTEMA 13/02/2026
A78: Factura electrónica | B78: c84b230a53be95bf9b9cfad19fcb5535a1a07c22273c9d9151e5a7b7686d589de280140f747c58dbc110610ac344f18c | C78: 105724 | D78: =C78-C79 -> -1 | E78: FVE | F78: 02-02-2026 | G78: 02-02-2026 12:12:09 | H78: 900800595 | I78: Provexpress SAS | J78: 860029415 | K78: Empresa Colombiana De Clavos Emcoclavos SAS | L78: 1219415.8 | M78: 0 | N78: 0 | O78: 7637393.8 | P78: Aprobado con notificación | Q78: Emitido | T78: X
A79: Factura electrónica | B79: af380d11a984c5fce59b56725bfcf7857d539ce60e3f642117fe00c4a99a4766815724a411c20e835f973ea6b50fab90 | C79: 105725 | D79: =C79-C80 -> -1 | E79: FVE | F79: 02-02-2026 | G79: 02-02-2026 12:12:13 | H79: 900800595 | I79: Provexpress SAS | J79: 860533413 | K79: IRCC SAS Industria De Restaurantes Casuales SAS | L79: 186200 | M79: 0 | N79: 0 | O79: 1166200 | P79: Aprobado con notificación | Q79: Emitido | R79: X
A80: Factura electrónica | B80: 25d0becf9a447183246e5b649600d33dbc1a07f2d0224535e65445fba9054055754de33a5c6d2089da0ba43494930607 | C80: 105726 | D80: =C80-C81 -> -1 | E80: FVE | F80: 02-02-2026 | G80: 02-02-2026 12:12:19 | H80: 900800595 | I80: Provexpress SAS | J80: 860050750 | K80: Banco Gnb Sudameris S A | L80: 85500 | M80: 0 | N80: 0 | O80: 535500 | P80: Aprobado con notificación | Q80: Emitido | R80: X
A81: Factura electrónica | B81: a127aea6e58cbbf0b5d466972d97a8cb5c97ef8738eba634e3f7db990db67549777b4e78f19c6fea1e8fbaae71bf0694 | C81: 105727 | D81: =C81-C82 -> -1 | E81: FVE | F81: 02-02-2026 | G81: 02-02-2026 12:12:22 | H81: 900800595 | I81: Provexpress SAS | J81: 900451379 | K81: Levare Services Ltd Sucursal Colombia | L81: 23560 | M81: 0 | N81: 0 | O81: 147560 | P81: Aprobado con notificación | Q81: Emitido | T81: X
A82: Factura electrónica | B82: 2c3ec62f4c8040d88e6e7a1f7fcb3ea601d413f563dec7a51e36983371e4a9b493261dfc1055b21363c154c74c5c86c8 | C82: 105728 | D82: =C82-C83 -> -1 | E82: FVE | F82: 02-02-2026 | G82: 02-02-2026 12:12:28 | H82: 900800595 | I82: Provexpress SAS | J82: 800066123 | K82: Gi Group Staffing SAS | L82: 148200 | M82: 0 | N82: 0 | O82: 928200 | P82: Aprobado con notificación | Q82: Emitido | V82: X
A83: Factura electrónica | B83: 7a83f02aeee9539957a89270e797d51e5ae988595ffdf828bd2d7badf04f44e7e701946e5568976c59f35a5519ba28a0 | C83: 105729 | D83: =C83-C84 -> -1 | E83: FVE | F83: 02-02-2026 | G83: 02-02-2026 12:27:35 | H83: 900800595 | I83: Provexpress SAS | J83: 860050906 | K83: Adecco Colombia S A | L83: 103360 | M83: 0 | N83: 0 | O83: 647360 | P83: Aprobado con notificación | Q83: Emitido | T83: X
A84: Factura electrónica | B84: 5b113308845a32926d39761515dc67651465ac9bcf6f6d054b2733ac3f1290c969d7d1c2b791f2e828c133f286ba2432 | C84: 105730 | D84: =C84-C85 -> -1 | E84: FVE | F84: 02-02-2026 | G84: 02-02-2026 12:27:39 | H84: 900800595 | I84: Provexpress SAS | J84: 860050906 | K84: Adecco Colombia S A | L84: 10260 | M84: 0 | N84: 0 | O84: 64260 | P84: Aprobado con notificación | Q84: Emitido | T84: X
A85: Factura electrónica | B85: 33d8e47ffd24df7387af41fa33af49f737a113e8b8ce3557e66bb42676037f80ebba811d0a7723356498a09c58eae841 | C85: 105731 | D85: =C85-C86 -> -1 | E85: FVE | F85: 02-02-2026 | G85: 02-02-2026 12:27:43 | H85: 900800595 | I85: Provexpress SAS | J85: 860050906 | K85: Adecco Colombia S A | L85: 17290 | M85: 0 | N85: 0 | O85: 108290 | P85: Aprobado con notificación | Q85: Emitido | T85: X
A86: Factura electrónica | B86: aa634563b5acc2a07606e60f7bf1eca1f3a15873f952a92cc0754bd6b2c6266a53808b4f044f6188c2272a0a6732c3e3 | C86: 105732 | D86: =C86-C87 -> -1 | E86: FVE | F86: 02-02-2026 | G86: 02-02-2026 12:27:48 | H86: 900800595 | I86: Provexpress SAS | J86: 800237608 | K86: Central De Insumos Y Materias Primas Para La Industria Alimentaria SAS | L86: 95000 | M86: 0 | N86: 0 | O86: 595000 | P86: Aprobado con notificación | Q86: Emitido | T86: X
A87: Factura electrónica | B87: 5cfefd84a8fe1834c99263cefd4756abf5bfb1fac93105f48976e238ad3eb0f9e96fe899e47f89e8b9c02c012225fd04 | C87: 105733 | D87: =C87-C88 -> -1 | E87: FVE | F87: 02-02-2026 | G87: 02-02-2026 12:27:52 | H87: 900800595 | I87: Provexpress SAS | J87: 901380344 | K87: Buk Col SAS | L87: 1729000 | M87: 0 | N87: 0 | O87: 10829000 | P87: Aprobado con notificación | Q87: Emitido | W87: X | X87: FACTURA PAGA EN EL SISTEMA 20/02/2026
A88: Factura electrónica | B88: b01ba36f568ec034af4bfa43dd2f104504d56f18b5a31b80569b5321c335a6f8474b765b3971929b606c29afebbfb205 | C88: 105734 | D88: =C88-C89 -> -1 | E88: FVE | F88: 02-02-2026 | G88: 02-02-2026 12:27:58 | H88: 900800595 | I88: Provexpress SAS | J88: 901380344 | K88: Buk Col SAS | L88: 444600 | M88: 0 | N88: 0 | O88: 2784600 | P88: Aprobado con notificación | Q88: Emitido | V88: X
A89: Factura electrónica | B89: e5f500062e105cf3b708db56d63aa25aeb39e6228daa69fe36d08d034bf0ef83396584ec1f9c26b3aff7d4c7fc136f3e | C89: 105735 | D89: =C89-C90 -> -1 | E89: FVE | F89: 02-02-2026 | G89: 02-02-2026 12:28:02 | H89: 900800595 | I89: Provexpress SAS | J89: 860504772 | K89: Efectimedios SAS | L89: 507110 | M89: 0 | N89: 0 | O89: 3176110 | P89: Aprobado con notificación | Q89: Emitido | R89: X
A90: Factura electrónica | B90: 203d752c3abb1719cb87dbac3601825bdcafc4a47744e94dbf17c907e6cf7750e16b34631d5c4fc54bcd9c88bf38ae2c | C90: 105736 | D90: =C90-C91 -> -1 | E90: FVE | F90: 02-02-2026 | G90: 02-02-2026 12:28:06 | H90: 900800595 | I90: Provexpress SAS | J90: 860504772 | K90: Efectimedios SAS | L90: 451250 | M90: 0 | N90: 0 | O90: 2826250 | P90: Aprobado con notificación | Q90: Emitido | R90: X
A91: Factura electrónica | B91: 6f12bd8e8e332a14faa985f917b4bd58a5880af1ab4f7306f61cbb2ce225592b19e2d6be5c5129bb6c6bb6c4519a9b7b | C91: 105737 | D91: =C91-C92 -> -1 | E91: FVE | F91: 02-02-2026 | G91: 02-02-2026 12:28:11 | H91: 900800595 | I91: Provexpress SAS | J91: 901383974 | K91: Mondi Cartagena SAS | L91: 269800 | M91: 0 | N91: 0 | O91: 1689800 | P91: Aprobado con notificación | Q91: Emitido | R91: X
A92: Factura electrónica | B92: 1471b77215a82bf54c2fcbf00e9bc062c165d9aaa5648d02993e07da96c5eda7766bdd0c23b54a9b4a243395fec63650 | C92: 105738 | D92: =C92-C93 -> -1 | E92: FVE | F92: 02-02-2026 | G92: 02-02-2026 12:28:16 | H92: 900800595 | I92: Provexpress SAS | J92: 901383974 | K92: Mondi Cartagena SAS | L92: 1197583.9 | M92: 0 | N92: 0 | O92: 7500656.9 | P92: Aprobado con notificación | Q92: Emitido | R92: X
A93: Factura electrónica | B93: 9cf2d24fba1c3ffd6e9284e01161c1d33347b6b045a08df4db867be4769bbc682f14a1c79274eec1d08fada53a5de286 | C93: 105739 | D93: =C93-C94 -> -1 | E93: FVE | F93: 02-02-2026 | G93: 02-02-2026 12:28:21 | H93: 900800595 | I93: Provexpress SAS | J93: 830050228 | K93: Adecco Servicios Colombia S A | L93: 59850 | M93: 0 | N93: 0 | O93: 374850 | P93: Aprobado con notificación | Q93: Emitido | T93: X
A94: Factura electrónica | B94: 749f55ce4f37ca82bbc7dcb697659aa740b40eb3a5daa86bb7284a437462d43ed56b0d74443c6bf5c6f868f7f665f637 | C94: 105740 | D94: =C94-C95 -> -1 | E94: FVE | F94: 02-02-2026 | G94: 02-02-2026 12:43:27 | H94: 900800595 | I94: Provexpress SAS | J94: 901383974 | K94: Mondi Cartagena SAS | L94: 866229 | M94: 0 | N94: 0 | O94: 5425329 | P94: Aprobado con notificación | Q94: Emitido | R94: X
A95: Factura electrónica | B95: b4a8de5057442bb67d7ccfe31246432059d0550dbaf264d5fa0fd9d1f459d7a1e01a14f53ffb1df36daaac180d0abd9c | C95: 105741 | D95: =C95-C96 -> -1 | E95: FVE | F95: 02-02-2026 | G95: 02-02-2026 12:43:31 | H95: 900800595 | I95: Provexpress SAS | J95: 901383974 | K95: Mondi Cartagena SAS | L95: 148200 | M95: 0 | N95: 0 | O95: 928200 | P95: Aprobado con notificación | Q95: Emitido | R95: X
A96: Factura electrónica | B96: 2e1763bd4723ef6d7fc980aaf78fb8c12149a0e799c8b1736113637bf6225b6e4bd2bbdeac5d911bfd37d5d666ae921e | C96: 105742 | D96: =C96-C97 -> -1 | E96: FVE | F96: 02-02-2026 | G96: 02-02-2026 12:43:37 | H96: 900800595 | I96: Provexpress SAS | J96: 890401802 | K96: Prosegur Vigilancia Y Seguridad Privada LTDA | L96: 80750 | M96: 0 | N96: 0 | O96: 505750 | P96: Aprobado con notificación | Q96: Emitido | R96: X
A97: Factura electrónica | B97: 4f79cc366c8c0ff4693c110cf1f66f8172e21df21fd8e74c77c690084bbef60cb857732b1b5a5f5a836c59942041aefa | C97: 105743 | D97: =C97-C98 -> -1 | E97: FVE | F97: 02-02-2026 | G97: 02-02-2026 12:43:41 | H97: 900800595 | I97: Provexpress SAS | J97: 890401802 | K97: Prosegur Vigilancia Y Seguridad Privada LTDA | L97: 505400 | M97: 0 | N97: 0 | O97: 3165400 | P97: Aprobado con notificación | Q97: Emitido | S97: X
A98: Factura electrónica | B98: e92f9bc6b81387671ec867f50f66faf4fd75fc5fd91d76409d194e1e9a9812720139a021c13aa3e4c5e4942a1a7c616e | C98: 105744 | D98: =C98-C99 -> -1 | E98: FVE | F98: 02-02-2026 | G98: 02-02-2026 12:43:46 | H98: 900800595 | I98: Provexpress SAS | J98: 890401802 | K98: Prosegur Vigilancia Y Seguridad Privada LTDA | L98: 182400 | M98: 0 | N98: 0 | O98: 1142400 | P98: Aprobado con notificación | Q98: Emitido | S98: X
A99: Factura electrónica | B99: dc5c4ee659e745b3979eb78c0b715c6299a04cd49e79aa2b053b46a1b86ff029909e9b6097434167f54790d9c338cb59 | C99: 105745 | D99: =C99-C100 -> -1 | E99: FVE | F99: 02-02-2026 | G99: 02-02-2026 12:43:50 | H99: 900800595 | I99: Provexpress SAS | J99: 890401802 | K99: Prosegur Vigilancia Y Seguridad Privada LTDA | L99: 235600 | M99: 0 | N99: 0 | O99: 1475600 | P99: Aprobado con notificación | Q99: Emitido | S99: X
A100: Factura electrónica | B100: 67914a89671ddc422fc5fd2e5207660a9ff1714675eb517a2590d65882d870bfa13ec323f41af539f384e4dea6553d66 | C100: 105746 | D100: =C100-C101 -> -1 | E100: FVE | F100: 02-02-2026 | G100: 02-02-2026 12:43:55 | H100: 900800595 | I100: Provexpress SAS | J100: 890401802 | K100: Prosegur Vigilancia Y Seguridad Privada LTDA | L100: 646000 | M100: 0 | N100: 0 | O100: 4046000 | P100: Aprobado con notificación | Q100: Emitido | S100: X
A101: Factura electrónica | B101: 64ec7f7caa4f9e3c3d1cc6b187fadd164b9a3f542bd181f3570e91143ab8cc70a6fbe0c1ec3ebb130604e17d5afe1e7f | C101: 105747 | D101: =C101-C102 -> -1 | E101: FVE | F101: 02-02-2026 | G101: 02-02-2026 12:43:59 | H101: 900800595 | I101: Provexpress SAS | J101: 890401802 | K101: Prosegur Vigilancia Y Seguridad Privada LTDA | L101: 473100 | M101: 0 | N101: 0 | O101: 2963100 | P101: Aprobado con notificación | Q101: Emitido | S101: X
A102: Factura electrónica | B102: a0dd3ac5678121152bf74f8ff804cc83dc06390f514b7ebf05b77a676966b536a42bdbd46783fdfb2dca2ba8f77a2586 | C102: 105748 | D102: =C102-C103 -> -1 | E102: FVE | F102: 02-02-2026 | G102: 02-02-2026 12:44:04 | H102: 900800595 | I102: Provexpress SAS | J102: 890401802 | K102: Prosegur Vigilancia Y Seguridad Privada LTDA | L102: 50350 | M102: 0 | N102: 0 | O102: 315350 | P102: Aprobado con notificación | Q102: Emitido | S102: X
...

Sheet Detalle1
A1: Detalles para Cuenta de 1 ACUSE - Nombre Receptor: Aon Risk Services Colombia S A Corredores De Seguros Pero Podra Girar Bajo La Sigla Aon Colombia S A, 1 ACUSE: X
A3: Tipo de documento | B3: CUFE/CUDE | C3: Folio | D3: Columna1 | E3: Prefijo | F3: Fecha Emisión | G3: Fecha Recepción | H3: NIT Emisor | I3: Nombre Emisor | J3: NIT Receptor | K3: Nombre Receptor | L3: IVA | M3: ICA | N3: IPC | O3: Total | P3: Estado | Q3: Grupo | R3: 1 ACUSE | S3: 2 ACUSE | T3: 3 ACUSE | U3: RECHAZADA | V3: SIN ACUSE | W3: YA PAGA EN SISTEMA | X3: OBSERVACIONES
A4: Factura electrónica | B4: b2f69d21b80c359fd38551759cf894c829ae88221bf1a712b4247484aff61a565361b3d2cf582d7efad4b6a8e276e8e0 | C4: 107247 | D4: -1 | E4: FVE | F4: 19-02-2026 | G4: 19-02-2026 12:29:10 | H4: 900800595 | I4: Provexpress SAS | J4: 860069265 | K4: Aon Risk Services Colombia S A Corredores De Seguros Pero Podra Girar Bajo La Sigla Aon Colombia S A | L4: 798000 | M4: 0 | N4: 0 | O4: 4998000 | P4: Aprobado con notificación | Q4: Emitido | R4: X

Sheet 1 ACUSE
A1: 1 ACUSE | B1: (Varios elementos)
A3: Nombre Receptor | B3: Folio | C3: Cuenta de 1 ACUSE | D3: Suma de Total
A4: Adecco Colombia S A | B4: 107031 | C4: 1 | D4: 108290
A5: Total Adecco Colombia S A | C5: 1 | D5: 108290
A6: Adecco Servicios Colombia S A | B6: 107145 | C6: 1 | D6: 27331780
B7: 107325 | C7: 1 | D7: 357595
B8: 107350 | C8: 1 | D8: 4625530
A9: Total Adecco Servicios Colombia S A | C9: 3 | D9: 32314905
A10: Administradora Country SAS | C10: 1 | D10: 10143723
A11: Aecsa SAS | B11: 107421 | C11: 1 | D11: 7370860
A12: Total Aecsa SAS | C12: 1 | D12: 7370860
A13: Aon Risk Services Colombia S A Corredores De Seguros Pero Podra Girar Bajo La Sigla Aon Colombia S A | B13: 107247 | C13: 1 | D13: 4998000
A14: Total Aon Risk Services Colombia S A Corredores De Seguros Pero Podra Girar Bajo La Sigla Aon Colombia S A | C14: 1 | D14: 4998000
A15: Applus Norcontrol Colombia Limitada | B15: 106490 | C15: 1 | D15: 2903659.5
A16: Total Applus Norcontrol Colombia Limitada | C16: 1 | D16: 2903659.5
A17: Asociacion De Egresados De La Universidad De Los Andes Uniandinos | B17: 106128 | C17: 1 | D17: 587021.05
B18: 106867 | C18: 1 | D18: 587021.05
B19: 107054 | C19: 1 | D19: 2771997.9
A20: Total Asociacion De Egresados De La Universidad De Los Andes Uniandinos | C20: 3 | D20: 3946040
A21: Autogermana SAS | B21: 107111 | C21: 1 | D21: 1301979
A22: Total Autogermana SAS | C22: 1 | D22: 1301979
A23: Automundial SA | B23: 105912 | C23: 1 | D23: 196350
B24: 105913 | C24: 1 | D24: 196350
B25: 106117 | C25: 1 | D25: 113050
A26: Total Automundial SA | C26: 3 | D26: 505750
A27: Banco Gnb Sudameris S A | B27: 105726 | C27: 1 | D27: 535500
B28: 106081 | C28: 1 | D28: 267750
A29: Total Banco Gnb Sudameris S A | C29: 2 | D29: 803250
A30: Boticario Colombia S A S | B30: 105806 | C30: 1 | D30: 999600
B31: 105807 | C31: 1 | D31: 4819500
B32: 106549 | C32: 1 | D32: 39139897
A33: Total Boticario Colombia S A S | C33: 3 | D33: 44958997
A34: Carbe SAS | B34: 107176 | C34: 1 | D34: 772905
A35: Total Carbe SAS | C35: 1 | D35: 772905
A36: Carboinsa SAS | B36: 105861 | C36: 1 | D36: 666572.55
B37: 107342 | C37: 1 | D37: 2507288.4
A38: Total Carboinsa SAS | C38: 2 | D38: 3173860.9
A39: Centros Medicos Colsanitas S A S | B39: 107241 | C39: 1 | D39: 370222.09
A40: Total Centros Medicos Colsanitas S A S | C40: 1 | D40: 370222.09
A41: Ceramica San Lorenzo Industrial De Colombia SA | B41: 106370 | C41: 1 | D41: 252945
B42: 106927 | C42: 1 | D42: 180642
B43: 107084 | C43: 1 | D43: 702873.5
A44: Total Ceramica San Lorenzo Industrial De Colombia SA | C44: 3 | D44: 1136460.5
A45: Challenger SAS | B45: 107178 | C45: 1 | D45: 868700
B46: 107322 | C46: 1 | D46: 445060
A47: Total Challenger SAS | C47: 2 | D47: 1313760
A48: Clinica Colsanitas SA | B48: 106295 | C48: 1 | D48: 1460454.9
B49: 106887 | C49: 1 | D49: 1535483.2
B50: 106889 | C50: 1 | D50: 25204901
B51: 107244 | C51: 1 | D51: 489136.41
A52: Total Clinica Colsanitas SA | C52: 4 | D52: 28689975
A53: Clinica Dental Keralty SAS | B53: 107245 | C53: 1 | D53: 370222.09
B54: 107246 | C54: 1 | D54: 370222.09
A55: Total Clinica Dental Keralty SAS | C55: 2 | D55: 740444.18
A56: Club Campestre El Rancho | B56: 105925 | C56: 1 | D56: 1892887.8
A57: Total Club Campestre El Rancho | C57: 1 | D57: 1892887.8
A58: Coala Arquitectura Y Construccion SAS | B58: 106498 | C58: 1 | D58: 379205.1
A59: Total Coala Arquitectura Y Construccion SAS | C59: 1 | D59: 379205.1
A60: Comercializadora Internacional Milpa SA | B60: 106082 | C60: 1 | D60: 13863500
B61: 107233 | C61: 1 | D61: 4069919
B62: 107395 | C62: 1 | D62: 1999200
B63: 107429 | C63: 1 | D63: 357000
A64: Total Comercializadora Internacional Milpa SA | C64: 4 | D64: 20289619
A65: Compañia De Medicina Prepagada Colsanitas SA | B65: 106888 | C65: 1 | D65: 124600.14
A66: Total Compañia De Medicina Prepagada Colsanitas SA | C66: 1 | D66: 124600.14
A67: Confederacion Colombiana De Camaras De Comercio Confecamaras | B67: 106849 | C67: 1 | D67: 70123606
B68: 107110 | C68: 1 | D68: 2588250
B69: 107118 | C69: 1 | D69: 89250
A70: Total Confederacion Colombiana De Camaras De Comercio Confecamaras | C70: 3 | D70: 72801106
A71: Creative Colors SA | B71: 106670 | C71: 1 | D71: 1059100
A72: Total Creative Colors SA | C72: 1 | D72: 1059100
A73: CYC Trading SAS | B73: 106226 | C73: 1 | D73: 116441.5
B74: 106227 | C74: 1 | D74: 154235.9
A75: Total CYC Trading SAS | C75: 2 | D75: 270677.4
A76: Distribuidora Y Editora Richmond SAS | B76: 106263 | C76: 1 | D76: 15333336
B77: 106288 | C77: 1 | D77: 6542844
B78: 106920 | C78: 1 | D78: 34500006
A79: Total Distribuidora Y Editora Richmond SAS | C79: 3 | D79: 56376186
A80: Doble A Ingenieria SAS | B80: 106710 | C80: 1 | D80: 509544
A81: Total Doble A Ingenieria SAS | C81: 1 | D81: 509544
A82: Don Maiz SAS | B82: 106839 | C82: 1 | D82: 4161828
A83: Total Don Maiz SAS | C83: 1 | D83: 4161828
A84: Editorial Santillana SAS | B84: 105692 | C84: 1 | D84: 10642619
B85: 105698 | C85: 1 | D85: 7666668
B86: 105699 | C86: 1 | D86: 25314619
B87: 105700 | C87: 1 | D87: 38333340
B88: 105702 | C88: 1 | D88: 37035844
B89: 105705 | C89: 1 | D89: 68656281
B90: 105717 | C90: 1 | D90: 4361896
B91: 105718 | C91: 1 | D91: 2314615.5
B92: 105719 | C92: 1 | D92: 37076116
B93: 106261 | C93: 1 | D93: 4495563.5
B94: 106262 | C94: 1 | D94: 48916528
B95: 106290 | C95: 1 | D95: 38680125
B96: 106291 | C96: 1 | D96: 39623774
... B109: 106922 | C109: 1 | D109: 4231282.5
A110: Total Editorial Santillana SAS | C110: 26 | D110: 7.395632e+08
A111: Educactiva SAS | B111: 105690 | C111: 1 | D111: 3017519.9
B112: 106658 | C112: 1 | D112: 1.3598048e+08
B113: 106716 | C113: 1 | D113: 43109124
...

Sheet 2 ACUSES
A1: 2 ACUSE | B1: (Varios elementos)
A3: Nombre Receptor | B3: Folio | C3: Cuenta de 2 ACUSE | D3: Suma de Total
A4: Administradora Clinica La Colina S A S | B4: 106119 | C4: 1 | D4: 3168232.2
A5: Total Administradora Clinica La Colina S A S | C5: 1 | D5: 3168232.2
A6: Administradora Country SAS | B6: 105775 | C6: 1 | D6: 3717189
A7: Total Administradora Country SAS | C7: 1 | D7: 3717189
A8: Caja Colombiana De Subsidio Familiar Colsubsidio | B8: 105660 | C8: 1 | D8: 175644
B9: 105661 | C9: 1 | D9: 77112
A10: Total Caja Colombiana De Subsidio Familiar Colsubsidio | C10: 2 | D10: 252756
A11: Ceramica San Lorenzo Industrial De Colombia SA | B11: 105799 | C11: 1 | D11: 9205413.5
A12: Total Ceramica San Lorenzo Industrial De Colombia SA | C12: 1 | D12: 9205413.5
A13: Colombian Shared Services SAS | B13: 106487 | C13: 1 | D13: 26455350
A14: Total Colombian Shared Services SAS | C14: 1 | D14: 26455350
A15: Confederacion Colombiana De Camaras De Comercio Confecamaras | B15: 106895 | C15: 1 | D15: 317206.4
A16: Total Confederacion Colombiana De Camaras De Comercio Confecamaras | C16: 1 | D16: 317206.4
A17: Congregacion De Hermanas De Caridad Dominicas De La Representacion De La Santisima Virgen | B17: 106624 | C17: 1 | D17: 1165819.2
A18: Total Congregacion De Hermanas De Caridad Dominicas De La Representacion De La Santisima Virgen | C18: 1 | D18: 1165819.2
A19: Don Maiz SAS | B19: 106442 | C19: 1 | D19: 137634.21
B20: 106844 | C20: 1 | D20: 2498533.5
B21: 106845 | C21: 1 | D21: 302600
B22: 106860 | C22: 1 | D22: 624117.36
B23: 107287 | C23: 1 | D23: 291038.3
A24: Total Don Maiz SAS | C24: 5 | D24: 3853923.4
A25: Esmeraldas De Los Andes SAS | B25: 106628 | C25: 1 | D25: 226100
A26: Total Esmeraldas De Los Andes SAS | C26: 1 | D26: 226100
A27: Fitness24seven Colombia S A S | B27: 106865 | C27: 1 | D27: 22947127
A28: Total Fitness24seven Colombia S A S | C28: 1 | D28: 22947127
A29: Flota La Macarena SA | B29: 105777 | C29: 1 | D29: 2420978.7
A30: Total Flota La Macarena SA | C30: 1 | D30: 2420978.7
A31: Geodis Colombia LTDA | B31: 106619 | C31: 1 | D31: 6420000
A32: Total Geodis Colombia LTDA | C32: 1 | D32: 6420000
A33: Idom Consulting Engineering Architecture SAU | B33: 106514 | C33: 1 | D33: 379930.11
A34: Total Idom Consulting Engineering Architecture SAU | C34: 1 | D34: 379930.11
A35: Industria Nacional De Gaseosas SA | B35: 106808 | C35: 1 | D35: 166046.65
B36: 107056 | C36: 1 | D36: 3067848.6
B37: 107210 | C37: 1 | D37: 7224002.1
A38: Total Industria Nacional De Gaseosas SA | C38: 3 | D38: 10457897
A39: Industrias De Refrigeracion Comercial SA Indufrial SA Reorganizacion Empresarial | B39: 106570 | C39: 1 | D39: 498610
A40: Total Industrias De Refrigeracion Comercial SA Indufrial SA Reorganizacion Empresarial | C40: 1 | D40: 498610
A41: Inverleoka SAS | B41: 105770 | C41: 1 | D41: 129234
B42: 106316 | C42: 1 | D42: 182800.66
B43: 106358 | C43: 1 | D43: 74039.42
B44: 106415 | C44: 1 | D44: 106921.5
B45: 106419 | C45: 1 | D45: 116620
A46: Total Inverleoka SAS | C46: 5 | D46: 609615.58
A47: Kata SAS | B47: 106121 | C47: 1 | D47: 537827.64
B48: 106351 | C48: 1 | D48: 178500
B49: 106352 | C49: 1 | D49: 116620
B50: 106353 | C50: 1 | D50: 116620
B51: 106354 | C51: 1 | D51: 116620
B52: 106355 | C52: 1 | D52: 116620
B53: 106414 | C53: 1 | D53: 35462
A54: Total Kata SAS | C54: 7 | D54: 1218269.6
A55: Prosegur Vigilancia Y Seguridad Privada LTDA | B55: 105743 | C55: 1 | D55: 3165400
B56: 105744 | C56: 1 | D56: 1142400
B57: 105745 | C57: 1 | D57: 1475600
B58: 105746 | C58: 1 | D58: 4046000
B59: 105747 | C59: 1 | D59: 2963100
B60: 105748 | C60: 1 | D60: 315350
B61: 105749 | C61: 1 | D61: 2600150
B62: 105750 | C62: 1 | D62: 291550
B63: 105751 | C63: 1 | D63: 160650
A64: Total Prosegur Vigilancia Y Seguridad Privada LTDA | C64: 9 | D64: 16160200
A65: Salitre Plaza Centro Comercial Propiedad Horizontal | B65: 106207 | C65: 1 | D65: 234192
B66: 107231 | C66: 1 | D66: 214200
A67: Total Salitre Plaza Centro Comercial Propiedad Horizontal | C67: 2 | D67: 448392
A68: Sofka Technologies SAS | B68: 107074 | C68: 1 | D68: 2302650
A69: Total Sofka Technologies SAS | C69: 1 | D69: 2302650
A70: Universidad De La Sabana | B70: 106140 | C70: 1 | D70: 1055000
B71: 106141 | C71: 1 | D71: 17136000
B72: 106368 | C72: 1 | D72: 1810704
B73: 106407 | C73: 1 | D73: 1386350
B74: 106754 | C74: 1 | D74: 357000
A75: Total Universidad De La Sabana | C75: 5 | D75: 21745054
A76: Banco Jpmorgan Colombia SA | B76: 106509 | C76: 1 | D76: 524909
B77: 106614 | C77: 1 | D77: 3594402.7
B78: 107211 | C78: 1 | D78: 130295.3
A79: Total Banco Jpmorgan Colombia SA | C79: 3 | D79: 4249607
A80: Prosegur Tecnologia SAS | B80: 105752 | C80: 1 | D80: 2308600
A81: Total Prosegur Tecnologia SAS | C81: 1 | D81: 2308600
A82: Fundacion Universidad Del Norte | B82: 105805 | C82: 1 | D82: 4605300
A83: Total Fundacion Universidad Del Norte | C83: 1 | D83: 4605300
A84: Amarey Nova Medical SA | B84: 105846 | C84: 1 | D84: 5759600
A85: Total Amarey Nova Medical SA | C85: 1 | D85: 5759600
A86: S3 Simple Smart Speedy SAS | B86: 105851 | C86: 1 | D86: 7378702.1
A87: Total S3 Simple Smart Speedy SAS | C87: 1 | D87: 7378702.1
A88: C I Importex SA | B88: 107367 | C88: 1 | D88: 27000482
A89: Total C I Importex SA | C89: 1 | D89: 27000482
A90: Comercial Allan SAS | B90: 106158 | C90: 1 | D90: 1639225
A91: Total Comercial Allan SAS | C91: 1 | D91: 1639225
A92: Mccann Erickson Corporation SA | B92: 106168 | C92: 1 | D92: 1356838
A93: Total Mccann Erickson Corporation SA | C93: 1 | D93: 1356838
A94: Promotora Barlovento Del Mar SAS | B94: 106171 | C94: 1 | D94: 1747681.6
A95: Total Promotora Barlovento Del Mar SAS | C95: 1 | D95: 1747681.6
A96: Ajecolombia SAS | B96: 107133 | C96: 1 | D96: 77000
A97: Total Ajecolombia SAS | C97: 1 | D97: 77000
A98: Takai SAS | B98: 106489 | C98: 1 | D98: 736324.4
A99: Total Takai SAS | C99: 1 | D99: 736324.4
A100: Servihosp LTDA | B100: 106702 | C100: 1 | D100: 498877.75
A101: Total Servihosp LTDA | C101: 1 | D101: 498877.75
...

Sheet 3 ACUSES
A1: 3 ACUSE | B1: (Varios elementos)
A3: Nombre Receptor | B3: Folio | C3: Cuenta de 3 ACUSE | D3: Suma de Total
A4: Accion Sociedad Fiduciaria SA | B4: 107102 | C4: 1 | D4: 10390128
A5: Total Accion Sociedad Fiduciaria SA | C5: 1 | D5: 10390128
A6: Adecco Colombia S A | B6: 105729 | C6: 1 | D6: 647360
B7: 105730 | C7: 1 | D7: 64260
B8: 105731 | C8: 1 | D8: 108290
A9: Total Adecco Colombia S A | C9: 3 | D9: 819910
A10: Adecco Servicios Colombia S A | B10: 105739 | C10: 1 | D10: 374850
B11: 105760 | C11: 1 | D11: 541450
B12: 105761 | C12: 1 | D12: 89250
B13: 105762 | C13: 1 | D13: 29110970
B14: 106024 | C14: 1 | D14: 1621970
B15: 106469 | C15: 1 | D15: 5472810
B16: 106470 | C16: 1 | D16: 401030
B17: 106914 | C17: 1 | D17: 714000
B18: 107123 | C18: 1 | D18: 92582
B19: 107124 | C19: 1 | D19: 309400
A20: Total Adecco Servicios Colombia S A | C20: 10 | D20: 38728312
A21: Agrointegral Andina SAS | B21: 106705 | C21: 1 | D21: 4786180
A22: Total Agrointegral Andina SAS | C22: 1 | D22: 4786180
A23: Agunsa Colombia SAS | B23: 106644 | C23: 1 | D23: 71400
B24: 106813 | C24: 1 | D24: 18207000
B25: 106879 | C25: 1 | D25: 559300
A26: Total Agunsa Colombia SAS | C26: 3 | D26: 18837700
A27: Asociacion Para La Enseñanza Aspaen | B27: 105773 | C27: 1 | D27: 393106.98
A28: Total Asociacion Para La Enseñanza Aspaen | C28: 1 | D28: 393106.98
A29: Atp Ingenieria SAS En Reorganizacion | B29: 106462 | C29: 1 | D29: 850000
A30: Total Atp Ingenieria SAS En Reorganizacion | C30: 1 | D30: 850000
A31: Bel Star SA | B31: 106508 | C31: 1 | D31: 8454950
A32: Total Bel Star SA | C32: 1 | D32: 8454950
A33: Bigfoot Colombia SAS | B33: 106279 | C33: 1 | D33: 1772862
A34: Total Bigfoot Colombia SAS | C34: 1 | D34: 1772862
A35: Bold Co SAS | B35: 105918 | C35: 1 | D35: 1234000
B36: 105919 | C36: 1 | D36: 5652500
B37: 105928 | C37: 1 | D37: 6937700
B38: 106067 | C38: 1 | D38: 3427200
B39: 107077 | C39: 1 | D39: 15151675
A40: Total Bold Co SAS | C40: 5 | D40: 32403075
A41: Boydorr SAS | B41: 106592 | C41: 1 | D41: 290419.5
A42: Total Boydorr SAS | C42: 1 | D42: 290419.5
A43: BR Group SA | B43: 105797 | C43: 1 | D43: 277567.5
A44: Total BR Group SA | C44: 1 | D44: 277567.5
A45: Caja Colombiana De Subsidio Familiar Colsubsidio | B45: 105662 | C45: 1 | D45: 794275.02
B46: 105663 | C46: 1 | D46: 1657793.8
B47: 105664 | C47: 1 | D47: 116917.5
B48: 106029 | C48: 1 | D48: 475945.26
B49: 106030 | C49: 1 | D49: 154021.7
B50: 106629 | C50: 1 | D50: 258230
B51: 106689 | C51: 1 | D51: 3196399.5
B52: 106835 | C52: 1 | D52: 1853308.4
B53: 107042 | C53: 1 | D53: 529516.68
B54: 107095 | C54: 1 | D54: 467075
B55: 107094 | C55: 1 | D55: 354620
A56: Total Caja Colombiana De Subsidio Familiar Colsubsidio | C56: 11 | D56: 9858102.8
A57: Casahidalgo Constructores SAS | B57: 106894 | C57: 1 | D57: 512509.2
A58: Total Casahidalgo Constructores SAS | C58: 1 | D58: 512509.2
A59: Centro Medico Oftalmologico Y Laboratorio Clinico Andrade Narvaez Sociedad Por Acciones Simplificada | B59: 105658 | C59: 1 | D59: 18775225
A60: Total Centro Medico Oftalmologico Y Laboratorio Clinico Andrade Narvaez Sociedad Por Acciones Simplificada | C60: 1 | D60: 18775225
A61: Centros Medicos Colsanitas S A S | B61: 106294 | C61: 1 | D61: 99412.6
B62: 106345 | C62: 1 | D62: 2337439.6
B63: 106347 | C63: 1 | D63: 2337439.6
A64: Total Centros Medicos Colsanitas S A S | C64: 3 | D64: 4774291.9
A65: Clinica Colsanitas SA | B65: 105678 | C65: 1 | D65: 103634.72
B66: 105830 | C66: 1 | D66: 867783.7
B67: 105831 | C67: 1 | D67: 767741.59
B68: 105832 | C68: 1 | D68: 14556561
B69: 105942 | C69: 1 | D69: 370222.09
B70: 105943 | C70: 1 | D70: 740444.18
B71: 106346 | C71: 1 | D71: 7012319
A72: Total Clinica Colsanitas SA | C72: 7 | D72: 24418706
A73: Clinicos Programas De Atencion Integral SAS IPS | B73: 105867 | C73: 1 | D73: 436373
B74: 105871 | C74: 1 | D74: 4028328.5
A75: Total Clinicos Programas De Atencion Integral SAS IPS | C75: 2 | D75: 4464701.5
A76: Colinagro SA | B76: 105794 | C76: 1 | D76: 142800
B77: 105795 | C77: 1 | D77: 147560
B78: 105796 | C78: 1 | D78: 298571
B79: 106066 | C79: 1 | D79: 4331140
B80: 106380 | C80: 1 | D80: 287623
B81: 106640 | C81: 1 | D81: 1222400
B82: 106643 | C82: 1 | D82: 8717940
B83: 106776 | C83: 1 | D83: 292740
B84: 107001 | C84: 1 | D84: 1504993
B85: 107002 | C85: 1 | D85: 298571
A86: Total Colinagro SA | C86: 10 | D86: 17244338
A87: Comercializadora Colombiana De Carbones Y Coques SAS C I | B87: 106188 | C87: 1 | D87: 487900
B88: 106795 | C88: 1 | D88: 1382780
A89: Total Comercializadora Colombiana De Carbones Y Coques SAS C I | C89: 2 | D89: 1870680
A90: Compañia De Medicina Prepagada Colsanitas SA | B90: 105945 | C90: 1 | D90: 164354.47
B91: 106344 | C91: 1 | D91: 2337439.6
A92: Total Compañia De Medicina Prepagada Colsanitas SA | C92: 2 | D92: 2501794.1
A93: Compañia De Seguros Colsanitas SA | B93: 106342 | C93: 1 | D93: 4674879.3
B94: 106343 | C94: 1 | D94: 9349758.6
A95: Total Compañia De Seguros Colsanitas SA | C95: 2 | D95: 14024638
A96: Consultec International Sucursal Colombia | B96: 106307 | C96: 1 | D96: 19873000
A97: Total Consultec International Sucursal Colombia | C97: 1 | D97: 19873000
A98: Cooperativa De Empleados de Cafam | B98: 107188 | C98: 1 | D98: 1560229.8
A99: Total Cooperativa De Empleados de Cafam | C99: 1 | D99: 1560229.8
A100: Coopervision Colombia SAS | B100: 106630 | C100: 1 | D100: 2406744.1
A101: Total Coopervision Colombia SAS | C101: 1 | D101: 2406744.1
...

Sheet SIN ACUSE
A1: SIN ACUSE | B1: (Varios elementos)
A3: Nombre Receptor | B3: Folio | C3: Cuenta de SIN ACUSE | D3: Suma de Total
A4: 24K Global Logistics SAS | B4: 106603 | C4: 1 | D4: 4606687.5
A5: Total 24K Global Logistics SAS | C5: 1 | D5: 4606687.5
A6: Accion Sociedad Fiduciaria SA | B6: 107562 | C6: 1 | D6: 9473114
B7: 107563 | C7: 1 | D7: 10370969
A8: Total Accion Sociedad Fiduciaria SA | C8: 2 | D8: 19844083
A9: ACI Proyectos SAS | B9: 106402 | C9: 1 | D9: 222789.42
B10: 106904 | C10: 1 | D10: 5116703.7
B11: 107206 | C11: 1 | D11: 916050.11
A12: Total ACI Proyectos SAS | C12: 3 | D12: 6255543.2
A13: Agencia De Aduanas Abc Repecev SAS Nivel 1 | B13: 106083 | C13: 1 | D13: 483140
B14: 106841 | C14: 1 | D14: 345100
B15: 106842 | C15: 1 | D15: 2520420
B16: 106951 | C16: 1 | D16: 357000
B17: 107112 | C17: 1 | D17: 454580
B18: 107230 | C18: 1 | D18: 85680
B19: 107541 | C19: 1 | D19: 724710
B20: 107542 | C20: 1 | D20: 454580
A21: Total Agencia De Aduanas Abc Repecev SAS Nivel 1 | C21: 8 | D21: 5425210
A22: Agricultura Y Servicios S A S | B22: 107113 | C22: 1 | D22: 928200
A23: Total Agricultura Y Servicios S A S | C23: 1 | D23: 928200
A24: Agrointegral Andina SAS | B24: 107114 | C24: 1 | D24: 3088050
A25: Total Agrointegral Andina SAS | C25: 1 | D25: 3088050
A26: Algranel SA | B26: 106825 | C26: 1 | D26: 1563660
A27: Total Algranel SA | C27: 1 | D27: 1563660
A28: Alimentos Thearion Suqa SAS | B28: 106394 | C28: 1 | D28: 838305.06
A29: Total Alimentos Thearion Suqa SAS | C29: 1 | D29: 838305.06
A30: Applus Norcontrol Colombia Limitada | B30: 105763 | C30: 1 | D30: 709047.93
B31: 105764 | C31: 1 | D31: 2903659.5
B32: 105765 | C32: 1 | D32: 1294922.3
B33: 105766 | C33: 1 | D33: 75105.66
B34: 105767 | C34: 1 | D34: 364454.16
B35: 105768 | C35: 1 | D35: 1142084.6
B36: 105769 | C36: 1 | D36: 416500
B37: 106025 | C37: 1 | D37: 221970.7
B38: 106026 | C38: 1 | D38: 63303.24
B39: 106027 | C39: 1 | D39: 260221.83
B40: 106169 | C40: 1 | D40: 114488.8
B41: 106234 | C41: 1 | D41: 499260.93
B42: 106472 | C42: 1 | D42: 2784124
... B57: 107034 | C57: 1 | D57: 1598406.8
A58: Total Applus Norcontrol Colombia Limitada | C58: 28 | D58: 54554323
A59: Aquia SAS | B59: 106683 | C59: 1 | D59: 1428000
B60: 107383 | C60: 1 | D60: 19800
A61: Total Aquia SAS | C61: 2 | D61: 1447800
A62: Area Limpia Distrito Capital SAS E.S.P | B62: 107289 | C62: 1 | D62: 1420000
B63: 107290 | C63: 1 | D63: 606900
A64: Total Area Limpia Distrito Capital SAS E.S.P | C64: 2 | D64: 2026900
A65: Astaf Auditores Y Consultores Contables SAS | B65: 106685 | C65: 1 | D65: 1071000
A66: Total Astaf Auditores Y Consultores Contables SAS | C66: 1 | D66: 1071000
A67: Atp Ingenieria SAS En Reorganizacion | B67: 106461 | C67: 1 | D67: 142800
B68: 106463 | C68: 1 | D68: 965000
B69: 107147 | C69: 1 | D69: 517650
A70: Total Atp Ingenieria SAS En Reorganizacion | C70: 3 | D70: 1625450
A71: Banco Caja Social SA | B71: 107529 | C71: 1 | D71: 41644336
A72: Total Banco Caja Social SA | C72: 1 | D72: 41644336
A73: Bandas Y Elasticos Bandel SAS | B73: 107288 | C73: 1 | D73: 208607
B74: 107295 | C74: 1 | D74: 356006.14
A75: Total Bandas Y Elasticos Bandel SAS | C75: 2 | D75: 564613.14
A76: Bawer Company SAS | B76: 106441 | C76: 1 | D76: 8068200
A77: Total Bawer Company SAS | C77: 1 | D77: 8068200
A78: Beauty International Brands SAS | B78: 106650 | C78: 1 | D78: 396714.08
B79: 107096 | C79: 1 | D79: 183557.5
B80: 107266 | C80: 1 | D80: 507948.98
B81: 107267 | C81: 1 | D81: 577152.6
B82: 107587 | C82: 1 | D82: 806838.22
A83: Total Beauty International Brands SAS | C83: 5 | D83: 2472211.4
A84: Belltech Colombia SA | B84: 106187 | C84: 1 | D84: 653310
B85: 106375 | C85: 1 | D85: 4452980
A86: Total Belltech Colombia SA | C86: 2 | D86: 5106290
A87: Bold Co SAS | B87: 107473 | C87: 1 | D87: 13685000
A88: Total Bold Co SAS | C88: 1 | D88: 13685000
A89: Bongo Analytics SAS | B89: 106135 | C89: 1 | D89: 3209430
A90: Total Bongo Analytics SAS | C90: 1 | D90: 3209430
A91: Boydorr SAS | B91: 106623 | C91: 1 | D91: 6182823.5
A92: Total Boydorr SAS | C92: 1 | D92: 6182823.5
A93: BR Group SA | B93: 107514 | C93: 1 | D93: 1278655
A94: Total BR Group SA | C94: 1 | D94: 1278655
A95: Buk Col SAS | B95: 105734 | C95: 1 | D95: 2784600
A96: Total Buk Col SAS | C96: 1 | D96: 2784600
A97: Cabarria IQA SAS | B97: 105787 | C97: 1 | D97: 154700
B98: 105788 | C98: 1 | D98: 16921800
A99: Total Cabarria IQA SAS | C99: 2 | D99: 17076500
A100: Carboinsa SAS | B100: 107447 | C100: 1 | D100: 5355846.5
A101: Total Carboinsa SAS | C101: 1 | D101: 5355846.5
A102: Casahidalgo Constructores SAS | B102: 107239 | C102: 1 | D102: 4878055.1
B103: 107460 | C103: 1 | D103: 717552.6
A104: Total Casahidalgo Constructores SAS | C104: 2 | D104: 5595607.7
A105: Castro Y Rincon SAS | B105: 107345 | C105: 1 | D105: 1683255
A106: Total Castro Y Rincon SAS | C106: 1 | D106: 1683255
A107: Centro Recreacional De Oficiales Bogota | B107: 107572 | C107: 1 | D107: 4588360
A108: Total Centro Recreacional De Oficiales Bogota | C108: 1 | D108: 4588360
A109: Ceramica San Lorenzo Industrial De Colombia SA | B109: 107556 | C109: 1 | D109: 2123674
A110: Total Ceramica San Lorenzo Industrial De Colombia SA | C110: 1 | D110: 2123674
A111: Cheil Colombia | B111: 107045 | C111: 1 | D111: 4163203.1
A112: Total Cheil Colombia | C112: 1 | D112: 4163203.1
A113: City Parking SAS | B113: 106232 | C113: 1 | D113: 6677249.5
A114: Total City Parking SAS | C114: 1 | D114: 6677249.5
A115: Colinagro SA | B115: 107410 | C115: 1 | D115: 183855
...

Sheet Detalle2
A1: Detalles para Cuenta de RECHAZADA - Folio: 106231, Nombre Receptor: City Parking SAS, RECHAZADA: X
A3: Tipo de documento | B3: CUFE/CUDE | C3: Folio | D3: Columna1 | E3: Prefijo | F3: Fecha Emisión | G3: Fecha Recepción | H3: NIT Emisor | I3: Nombre Emisor | J3: NIT Receptor | K3: Nombre Receptor | L3: IVA | M3: ICA | N3: IPC | O3: Total | P3: Estado | Q3: Grupo | R3: 1 ACUSE | S3: 2 ACUSE | T3: 3 ACUSE | U3: RECHAZADA | V3: SIN ACUSE | W3: YA PAGA EN SISTEMA | X3: OBSERVACIONES
A4: Factura electrónica | B4: cf0fd6f3c49f1f76926a635cef10106f442ee6dfced1b864a4769c763ffe2d133313cee363ca7547f63a3bab587bb776 | C4: 106231 | D4: -1 | E4: FVE | F4: 05-02-2026 | G4: 05-02-2026 12:16:53 | H4: 900800595 | I4: Provexpress SAS | J4: 830050619 | K4: City Parking SAS | L4: 169130.97 | M4: 0 | N4: 0 | O4: 1059294 | P4: Aprobado con notificación | Q4: Emitido | U4: X

Sheet RECHAZADAS
A1: RECHAZADA | B1: X
A3: Nombre Receptor | B3: Folio | C3: Cuenta de RECHAZADA | D3: Suma de Total
A4: Agencia De Aduanas Abc Repecev SAS Nivel 1 | B4: 107129 | C4: 1 | D4: 483140
A5: Total Agencia De Aduanas Abc Repecev SAS Nivel 1 | C5: 1 | D5: 483140
A6: City Parking SAS | B6: 106231 | C6: 1 | D6: 1059294
B7: 106466 | C7: 1 | D7: 3213000
B8: 106468 | C8: 1 | D8: 2600000
A9: Total City Parking SAS | C9: 3 | D9: 6872294
A10: Comercializadora Colombiana De Carbones Y Coques SAS C I | B10: 106201 | C10: 1 | D10: 1382780
A11: Total Comercializadora Colombiana De Carbones Y Coques SAS C I | C11: 1 | D11: 1382780
A12: Construcciones Arrecife SAS | B12: 106928 | C12: 1 | D12: 246925
A13: Total Construcciones Arrecife SAS | C13: 1 | D13: 246925
A14: Editorial Santillana SAS | B14: 105693 | C14: 1 | D14: 6651505.6
B15: 105694 | C15: 1 | D15: 39432998
B16: 105695 | C16: 1 | D16: 74317600
B17: 105696 | C17: 1 | D17: 44351417
B18: 105697 | C18: 1 | D18: 1.2997053e+08
B19: 105701 | C19: 1 | D19: 22876309
B20: 105703 | C20: 1 | D20: 19887655
B21: 105704 | C21: 1 | D21: 8405629.3
B22: 105706 | C22: 1 | D22: 58579239
B23: 105707 | C23: 1 | D23: 2.6433606e+08
B24: 105708 | C24: 1 | D24: 37015200
B25: 105709 | C25: 1 | D25: 12105470
B26: 105710 | C26: 1 | D26: 13537785
... B34: 106292 | C34: 1 | D34: 67008783
A35: Total Editorial Santillana SAS | C35: 21 | D35: 1.0462382e+09
A36: Fitness24seven Colombia S A S | B36: 106735 | C36: 1 | D36: 12100694
A37: Total Fitness24seven Colombia S A S | C37: 1 | D37: 12100694
A38: Heel Colombia Ltda | B38: 106098 | C38: 1 | D38: 983178
A39: Total Heel Colombia Ltda | C39: 1 | D39: 983178
A40: Industria Nacional De Gaseosas SA | B40: 107051 | C40: 1 | D40: 3067848.6
A41: Total Industria Nacional De Gaseosas SA | C41: 1 | D41: 3067848.6
A42: Kata SAS | B42: 106356 | C42: 1 | D42: 116620
A43: Total Kata SAS | C43: 1 | D43: 116620
A44: Lipesa Colombia SAS | B44: 107315 | C44: 1 | D44: 4281620
B45: 107353 | C45: 1 | D45: 110670
A46: Total Lipesa Colombia SAS | C46: 2 | D46: 4392290
A47: Patrimonios Autonomos Fiduciaria Bancolombia SA Sociedad Fiduciaria | B47: 106491 | C47: 1 | D47: 1.1934655e+08
A48: Total Patrimonios Autonomos Fiduciaria Bancolombia SA Sociedad Fiduciaria | C48: 1 | D48: 1.1934655e+08
A49: Promotora Caledonia SAS | B49: 107310 | C49: 1 | D49: 374691.03
A50: Total Promotora Caledonia SAS | C50: 1 | D50: 374691.03
A51: Stefanini Colombia SAS | B51: 106801 | C51: 1 | D51: 1200959.9
A52: Total Stefanini Colombia SAS | C52: 1 | D52: 1200959.9
A53: Actual Constructora SAS | B53: 105852 | C53: 1 | D53: 172550
A54: Total Actual Constructora SAS | C54: 1 | D54: 172550
A55: Actual Colombia Inmobiliaria SAS | B55: 106556 | C55: 1 | D55: 172550
B56: 106560 | C56: 1 | D56: 690200
A57: Total Actual Colombia Inmobiliaria SAS | C57: 2 | D57: 862750
A58: Mct SAS | B58: 106931 | C58: 1 | D58: 379610
A59: Total Mct SAS | C59: 1 | D59: 379610
A60: MPS Mayorista De Colombia SA | B60: 106255 | C60: 1 | D60: 162363.6
A61: Total MPS Mayorista De Colombia SA | C61: 1 | D61: 162363.6
A62: Comercializadora Arturo Calle SAS | B62: 107090 | C62: 1 | D62: 2499000
A63: Total Comercializadora Arturo Calle SAS | C63: 1 | D63: 2499000
A64: Despegar Colombia S A S | B64: 106563 | C64: 1 | D64: 11243560
A65: Total Despegar Colombia S A S | C65: 1 | D65: 11243560
A66: Constructora Experta SAS | B66: 106448 | C66: 1 | D66: 1197041.6
A67: Total Constructora Experta SAS | C67: 1 | D67: 1197041.6
A68: Ix Comercio Colombia SAS | B68: 107272 | C68: 1 | D68: 8752212
A69: Total Ix Comercio Colombia SAS | C69: 1 | D69: 8752212
A70: Soldepye Soluciones De Potencia E Ingenieria SAS | B70: 106982 | C70: 1 | D70: 1666000
A71: Total Soldepye Soluciones De Potencia E Ingenieria SAS | C71: 1 | D71: 1666000
A72: Concremack SAS | B72: 107255 | C72: 1 | D72: 354264.19
A73: Total Concremack SAS | C73: 1 | D73: 354264.19
A74: Fundacion Universitaria San Martin | B74: 107390 | C74: 1 | D74: 63519021
B75: 107392 | C75: 1 | D75: 73731878
A76: Total Fundacion Universitaria San Martin | C76: 2 | D76: 1.372509e+08
A77: Total general | C77: 49 | D77: 1.3613464e+09

Sheet PAGAS EN SISTEMA
A1: YA PAGA EN SISTEMA | B1: (Varios elementos)
A3: Nombre Receptor | B3: Folio | C3: Cuenta de YA PAGA EN SISTEMA | D3: Suma de Total
A4: Accion Sociedad Fiduciaria SA | B4: 107443 | C4: 1 | D4: 1234200
A5: Total Accion Sociedad Fiduciaria SA | C5: 1 | D5: 1234200
A6: Agencia De Aduanas Abc Repecev SAS Nivel 1 | B6: 106851 | C6: 1 | D6: 90440
A7: Total Agencia De Aduanas Abc Repecev SAS Nivel 1 | C7: 1 | D7: 90440
A8: Agunsa Colombia SAS | B8: 105894 | C8: 1 | D8: 14458500
B9: 106237 | C9: 1 | D9: 297500
A10: Total Agunsa Colombia SAS | C10: 2 | D10: 14756000
A11: Arcelor Mittal International Colombia SAS | B11: 107044 | C11: 1 | D11: 318298.4
A12: Total Arcelor Mittal International Colombia SAS | C12: 1 | D12: 318298.4
A13: Axa Colpatria Seguros De Vida SA | B13: 105680 | C13: 1 | D13: 7931301
A14: Total Axa Colpatria Seguros De Vida SA | C14: 1 | D14: 7931301
A15: Bmi Colombia Compañia De Seguros De Vida SA | B15: 105948 | C15: 1 | D15: 5434135
B16: 106713 | C16: 1 | D16: 29864985
A17: Total Bmi Colombia Compañia De Seguros De Vida SA | C17: 2 | D17: 35299120
A18: Buk Col SAS | B18: 105733 | C18: 1 | D18: 10829000
A19: Total Buk Col SAS | C19: 1 | D19: 10829000
A20: Cardif Colombia Seguros Generales SA | B20: 107181 | C20: 1 | D20: 6147094.9
A21: Total Cardif Colombia Seguros Generales SA | C21: 1 | D21: 6147094.9
A22: Consejo Profesional De Biologia | B22: 105772 | C22: 1 | D22: 318682
A23: Total Consejo Profesional De Biologia | C23: 1 | D23: 318682
A24: Conservation International Foundation | B24: 106037 | C24: 1 | D24: 940100
B25: 106574 | C25: 1 | D25: 2038470
B26: 106676 | C26: 1 | D26: 279650
A27: Total Conservation International Foundation | C27: 3 | D27: 3258220
A28: Cooperativa Del Magisterio Codema | B28: 106131 | C28: 1 | D28: 19608820
A29: Total Cooperativa Del Magisterio Codema | C29: 1 | D29: 19608820
A30: Cooperativa Nacional De Droguistas Detallistas | B30: 105920 | C30: 1 | D30: 15606857
B31: 105921 | C31: 1 | D31: 2225300
B32: 105922 | C32: 1 | D32: 16476278
B33: 106815 | C33: 1 | D33: 4867385.6
B34: 106816 | C34: 1 | D34: 33422340
B35: 106817 | C35: 1 | D35: 4648140
A36: Total Cooperativa Nacional De Droguistas Detallistas | C36: 6 | D36: 77246301
A37: Corporacion Universitaria De Asturias | B37: 106528 | C37: 1 | D37: 1256640
A38: Total Corporacion Universitaria De Asturias | C38: 1 | D38: 1256640
A39: Croydon Colombia SA | B39: 105989 | C39: 1 | D39: 157997.49
A40: Total Croydon Colombia SA | C40: 1 | D40: 157997.49
A41: Digital Copy Soluciones Digitales SAS | B41: 106691 | C41: 1 | D41: 208250
A42: Total Digital Copy Soluciones Digitales SAS | C42: 1 | D42: 208250
A43: Doris Jeannet Urrego Amortegui | B43: 106312 | C43: 1 | D43: 109519.28
A44: Total Doris Jeannet Urrego Amortegui | C44: 1 | D44: 109519.28
A45: Embajada De La República Federal De Alemania | B45: 105967 | C45: 1 | D45: 2677500
A46: Total Embajada De La República Federal De Alemania | C46: 1 | D46: 2677500
A47: Endress+Hauser Colombia SAS | B47: 105990 | C47: 1 | D47: 1047543
A48: Total Endress+Hauser Colombia SAS | C48: 1 | D48: 1047543
A49: Exlservice Colombia SAS | B49: 106511 | C49: 1 | D49: 63837990
B50: 106964 | C50: 1 | D50: 92462804
A51: Total Exlservice Colombia SAS | C51: 2 | D51: 1.5630079e+08
A52: FCL Impart SAS | B52: 105754 | C52: 1 | D52: 10909920
A53: Total FCL Impart SAS | C53: 1 | D53: 10909920
A54: General Business Machines De Colombia SAS | B54: 105720 | C54: 1 | D54: 431336.58
A55: Total General Business Machines De Colombia SAS | C55: 1 | D55: 431336.58
A56: Grupo Babel Colombia SAS | B56: 106496 | C56: 1 | D56: 180544.5
B57: 106497 | C57: 1 | D57: 144130.42
A58: Total Grupo Babel Colombia SAS | C58: 2 | D58: 324674.92
A59: Hire Horatio Co S A S | B59: 106400 | C59: 1 | D59: 388445.75
B60: 106975 | C60: 1 | D60: 101269
A61: Total Hire Horatio Co S A S | C61: 2 | D61: 489714.75
A62: Iglesia Cristiana De Los Testigos De Jehova | B62: 107285 | C62: 1 | D62: 3236800
A63: Total Iglesia Cristiana De Los Testigos De Jehova | C63: 1 | D63: 3236800
A64: Indra Colombia SAS | B64: 106799 | C64: 1 | D64: 5523980
A65: Total Indra Colombia SAS | C65: 1 | D65: 5523980
A66: Inter Rapidisimo SA | B66: 105973 | C66: 1 | D66: 27132000
B67: 105974 | C67: 1 | D67: 4657636.2
B68: 105975 | C68: 1 | D68: 620398.17
B69: 105976 | C69: 1 | D69: 229194
B70: 105977 | C70: 1 | D70: 317333.73
B71: 105978 | C71: 1 | D71: 324546.32
B72: 105979 | C72: 1 | D72: 4416758.8
B73: 105980 | C73: 1 | D73: 839504.54
B74: 106076 | C74: 1 | D74: 229194
B75: 106173 | C75: 1 | D75: 4261045
B76: 106545 | C76: 1 | D76: 973052
A77: Total Inter Rapidisimo SA | C77: 11 | D77: 44000663
A78: Interasesores Asesores Empresariales Administrativos SA | B78: 106162 | C78: 1 | D78: 335829.9
B79: 106163 | C79: 1 | D79: 490256.2
A80: Total Interasesores Asesores Empresariales Administrativos SA | C80: 2 | D80: 826086.1
A81: Isi Emerging Markets Colombia SAS | B81: 105880 | C81: 1 | D81: 603330
A82: Total Isi Emerging Markets Colombia SAS | C82: 1 | D82: 603330
A83: Javier Antonio Cortes Murcia | B83: 106213 | C83: 1 | D83: 120395.97
A84: Total Javier Antonio Cortes Murcia | C84: 1 | D84: 120395.97
A85: Leidy Astrid Jimenez Ossa | B85: 106607 | C85: 1 | D85: 701521.66
B86: 106838 | C86: 1 | D86: 65791.53
A87: Total Leidy Astrid Jimenez Ossa | C87: 2 | D87: 767313.19
A88: Logysteel Operador Logistico SAS | B88: 105723 | C88: 1 | D88: 2494500
B89: 105872 | C89: 1 | D89: 7450500
B90: 106682 | C90: 1 | D90: 2419746
A91: Total Logysteel Operador Logistico SAS | C91: 3 | D91: 12364746
A92: Mario Reyes Gutierrez | B92: 106657 | C92: 1 | D92: 101507
A93: Total Mario Reyes Gutierrez | C93: 1 | D93: 101507
A94: Multipagas SAS | B94: 106326 | C94: 1 | D94: 7442260
A95: Total Multipagas SAS | C95: 1 | D95: 7442260
A96: Novasoft S A S | B96: 105819 | C96: 1 | D96: 1610749.1
B97: 105854 | C97: 1 | D97: 2322880
A98: Total Novasoft S A S | C98: 2 | D98: 3933629.1
A99: Novomatic Gaming Colombia SAS | B99: 106268 | C99: 1 | D99: 4097077.2
B100: 106269 | C100: 1 | D100: 585291.98
B101: 107225 | C101: 1 | D101: 1261878.4
...
