Workbook

Sheet MATRIZ MARZO
A1: CONCEPTOS | B1: CANTIDAD | C1: VALOR TOTAL
A2: RECHAZADAS | B2: =GETPIVOTDATA("Cuenta de RECHAZADA",RECHAZADAS!$A$3) -> #REF! | C2: =GETPIVOTDATA("Suma de Total",RECHAZADAS!$A$3) -> 1304825.5
A3: 3 ACUSES | B3: =GETPIVOTDATA("Cuenta de 3 ACUSE",'3 ACUSES'!$A$3) -> 117 | C3: =GETPIVOTDATA("Suma de Total",'3 ACUSES'!$A$3) -> 2.2794473e+08
A4: 2 ACUSES | B4: =GETPIVOTDATA("Cuenta de 2 ACUSE",'2 ACUSES'!$A$3) -> 21 | C4: =GETPIVOTDATA("Suma de Total",'2 ACUSES'!$A$3) -> 3.5236346e+08
A5: 1 ACUSE | B5: =GETPIVOTDATA("Cuenta de 1 ACUSE",'1 ACUSE'!$A$3) -> 212 | C5: =GETPIVOTDATA("Suma de Total",'1 ACUSE'!$A$3) -> 1.3496895e+09
A6: SIN ACUSE | B6: =GETPIVOTDATA("Cuenta de SIN ACUSE",'SIN ACUSE'!$A$3) -> 1688 | C6: =GETPIVOTDATA("Suma de Total",'SIN ACUSE'!$A$3) -> 7.1599157e+09
A7: PAGAS EN SISTEMA | B7: =GETPIVOTDATA("Cuenta de YA PAGA EN SISTEMA",'PAGAS EN SISTEMA'!$A$1) -> 0 | C7: =GETPIVOTDATA("Suma de Total",'PAGAS EN SISTEMA'!$A$3) -> 9.0900214e+09
B8: =SUM(B2:B7) -> #REF! | C8: =SUM(C2:C7) -> 1.818124e+10
A10: Tipo de documento | B10: CUFE/CUDE | C10: Folio | D10: Columna1 | E10: Prefijo | F10: Fecha Emisión | G10: Fecha Recepción | H10: NIT Emisor | I10: Nombre Emisor | J10: NIT Receptor | K10: Nombre Receptor | L10: IVA | M10: ICA | N10: Total | O10: Estado | P10: Grupo | Q10: 1 ACUSE | R10: 2 ACUSE | S10: 3 ACUSE | T10: RECHAZADA | U10: SIN ACUSE | V10: YA PAGA EN SISTEMA | W10: OBSERVACIONES | X10: ESTADO2
A11: Factura electrónica | B11: 3758541101d1e2d69232eff132df32489d8ab73ed2619379a6c2ced87d8aa51b47d38ff235acbdc4c1b90768e067b54c | C11: 107597 | D11: =C11-C12 -> -1 | E11: FVE | F11: 02-03-2026 | G11: 02-03-2026 07:03:23 | H11: 900800595 | I11: Provexpress SAS | J11: 890333023 | K11: Siderurgica Del Occidente SAS Sidoc SAS | L11: 54440.7 | M11: 0 | N11: 340970.7 | O11: Aprobado con notificación | P11: Emitido | Q11: x | X11: =IFERROR(VLOOKUP(J10:J1902,[1]sheet1!$A:$K,11,0),"sin acuse") -> Recibo Bien y/o Servicio
A12: Factura electrónica | B12: 4388e89194096fd555bada7968b607e24e1baa4934b6013e84c1c9c5267f72249c419e4187d638adb2817edb17f2436b | C12: 107598 | D12: =C12-C13 -> -1 | E12: FVE | F12: 02-03-2026 | G12: 02-03-2026 07:03:28 | H12: 900800595 | I12: Provexpress SAS | J12: 830513366 | K12: Newsat SAS | L12: 85842 | M12: 0 | N12: 537642 | O12: Aprobado con notificación | P12: Emitido | S12: x | W12: se envia correo al ciente | X12: =IFERROR(VLOOKUP(J11:J1903,[1]sheet1!$A:$K,11,0),"sin acuse") -> sin acuse
A13: Factura electrónica | B13: 35ba599dff3e14960da1a882fdfbc3e4e3b28626fdad619ab3bdf68687447f1b186aa8dfb024e92d621a50d0467fb2e7 | C13: 107599 | D13: =C13-C14 -> -1 | E13: FVE | F13: 02-03-2026 | G13: 02-03-2026 07:03:32 | H13: 900800595 | I13: Provexpress SAS | J13: 860031699 | K13: Vitro Colombia SAS | L13: 20064 | M13: 0 | N13: 125664 | O13: Aprobado con notificación | P13: Emitido | S13: x | X13: =IFERROR(VLOOKUP(J12:J1904,[1]sheet1!$A:$K,11,0),"sin acuse") -> Aceptacion Expresa
A14: Factura electrónica | B14: 1f8378e7c4a9d365bb9e90b8294758634ebe1e07c5511e47d92187e0091f4a58eedbd0352201603c89e91faad7f0ca94 | C14: 107600 | D14: =C14-C15 -> -1 | E14: FVE | F14: 02-03-2026 | G14: 46083.294 | H14: 900800595 | I14: Provexpress SAS | J14: 900396965 | K14: Agroindustrial De Palma Aceitera SA Sucursal Colombia | L14: 23940 | M14: 0 | N14: 149940 | O14: Aprobado con notificación | P14: Emitido | S14: x | X14: =IFERROR(VLOOKUP(J13:J1905,[1]sheet1!$A:$K,11,0),"sin acuse") -> Aceptacion Expresa
A15: Factura electrónica | B15: 42c16285c8279dcf8d699cc6c97a3469ad61694e81fdcb60c72e298331e5bd719a87340798d5b10008b5ec039e6b9018 | C15: 107601 | D15: =C15-C16 -> -1 | E15: FVE | F15: 02-03-2026 | G15: 02-03-2026 07:03:41 | H15: 900800595 | I15: Provexpress SAS | J15: 860023264 | K15: Securitas Colombia SA | L15: 58710 | M15: 0 | N15: 2362710 | O15: Aprobado con notificación | P15: Emitido | Q15: X | X15: =IFERROR(VLOOKUP(J14:J1906,[1]sheet1!$A:$K,11,0),"sin acuse") -> Acuse Recibo
A16: Factura electrónica | B16: c8cf81337c2d266fceab81e803a44b05a480174e1744c2450d324343f46cf679b4c4a1d545c43188e8dee58304420c54 | C16: 107602 | D16: =C16-C17 -> -1 | E16: FVE | F16: 02-03-2026 | G16: 02-03-2026 07:03:46 | H16: 900800595 | I16: Provexpress SAS | J16: 860023264 | K16: Securitas Colombia SA | L16: 58710 | M16: 0 | N16: 2362710 | O16: Aprobado con notificación | P16: Emitido | Q16: X | X16: =IFERROR(VLOOKUP(J15:J1907,[1]sheet1!$A:$K,11,0),"sin acuse") -> Acuse Recibo
A17: Factura electrónica | B17: 276f6ea62b6379d8410370511351a243b8874cb9b5215bc7ced3e2acd6648a83dd02af25519ffa8d7c0cdb0ec58db1b0 | C17: 107603 | D17: =C17-C18 -> -1 | E17: FVE | F17: 02-03-2026 | G17: 02-03-2026 07:03:50 | H17: 900800595 | I17: Provexpress SAS | J17: 860023264 | K17: Securitas Colombia SA | L17: 39140 | M17: 0 | N17: 1575140 | O17: Aprobado con notificación | P17: Emitido | Q17: X | X17: =IFERROR(VLOOKUP(J16:J1908,[1]sheet1!$A:$K,11,0),"sin acuse") -> Acuse Recibo
A18: Factura electrónica | B18: bfc426cad854dea842cb25ca57a25b26129c268dcb41fadba6176369cc73978274b318568f5d22c095017d6a6efd8fe9 | C18: 107604 | D18: =C18-C19 -> -1 | E18: FVE | F18: 02-03-2026 | G18: 02-03-2026 07:03:55 | H18: 900800595 | I18: Provexpress SAS | J18: 860023264 | K18: Securitas Colombia SA | L18: 78280 | M18: 0 | N18: 3150280 | O18: Aprobado con notificación | P18: Emitido | S18: X | X18: =IFERROR(VLOOKUP(J17:J1909,[1]sheet1!$A:$K,11,0),"sin acuse") -> Acuse Recibo
A19: Factura electrónica | B19: 3fb423db44c410d711667dd059b92afc03ac778bcda1663c2302592706c5797d18448414f03a426eb53f9a5bd2249c44 | C19: 107605 | D19: =C19-C20 -> -1 | E19: FVE | F19: 02-03-2026 | G19: 02-03-2026 07:03:59 | H19: 900800595 | I19: Provexpress SAS | J19: 860023264 | K19: Securitas Colombia SA | L19: 19570 | M19: 0 | N19: 787570 | O19: Aprobado con notificación | P19: Emitido | Q19: X | X19: =IFERROR(VLOOKUP(J18:J1910,[1]sheet1!$A:$K,11,0),"sin acuse") -> Acuse Recibo
A20: Factura electrónica | B20: 9973d12d7e8050416731a7bdbef8066c4bd1064a2cb2b2998717fa882f00acc20034e1e284bd341b76ec3b7ebc924fe5 | C20: 107606 | D20: =C20-C21 -> -1 | E20: FVE | F20: 02-03-2026 | G20: 02-03-2026 07:04:06 | H20: 900800595 | I20: Provexpress SAS | J20: 830077655 | K20: Panamericana Outsourcing SA | L20: 129060.73 | M20: 0 | N20: 808327.73 | O20: Aprobado con notificación | P20: Emitido | Q20: X | X20: =IFERROR(VLOOKUP(J19:J1911,[1]sheet1!$A:$K,11,0),"sin acuse") -> Acuse Recibo
A21: Factura electrónica | B21: 444417369daaf98106d64965126ccd1773530080d80c9964bf476d210e8953a4b794367bf215b48702cdfbc07fbc7579 | C21: 107607 | D21: =C21-C22 -> -1 | E21: FVE | F21: 02-03-2026 | G21: 02-03-2026 07:04:10 | H21: 900800595 | I21: Provexpress SAS | J21: 900396965 | K21: Agroindustrial De Palma Aceitera SA Sucursal Colombia | L21: 435480 | M21: 0 | N21: 2727480 | O21: Aprobado con notificación | P21: Emitido | S21: x | X21: =IFERROR(VLOOKUP(J20:J1912,[1]sheet1!$A:$K,11,0),"sin acuse") -> Aceptacion Expresa
A22: Factura electrónica | B22: e4558344b9bd98ca156e7d2b0a80deff43fc2fc7220d681e0e2b91725aab5987a301a9b814f00dfa62916a131fb4ee27 | C22: 107608 | D22: =C22-C23 -> -1 | E22: FVE | F22: 02-03-2026 | G22: 02-03-2026 07:04:16 | H22: 900800595 | I22: Provexpress SAS | J22: 860001615 | K22: Automundial SA | L22: 14250 | M22: 0 | N22: 89250 | O22: Aprobado con notificación | P22: Emitido | Q22: X | X22: =IFERROR(VLOOKUP(J21:J1913,[1]sheet1!$A:$K,11,0),"sin acuse") -> sin acuse
A23: Factura electrónica | B23: f3daba2d454d23e4cf17a3b2f47b236d255acedbfea51ffba10afb32276a117ed956f3d08b58de61d928064bb2319a45 | C23: 107609 | D23: =C23-C24 -> -1 | E23: FVE | F23: 02-03-2026 | G23: 02-03-2026 07:04:20 | H23: 900800595 | I23: Provexpress SAS | J23: 860031699 | K23: Vitro Colombia SAS | L23: 347548 | M23: 0 | N23: 2176748 | O23: Aprobado con notificación | P23: Emitido | S23: X | X23: =IFERROR(VLOOKUP(J22:J1914,[1]sheet1!$A:$K,11,0),"sin acuse") -> Aceptacion Expresa
A24: Factura electrónica | B24: 88149d6d5b109f2d229b117470f3e6c5be0d16e1a4d68566a0c60b312e181d8bb33294b455d028831188e1af3d21d40c | C24: 107610 | D24: =C24-C25 -> -1 | E24: FVE | F24: 02-03-2026 | G24: 02-03-2026 07:04:24 | H24: 900800595 | I24: Provexpress SAS | J24: 860056869 | K24: Cooperativa De Ahorro Y Credito Crediflores | L24: 19760 | M24: 0 | N24: 123760 | O24: Aprobado con notificación | P24: Emitido | S24: x | U24: X | W24: se envia correo al ciente | X24: =IFERROR(VLOOKUP(J23:J1915,[1]sheet1!$A:$K,11,0),"sin acuse") -> sin acuse
A25: Factura electrónica | B25: b24d1dce927474be9e7007de0ce10a3044e4adf059eb438eb5390691b8d9457d46c9680a09873143cf395139e583a8df | C25: 107611 | D25: =C25-C26 -> -1 | E25: FVE | F25: 02-03-2026 | G25: 02-03-2026 07:19:33 | H25: 900800595 | I25: Provexpress SAS | J25: 860513970 | K25: Comercializadora Internacional Milpa SA | L25: 91770 | M25: 0 | N25: 574770 | O25: Aprobado con notificación | P25: Emitido | Q25: X | X25: =IFERROR(VLOOKUP(J24:J1916,[1]sheet1!$A:$K,11,0),"sin acuse") -> Aceptacion Expresa
A26: Factura electrónica | B26: 794a289160cb70e5cf3b4e62da499db166e811ffefa210f9e130344695274e4db23852ea3e055c4a57256c60648dbe30 | C26: 107612 | D26: =C26-C27 -> -1 | E26: FVE | F26: 02-03-2026 | G26: 02-03-2026 07:19:38 | H26: 900800595 | I26: Provexpress SAS | J26: 830109997 | K26: Otto Bock Healthcare Andina SAS | L26: 19000 | M26: 0 | N26: 119000 | O26: Aprobado con notificación | P26: Emitido | U26: X | W26: Se envia correo al cliente | X26: =IFERROR(VLOOKUP(J25:J1917,[1]sheet1!$A:$K,11,0),"sin acuse") -> Sin Evento
A27: Factura electrónica | B27: 1df69dc95a8401394834ab3908c8ece32908743e5ca9cfc1353f2ccc4ebecd2a0bbfd181c4d24c3321015bc632665dad | C27: 107613 | D27: =C27-C28 -> -1 | E27: FVE | F27: 02-03-2026 | G27: 02-03-2026 07:19:42 | H27: 900800595 | I27: Provexpress SAS | J27: 900206480 | K27: Ingetec Ingenieria & Diseños SAS | L27: 4436.5 | M27: 0 | N27: 27786.5 | O27: Aprobado con notificación | P27: Emitido | U27: X | W27: se envia correo al cliente | X27: =IFERROR(VLOOKUP(J26:J1918,[1]sheet1!$A:$K,11,0),"sin acuse") -> Acuse Recibo
A28: Factura electrónica | B28: 4a0a67ffc46ce2dd7439195de79d9e2d8ad3938550d85470c7e64e47bd66ce25b98db2ebb85fc22a6faef129465bef54 | C28: 107614 | D28: =C28-C29 -> -1 | E28: FVE | F28: 02-03-2026 | G28: 02-03-2026 07:19:47 | H28: 900800595 | I28: Provexpress SAS | J28: 860017005 | K28: Challenger SAS | L28: 22800 | M28: 0 | N28: 142800 | O28: Aprobado con notificación | P28: Emitido | Q28: X | X28: =IFERROR(VLOOKUP(J27:J1919,[1]sheet1!$A:$K,11,0),"sin acuse") -> Aceptacion Expresa
A29: Factura electrónica | B29: 89ae5508147e9072a59cfa50447221942213e0b17f8d9fe2385c5f43c17c934e7eacb2072db8b86e577a5cab87e5d8da | C29: 107615 | D29: =C29-C30 -> -1 | E29: FVE | F29: 02-03-2026 | G29: 02-03-2026 07:19:51 | H29: 900800595 | I29: Provexpress SAS | J29: 860031699 | K29: Vitro Colombia SAS | L29: 231800 | M29: 0 | N29: 1451800 | O29: Aprobado con notificación | P29: Emitido | S29: X | X29: =IFERROR(VLOOKUP(J28:J1920,[1]sheet1!$A:$K,11,0),"sin acuse") -> Aceptacion Expresa
A30: Factura electrónica | B30: 035a5722c5509f6b0c11d0c5bf7725d2276e594b727b03e7983c7a425e3d3583d7da89e644544ebee051b85b50a8811d | C30: 107616 | D30: =C30-C31 -> -1 | E30: FVE | F30: 02-03-2026 | G30: 02-03-2026 07:19:56 | H30: 900800595 | I30: Provexpress SAS | J30: 860007336 | K30: Caja Colombiana De Subsidio Familiar Colsubsidio | L30: 31280.46 | M30: 0 | N30: 195914.46 | O30: Aprobado con notificación | P30: Emitido | S30: X | X30: =IFERROR(VLOOKUP(J29:J1921,[1]sheet1!$A:$K,11,0),"sin acuse") -> Aceptacion Expresa
A31: Factura electrónica | B31: 6c8ebfc79fdfdc5b3dca3921a4d55c4d837b01564d977dc46b5c59f8633ca4f52193d8ed2f9c8220962b87152e8fcff7 | C31: 107617 | D31: =C31-C32 -> -1 | E31: FVE | F31: 02-03-2026 | G31: 02-03-2026 07:20:00 | H31: 900800595 | I31: Provexpress SAS | J31: 860007336 | K31: Caja Colombiana De Subsidio Familiar Colsubsidio | L31: 31472.36 | M31: 0 | N31: 197116.36 | O31: Aprobado con notificación | P31: Emitido | S31: X | X31: =IFERROR(VLOOKUP(J30:J1922,[1]sheet1!$A:$K,11,0),"sin acuse") -> Aceptacion Expresa
A32: Factura electrónica | B32: 2bcefacbb756dea198f9c3fc8cdd287d213dff148b6301a60990edb9e1b66a015154c03db14dd52e7beefa945d71c048 | C32: 107618 | D32: =C32-C33 -> -1 | E32: FVE | F32: 02-03-2026 | G32: 02-03-2026 07:20:05 | H32: 900800595 | I32: Provexpress SAS | J32: 860007336 | K32: Caja Colombiana De Subsidio Familiar Colsubsidio | L32: 31472.36 | M32: 0 | N32: 197116.36 | O32: Aprobado con notificación | P32: Emitido | S32: X | X32: =IFERROR(VLOOKUP(J31:J1923,[1]sheet1!$A:$K,11,0),"sin acuse") -> Aceptacion Expresa
A33: Factura electrónica | B33: 73b318602f0ff45d2295099457ead2d23388fc157a97341c1a02b2b02bf87d84d547c378ee62b24c4418644a363ceed8 | C33: 107619 | D33: =C33-C34 -> -1 | E33: FVE | F33: 02-03-2026 | G33: 02-03-2026 07:20:37 | H33: 900800595 | I33: Provexpress SAS | J33: 860007336 | K33: Caja Colombiana De Subsidio Familiar Colsubsidio | L33: 31472.36 | M33: 0 | N33: 197116.36 | O33: Aprobado con notificación | P33: Emitido | S33: X | X33: =IFERROR(VLOOKUP(J32:J1924,[1]sheet1!$A:$K,11,0),"sin acuse") -> Aceptacion Expresa
A34: Factura electrónica | B34: a789a5dee17a4afa6e372b691115ab6adc630483baff6b5b66fd22870a243430602422bb7eafc0754efc0482c4ba8ed5 | C34: 107620 | D34: =C34-C35 -> -1 | E34: FVE | F34: 02-03-2026 | G34: 02-03-2026 07:20:37 | H34: 900800595 | I34: Provexpress SAS | J34: 860007336 | K34: Caja Colombiana De Subsidio Familiar Colsubsidio | L34: 31280.46 | M34: 0 | N34: 195914.46 | O34: Aprobado con notificación | P34: Emitido | S34: X | X34: =IFERROR(VLOOKUP(J33:J1925,[1]sheet1!$A:$K,11,0),"sin acuse") -> Aceptacion Expresa
A35: Factura electrónica | B35: 51e0dd67f709168072945bd54d6515ffe381fea0a407a9d01df003a0a8fd1cbafcddb7d008690745f89ea758e8342b33 | C35: 107621 | D35: =C35-C36 -> -1 | E35: FVE | F35: 02-03-2026 | G35: 02-03-2026 07:20:37 | H35: 900800595 | I35: Provexpress SAS | J35: 860007336 | K35: Caja Colombiana De Subsidio Familiar Colsubsidio | L35: 31280.46 | M35: 0 | N35: 195914.46 | O35: Aprobado con notificación | P35: Emitido | S35: X | X35: =IFERROR(VLOOKUP(J34:J1926,[1]sheet1!$A:$K,11,0),"sin acuse") -> Aceptacion Expresa
A36: Factura electrónica | B36: 555d5027e50dd73dee48cf73fed4ef228a78a50184b8cae1abb9b0911e6becdc462863cc2b32be64393238c1a4702790 | C36: 107622 | D36: =C36-C37 -> -1 | E36: FVE | F36: 02-03-2026 | G36: 02-03-2026 07:20:34 | H36: 900800595 | I36: Provexpress SAS | J36: 860007336 | K36: Caja Colombiana De Subsidio Familiar Colsubsidio | L36: 29687.5 | M36: 0 | N36: 185937.5 | O36: Aprobado con notificación | P36: Emitido | S36: X | X36: =IFERROR(VLOOKUP(J35:J1927,[1]sheet1!$A:$K,11,0),"sin acuse") -> Aceptacion Expresa
A37: Factura electrónica | B37: e163522c5da6e5452f1a1f396cb5f82bd65653d401a9fcd84e8cc9013c648edc515d0724fb756257950976cb117ab4dc | C37: 107623 | D37: =C37-C38 -> -1 | E37: FVE | F37: 02-03-2026 | G37: 02-03-2026 07:20:37 | H37: 900800595 | I37: Provexpress SAS | J37: 860007336 | K37: Caja Colombiana De Subsidio Familiar Colsubsidio | L37: 29141.06 | M37: 0 | N37: 182515.06 | O37: Aprobado con notificación | P37: Emitido | S37: X | X37: =IFERROR(VLOOKUP(J36:J1928,[1]sheet1!$A:$K,11,0),"sin acuse") -> Aceptacion Expresa
A38: Factura electrónica | B38: a9ffb6ffa5bb680aafa918cb7ad350a6d056965f07f090ed29c55fc8c00c9f65b62f0c474dfe05ac383b5c4e070111c4 | C38: 107624 | D38: =C38-C39 -> -1 | E38: FVE | F38: 02-03-2026 | G38: 02-03-2026 07:20:37 | H38: 900800595 | I38: Provexpress SAS | J38: 901847883 | K38: IA4 SAS | L38: 347600.82 | M38: 0 | N38: 2177078.8 | O38: Aprobado con notificación | P38: Emitido | Q38: X | X38: =IFERROR(VLOOKUP(J37:J1929,[1]sheet1!$A:$K,11,0),"sin acuse") -> Aceptacion Expresa
A39: Factura electrónica | B39: 6e29fef0a27509b6ee27040e09b192b818547f713d210226e06480f1df8481c71dab146c29cf461c70554cd1f221fade | C39: 107625 | D39: =C39-C40 -> -1 | E39: FVE | F39: 02-03-2026 | G39: 02-03-2026 07:20:39 | H39: 900800595 | I39: Provexpress SAS | J39: 800201648 | K39: Asesorias Servicios Ecologicos E Industriales SAS | L39: 78983.25 | M39: 0 | N39: 527406.25 | O39: Aprobado con notificación | P39: Emitido | Q39: X | X39: =IFERROR(VLOOKUP(J38:J1930,[1]sheet1!$A:$K,11,0),"sin acuse") -> Aceptacion Expresa
A40: Factura electrónica | B40: 4dddb3e5c086a8fe3e4479560eddb501d61277f788fdcfbb270de8365276bf382c90c693b472f1b72c3c972f9e284290 | C40: 107626 | D40: =C40-C41 -> -1 | E40: FVE | F40: 02-03-2026 | G40: 02-03-2026 07:20:42 | H40: 900800595 | I40: Provexpress SAS | J40: 830111257 | K40: Grupo Empresarial En Linea S.A. | L40: 89870 | M40: 0 | N40: 7778870 | O40: Aprobado con notificación | P40: Emitido | S40: X | X40: =IFERROR(VLOOKUP(J39:J1931,[1]sheet1!$A:$K,11,0),"sin acuse") -> Aceptacion Expresa
A41: Factura electrónica | B41: bf1f80ad8fd6439b6acc8281b55a9ae4d6f9c1e75a4e70846e3e2fce7a6a179b577e69b9521b6f8b3bc36129e0b4cc94 | C41: 107627 | D41: =C41-C42 -> -1 | E41: FVE | F41: 02-03-2026 | G41: 02-03-2026 07:35:50 | H41: 900800595 | I41: Provexpress SAS | J41: 860007336 | K41: Caja Colombiana De Subsidio Familiar Colsubsidio | L41: 49495 | M41: 0 | N41: 309995 | O41: Aprobado con notificación | P41: Emitido | S41: X | X41: =IFERROR(VLOOKUP(J40:J1932,[1]sheet1!$A:$K,11,0),"sin acuse") -> Aceptacion Expresa
A42: Factura electrónica | B42: 4385e7b13325ef0d0a3927b896d329a3e0e88e7c449d5add5934fd6eca68316d22b4bac6cf1130f9c5d8102e60561b8a | C42: 107628 | D42: =C42-C43 -> -1 | E42: FVE | F42: 02-03-2026 | G42: 02-03-2026 07:35:55 | H42: 900800595 | I42: Provexpress SAS | J42: 860007336 | K42: Caja Colombiana De Subsidio Familiar Colsubsidio | L42: 15124 | M42: 0 | N42: 94724 | O42: Aprobado con notificación | P42: Emitido | S42: X | X42: =IFERROR(VLOOKUP(J41:J1933,[1]sheet1!$A:$K,11,0),"sin acuse") -> Aceptacion Expresa
A43: Factura electrónica | B43: debb3f527bf65df7ec378f287f4c6583455a9032be02e5790af8406cf0a30cf32d66658cd3c88a749838a80900595061 | C43: 107629 | D43: =C43-C44 -> -1 | E43: FVE | F43: 02-03-2026 | G43: 02-03-2026 07:36:00 | H43: 900800595 | I43: Provexpress SAS | J43: 860007336 | K43: Caja Colombiana De Subsidio Familiar Colsubsidio | L43: 45372 | M43: 0 | N43: 284172 | O43: Aprobado con notificación | P43: Emitido | S43: X | X43: =IFERROR(VLOOKUP(J42:J1934,[1]sheet1!$A:$K,11,0),"sin acuse") -> Aceptacion Expresa
A44: Factura electrónica | B44: 30b1196c726a369bc52368948009eade55607abd13152124761ee2bc31d62df4c10b60992d0143a1da34abf3d5d73231 | C44: 107630 | D44: =C44-C45 -> -1 | E44: FVE | F44: 02-03-2026 | G44: 02-03-2026 07:36:05 | H44: 900800595 | I44: Provexpress SAS | J44: 900768933 | K44: Banco Mundo Mujer SA O Mundo Mujer El Banco De La Comunidad O Mundo Mujer | L44: 57891.1 | M44: 0 | N44: 362581.1 | O44: Aprobado con notificación | P44: Emitido | Q44: X | X44: =IFERROR(VLOOKUP(J43:J1935,[1]sheet1!$A:$K,11,0),"sin acuse") -> Aceptacion Expresa
A45: Factura electrónica | B45: ac15949239e3c843e6d174924e8eacb8dc5c1be9385d63118c8ab4fbff0f6ed61567821214148c65be351ab64399864d | C45: 107631 | D45: =C45-C46 -> -1 | E45: FVE | F45: 02-03-2026 | G45: 02-03-2026 07:36:10 | H45: 900800595 | I45: Provexpress SAS | J45: 830136065 | K45: Evertec Colombia SAS | L45: 7125 | M45: 0 | N45: 44625 | O45: Aprobado con notificación | P45: Emitido | S45: X | X45: =IFERROR(VLOOKUP(J44:J1936,[1]sheet1!$A:$K,11,0),"sin acuse") -> Acuse Recibo
A46: Factura electrónica | B46: fbdf611ef48bb73e808f7d83d65dceef47add57c8011b23fe545523e19af3ef225554bcae574daeaa4df6fee8f305760 | C46: 107632 | D46: =C46-C47 -> -1 | E46: FVE | F46: 02-03-2026 | G46: 02-03-2026 07:36:13 | H46: 900800595 | I46: Provexpress SAS | J46: 800193444 | K46: Ecologia Y Entorno SAS E.S.P Ecoentorno | L46: 161086.75 | M46: 0 | N46: 1008911.8 | O46: Aprobado con notificación | P46: Emitido | S46: X | X46: =IFERROR(VLOOKUP(J45:J1937,[1]sheet1!$A:$K,11,0),"sin acuse") -> Aceptacion Expresa
A47: Factura electrónica | B47: 232a4745fc85c186018b82e9d1197505a7d6fd621447c8051e6b7d718aad91a757b9b1c95c983734f60eed7e94598ab5 | C47: 107633 | D47: =C47-C48 -> -1 | E47: FVE | F47: 02-03-2026 | G47: 02-03-2026 07:36:18 | H47: 900800595 | I47: Provexpress SAS | J47: 900024398 | K47: Ecologistica SAS Empresa De Servicios Publicos Ecologistica SAS ESP | L47: 161086.75 | M47: 0 | N47: 1008911.8 | O47: Aprobado con notificación | P47: Emitido | S47: X | X47: =IFERROR(VLOOKUP(J46:J1938,[1]sheet1!$A:$K,11,0),"sin acuse") -> Aceptacion Expresa
A48: Factura electrónica | B48: 3c04f7a6f367999b5ea0856af627b539959223647f4901539b2dd0e7d44c7f4b3641a05ea3533344ac6912f842152b8e | C48: 107634 | D48: =C48-C49 -> -1 | E48: FVE | F48: 02-03-2026 | G48: 02-03-2026 07:36:22 | H48: 900800595 | I48: Provexpress SAS | J48: 860028415 | K48: La Equidad Seguros Generales Organismo Cooperativo | L48: 209000 | M48: 0 | N48: 1309000 | O48: Aprobado con notificación | P48: Emitido | S48: X | X48: =IFERROR(VLOOKUP(J47:J1939,[1]sheet1!$A:$K,11,0),"sin acuse") -> sin acuse
A49: Factura electrónica | B49: 2f425de007b7a26bf9dad87f9508fcae405ea6eade3e1e4e8a00834fbca6e0c1e3d82d5728b747eba774d67f583554be | C49: 107635 | D49: =C49-C50 -> -1 | E49: FVE | F49: 02-03-2026 | G49: 02-03-2026 07:51:28 | H49: 900800595 | I49: Provexpress SAS | J49: 860503184 | K49: Bip Colombia SAS | L49: 33568.25 | M49: 0 | N49: 210243.25 | O49: Aprobado con notificación | P49: Emitido | S49: X | U49: X | X49: =IFERROR(VLOOKUP(J48:J1940,[1]sheet1!$A:$K,11,0),"sin acuse") -> Aceptacion Expresa
A50: Factura electrónica | B50: a552081676350bfbb98c1ae483bd7c46b461ef9ef35c64dc4ed342a2f2c73cfbbaf4bbe6f116a84132fe7637cd472c22 | C50: 107636 | D50: =C50-C51 -> -1 | E50: FVE | F50: 02-03-2026 | G50: 02-03-2026 07:51:32 | H50: 900800595 | I50: Provexpress SAS | J50: 900050036 | K50: Cushman & WaKefield Colombia SAS | L50: 99788 | M50: 0 | N50: 624988 | O50: Aprobado con notificación | P50: Emitido | U50: X | W50: Se envia correo al cliente | X50: =IFERROR(VLOOKUP(J49:J1941,[1]sheet1!$A:$K,11,0),"sin acuse") -> sin acuse
A51: Factura electrónica | B51: c2c61036d5eb3190ca3f03ff13fd17d6350add4584d207144406e7690002232bacb9e3ba7400b0afd2396392266d485b | C51: 107637 | D51: =C51-C52 -> -1 | E51: FVE | F51: 02-03-2026 | G51: 02-03-2026 07:51:37 | H51: 900800595 | I51: Provexpress SAS | J51: 900050036 | K51: Cushman & WaKefield Colombia SAS | L51: 326491.44 | M51: 0 | N51: 2044867.4 | O51: Aprobado con notificación | P51: Emitido | U51: X | W51: Se envia correo al cliente | X51: =IFERROR(VLOOKUP(J50:J1942,[1]sheet1!$A:$K,11,0),"sin acuse") -> sin acuse
A52: Factura electrónica | B52: 88bedf12fc3ed739b9160da0554fd5c35624114ba4b6ddcb10ae8b79c22c17745ba3d1f3a946eb5fb4087ff10976ea6f | C52: 107638 | D52: =C52-C53 -> -1 | E52: FVE | F52: 02-03-2026 | G52: 02-03-2026 07:51:41 | H52: 900800595 | I52: Provexpress SAS | J52: 860509527 | K52: Constructora Obreval SA | L52: 471200 | M52: 0 | N52: 2951200 | O52: Aprobado con notificación | P52: Emitido | S52: X | X52: =IFERROR(VLOOKUP(J51:J1943,[1]sheet1!$A:$K,11,0),"sin acuse") -> Aceptacion Expresa
A53: Factura electrónica | B53: 2bb40325d93d3a7693ab04a5896e25a0bbeb81df10eae7b815d6a9ed43e394500266dac621cbcad40ef0a61ccf5d67ef | C53: 107639 | D53: =C53-C54 -> -1 | E53: FVE | F53: 02-03-2026 | G53: 02-03-2026 07:51:46 | H53: 900800595 | I53: Provexpress SAS | J53: 900114676 | K53: Minex Compañia Internacional Sociedad Por Acciones Simplificada C I | L53: 96900 | M53: 0 | N53: 606900 | O53: Aprobado con notificación | P53: Emitido | R53: x | U53: X | X53: =IFERROR(VLOOKUP(J52:J1944,[1]sheet1!$A:$K,11,0),"sin acuse") -> Sin Evento
A54: Factura electrónica | B54: aff25838314252a7a1f63bcc718b3eb3338d390b8bd3e0356cf125c098d149c71a7c34c3aae48b9dee6648327f69b7c4 | C54: 107640 | D54: =C54-C55 -> -1 | E54: FVE | F54: 02-03-2026 | G54: 02-03-2026 07:51:50 | H54: 900800595 | I54: Provexpress SAS | J54: 900114676 | K54: Minex Compañia Internacional Sociedad Por Acciones Simplificada C I | L54: 101650 | M54: 0 | N54: 636650 | O54: Aprobado con notificación | P54: Emitido | R54: x | U54: X | X54: =IFERROR(VLOOKUP(J53:J1945,[1]sheet1!$A:$K,11,0),"sin acuse") -> Sin Evento
A55: Factura electrónica | B55: 775f5865cadd0c63cfed7cc8be7a7713e1876975a9f04d4c6b8f2a68ff98b88e97f9bd15788cee6aab9eb42549c57ed8 | C55: 107641 | D55: =C55-C56 -> -1 | E55: FVE | F55: 02-03-2026 | G55: 02-03-2026 08:06:57 | H55: 900800595 | I55: Provexpress SAS | J55: 860031615 | K55: Agunsa Colombia SAS | L55: 1615000 | M55: 0 | N55: 10115000 | O55: Aprobado con notificación | P55: Emitido | S55: X | X55: =IFERROR(VLOOKUP(J54:J1946,[1]sheet1!$A:$K,11,0),"sin acuse") -> Aceptacion Expresa
A56: Factura electrónica | B56: 37fe64c087aa3681c632e49965fcdf58f3dcc7332c813c9975fcdf649fd3e33080116c3e1e7714cf53a8fdd2450109df | C56: 107642 | D56: =C56-C57 -> -1 | E56: FVE | F56: 02-03-2026 | G56: 02-03-2026 08:07:01 | H56: 900800595 | I56: Provexpress SAS | J56: 860522056 | K56: Lamitech SAS | L56: 99997 | M56: 0 | N56: 626297 | O56: Aprobado con notificación | P56: Emitido | Q56: X | X56: =IFERROR(VLOOKUP(J55:J1947,[1]sheet1!$A:$K,11,0),"sin acuse") -> Aceptacion Expresa
A57: Factura electrónica | B57: e434319286af7f06a3441a96b395771327aca0b00e72d27034352797fc842b1643969faa0d38b03cef506fafb9e81928 | C57: 107643 | D57: =C57-C58 -> -1 | E57: FVE | F57: 02-03-2026 | G57: 02-03-2026 08:07:06 | H57: 900800595 | I57: Provexpress SAS | J57: 860007759 | K57: Colegio Mayor De Nuestra Señora Del Rosario | L57: 5130 | M57: 0 | N57: 32130 | O57: Aprobado con notificación | P57: Emitido | U57: X | W57: se envia correo al ciente | X57: =IFERROR(VLOOKUP(J56:J1948,[1]sheet1!$A:$K,11,0),"sin acuse") -> Sin Evento
A58: Factura electrónica | B58: 3126a0fef1f6a3af11057f860d45e6d8b927866bd22aaac6c8754e06f99f4a281a53e1270a29f1beb8fb17ccf114c0de | C58: 107644 | D58: =C58-C59 -> -1 | E58: FVE | F58: 02-03-2026 | G58: 02-03-2026 08:07:11 | H58: 900800595 | I58: Provexpress SAS | J58: 860007759 | K58: Colegio Mayor De Nuestra Señora Del Rosario | L58: 48735 | M58: 0 | N58: 305235 | O58: Aprobado con notificación | P58: Emitido | U58: X | W58: se envia correo al ciente | X58: =IFERROR(VLOOKUP(J57:J1949,[1]sheet1!$A:$K,11,0),"sin acuse") -> Sin Evento
A59: Factura electrónica | B59: a6dec0f9b879985547143c848c57d627e6b9d25edd822ce7352600abe5e0b5594d2c573c43556f5e9a71df4defb8bc0c | C59: 107645 | D59: =C59-C60 -> -1 | E59: FVE | F59: 02-03-2026 | G59: 02-03-2026 08:07:15 | H59: 900800595 | I59: Provexpress SAS | J59: 860524513 | K59: Mullen Lowe Ssp3 SAS | L59: 12160 | M59: 0 | N59: 76160 | O59: Aprobado con notificación | P59: Emitido | Q59: X | X59: =IFERROR(VLOOKUP(J58:J1950,[1]sheet1!$A:$K,11,0),"sin acuse") -> Acuse Recibo
A60: Factura electrónica | B60: 9efaa90ebc456b31ebf02ef5f1c8246a04dd18f3806149dcc6c162ae325212ba957a99cda7529eea6aeaed78f2830313 | C60: 107646 | D60: =C60-C61 -> -1 | E60: FVE | F60: 02-03-2026 | G60: 02-03-2026 08:07:20 | H60: 900800595 | I60: Provexpress SAS | J60: 830077515 | K60: Global Motor SAS | L60: 513000 | M60: 0 | N60: 3213000 | O60: Aprobado con notificación | P60: Emitido | Q60: X | X60: =IFERROR(VLOOKUP(J59:J1951,[1]sheet1!$A:$K,11,0),"sin acuse") -> Acuse Recibo
A61: Factura electrónica | B61: bdbc69bb8b094dc5b2e591077339acb028aa7c895c888482e444cc782d192ddb384a4103cd9a4ee3d964e7dbb8931f32 | C61: 107647 | D61: =C61-C62 -> -1 | E61: FVE | F61: 02-03-2026 | G61: 02-03-2026 08:22:26 | H61: 900800595 | I61: Provexpress SAS | J61: 800077635 | K61: LM Instruments SA | L61: 49400 | M61: 0 | N61: 309400 | O61: Aprobado con notificación | P61: Emitido | S61: X | X61: =IFERROR(VLOOKUP(J60:J1952,[1]sheet1!$A:$K,11,0),"sin acuse") -> Aceptacion Expresa
A62: Factura electrónica | B62: fbf5ed1f491102395565a20e6dff5f0da5940ef10ea9d5ee2e8d219081868b850c77f283addf93ace195ea88d09fa58e | C62: 107648 | D62: =C62-C63 -> -1 | E62: FVE | F62: 02-03-2026 | G62: 02-03-2026 08:22:31 | H62: 900800595 | I62: Provexpress SAS | J62: 830033494 | K62: Heel Colombia Ltda | L62: 189573.45 | M62: 0 | N62: 1187328.4 | O62: Aprobado con notificación | P62: Emitido | Q62: X | X62: =IFERROR(VLOOKUP(J61:J1953,[1]sheet1!$A:$K,11,0),"sin acuse") -> Aceptacion Expresa
A63: Factura electrónica | B63: 346226bc164950fd746eeb1b1f32070b0a471835ab0ff460e2e0b3bfae47d3ddb79f9ecc11ec5c90767c588deb32b0ed | C63: 107649 | D63: =C63-C64 -> -1 | E63: FVE | F63: 02-03-2026 | G63: 02-03-2026 08:22:36 | H63: 900800595 | I63: Provexpress SAS | J63: 830033494 | K63: Heel Colombia Ltda | L63: 429321.57 | M63: 0 | N63: 3114702.6 | O63: Aprobado con notificación | P63: Emitido | Q63: X | X63: =IFERROR(VLOOKUP(J62:J1954,[1]sheet1!$A:$K,11,0),"sin acuse") -> Aceptacion Expresa
A64: Factura electrónica | B64: 172a5f13acd93e9358d37cd2d878b62e3e900885385f5519eb20704951f65b27a85b2f22eaab8ae22522631feda92ba5 | C64: 107650 | D64: =C64-C65 -> -1 | E64: FVE | F64: 02-03-2026 | G64: 02-03-2026 08:22:40 | H64: 900800595 | I64: Provexpress SAS | J64: 830033494 | K64: Heel Colombia Ltda | L64: 138390.3 | M64: 0 | N64: 866760.3 | O64: Aprobado con notificación | P64: Emitido | Q64: X | X64: =IFERROR(VLOOKUP(J63:J1955,[1]sheet1!$A:$K,11,0),"sin acuse") -> Aceptacion Expresa
A65: Factura electrónica | B65: 266bb1f6d248cbb44a90c7f4f9567652e42a46e5769eddba52a95fc58ed1eb3ad7ea91e48107371947130a040d182fe9 | C65: 107651 | D65: =C65-C66 -> -1 | E65: FVE | F65: 02-03-2026 | G65: 02-03-2026 08:22:44 | H65: 900800595 | I65: Provexpress SAS | J65: 860522056 | K65: Lamitech SAS | L65: 51186 | M65: 0 | N65: 320586 | O65: Aprobado con notificación | P65: Emitido | Q65: X | X65: =IFERROR(VLOOKUP(J64:J1956,[1]sheet1!$A:$K,11,0),"sin acuse") -> Aceptacion Expresa
A66: Factura electrónica | B66: ed3f9d686bae9254db48c75c9685d42ca3f87c8d60233b3f31446139fa2c9eabf066338c0a71915a9dbc92c1c5c2a6ff | C66: 107652 | D66: =C66-C67 -> -1 | E66: FVE | F66: 02-03-2026 | G66: 02-03-2026 08:22:50 | H66: 900800595 | I66: Provexpress SAS | J66: 830099238 | K66: Cementos Tequendama SAS | L66: 1149697.8 | M66: 0 | N66: 9958413.8 | O66: Aprobado con notificación | P66: Emitido | U66: X | X66: =IFERROR(VLOOKUP(J65:J1957,[1]sheet1!$A:$K,11,0),"sin acuse") -> Sin Evento
A67: Factura electrónica | B67: cecce1e87a4d07bd8b2071a1f8e63b808436c12fd2bd5a35ca8b9260db313493593824957967ae598f27787b8a5761b5 | C67: 107653 | D67: =C67-C68 -> -1 | E67: FVE | F67: 02-03-2026 | G67: 02-03-2026 08:22:55 | H67: 900800595 | I67: Provexpress SAS | J67: 900114346 | K67: Banco Jpmorgan Colombia SA | L67: 115026 | M67: 0 | N67: 720426 | O67: Aprobado con notificación | P67: Emitido | R67: X | X67: =IFERROR(VLOOKUP(J66:J1958,[1]sheet1!$A:$K,11,0),"sin acuse") -> Recibo Bien y/o Servicio
A68: Factura electrónica | B68: c3118c8a6532307a9854beaed9937fd13d3088be49de544864bdcf8f5f3184f92d3ae22799cdbf1ed898bc8c32dd321c | C68: 107654 | D68: =C68-C69 -> -1 | E68: FVE | F68: 02-03-2026 | G68: 02-03-2026 08:38:01 | H68: 900800595 | I68: Provexpress SAS | J68: 900224534 | K68: Isi Emerging Markets Colombia SAS | L68: 1509740 | M68: 0 | N68: 9455740 | O68: Aprobado con notificación | P68: Emitido | Q68: X | X68: =IFERROR(VLOOKUP(J67:J1959,[1]sheet1!$A:$K,11,0),"sin acuse") -> sin acuse
A69: Factura electrónica | B69: 430cd129a204403d97aa43386e87b9914fc116e05f78676ca3a4254ad6098c41c10f41d0a2f5dbc54b34c1f343968484 | C69: 107655 | D69: =C69-C70 -> -1 | E69: FVE | F69: 02-03-2026 | G69: 02-03-2026 08:38:05 | H69: 900800595 | I69: Provexpress SAS | J69: 900041757 | K69: Sky Forwarder SAS | L69: 167200 | M69: 0 | N69: 1047200 | O69: Aprobado con notificación | P69: Emitido | S69: X | X69: =IFERROR(VLOOKUP(J68:J1960,[1]sheet1!$A:$K,11,0),"sin acuse") -> sin acuse
A70: Factura electrónica | B70: 585213f737e6cc70435543aa981abc7e257b22eaba39c25d502a74588d0c82e31a55e44b1ab8cf7cb04a0c823eb161d6 | C70: 107656 | D70: =C70-C71 -> -1 | E70: FVE | F70: 02-03-2026 | G70: 02-03-2026 08:38:11 | H70: 900800595 | I70: Provexpress SAS | J70: 900714469 | K70: Sky Logistica Integral S A S | L70: 75240 | M70: 0 | N70: 471240 | O70: Aprobado con notificación | P70: Emitido | S70: X | X70: =IFERROR(VLOOKUP(J69:J1961,[1]sheet1!$A:$K,11,0),"sin acuse") -> Aceptacion Expresa
A71: Factura electrónica | B71: 3ac01d241e1500948cc03bbdcdebb0a699fa8cb35ca51478c9f0d4d28922e94eb18c11cbe70c3a5433854cc7ce6e2815 | C71: 107657 | D71: =C71-C72 -> -1 | E71: FVE | F71: 02-03-2026 | G71: 02-03-2026 08:38:15 | H71: 900800595 | I71: Provexpress SAS | J71: 900714469 | K71: Sky Logistica Integral S A S | L71: 49400 | M71: 0 | N71: 309400 | O71: Aprobado con notificación | P71: Emitido | S71: X | X71: =IFERROR(VLOOKUP(J70:J1962,[1]sheet1!$A:$K,11,0),"sin acuse") -> Aceptacion Expresa
A72: Factura electrónica | B72: 1a6796a770a4eedd3805fe72c0517ce0b1bc843c0ea81be750182ce8759aab0ad9a71361181e1db56ff6bdc68478cfa9 | C72: 107658 | D72: =C72-C73 -> -1 | E72: FVE | F72: 02-03-2026 | G72: 02-03-2026 08:38:19 | H72: 900800595 | I72: Provexpress SAS | J72: 900714469 | K72: Sky Logistica Integral S A S | L72: 117040 | M72: 0 | N72: 733040 | O72: Aprobado con notificación | P72: Emitido | S72: X | X72: =IFERROR(VLOOKUP(J71:J1963,[1]sheet1!$A:$K,11,0),"sin acuse") -> Aceptacion Expresa
A73: Factura electrónica | B73: 95f73eeaf91c496362a71f964f3387eeb0ba23794a9c69648f3af5662fcd93476103aaa15be53de6671b8c7aa8bb8d1c | C73: 107659 | D73: =C73-C74 -> -1 | E73: FVE | F73: 02-03-2026 | G73: 02-03-2026 08:53:25 | H73: 900800595 | I73: Provexpress SAS | J73: 900975788 | K73: Sky Industrial SAS | L73: 140220 | M73: 0 | N73: 878220 | O73: Aprobado con notificación | P73: Emitido | S73: X | X73: =IFERROR(VLOOKUP(J72:J1964,[1]sheet1!$A:$K,11,0),"sin acuse") -> Aceptacion Expresa
A74: Factura electrónica | B74: c0ea322e8c9b24bcc5fcd7cb09cc2f44b660222646ce8c04093c5be433f6e7a9a80e89814dbbcbf6a512310bbe3e5fd4 | C74: 107660 | D74: =C74-C75 -> -1 | E74: FVE | F74: 02-03-2026 | G74: 02-03-2026 08:53:30 | H74: 900800595 | I74: Provexpress SAS | J74: 900283577 | K74: Sinnetic SAS | L74: 155746 | M74: 0 | N74: 1231146 | O74: Aprobado con notificación | P74: Emitido | U74: X | X74: =IFERROR(VLOOKUP(J73:J1965,[1]sheet1!$A:$K,11,0),"sin acuse") -> Sin Evento
A75: Factura electrónica | B75: c029363a636383cf61c70f890542450444e6f6bda86ab83ffac441b49cc065f4d7dfdc5a5dea7bfbaafc31549deab580 | C75: 107661 | D75: =C75-C76 -> -1 | E75: FVE | F75: 02-03-2026 | G75: 02-03-2026 08:53:35 | H75: 900800595 | I75: Provexpress SAS | J75: 860516431 | K75: Gran Tierra Energy Colombia Gmbh Sucursal Colombia | L75: 1518100 | M75: 0 | N75: 9508100 | O75: Aprobado con notificación | P75: Emitido | S75: X | X75: =IFERROR(VLOOKUP(J74:J1966,[1]sheet1!$A:$K,11,0),"sin acuse") -> Aceptacion Expresa
A76: Factura electrónica | B76: 95a2ee5f3c5a9dcf51a0849e47e11accc8e1474a918b4da8f60cf8ed03db03aa6c236a661bf7202813ac55fd068dde2d | C76: 107662 | D76: =C76-C77 -> -1 | E76: FVE | F76: 02-03-2026 | G76: 02-03-2026 08:53:39 | H76: 900800595 | I76: Provexpress SAS | J76: 860400204 | K76: Saenz Fety S A S | L76: 273600 | M76: 0 | N76: 1713600 | O76: Aprobado con notificación | P76: Emitido | S76: X | X76: =IFERROR(VLOOKUP(J75:J1967,[1]sheet1!$A:$K,11,0),"sin acuse") -> Aceptacion Expresa
A77: Factura electrónica | B77: 53b7e05c8277ab1bd6b2064d778aa936535b4a645bd7b6ebc72e6ca7beefb9d9e411c192c385aa0283949579e1e8ce2f | C77: 107663 | D77: =C77-C78 -> -1 | E77: FVE | F77: 02-03-2026 | G77: 02-03-2026 08:53:43 | H77: 900800595 | I77: Provexpress SAS | J77: 800181114 | K77: Puerto Pimsa SA | L77: 684000 | M77: 0 | N77: 4284000 | O77: Aprobado con notificación | P77: Emitido | Q77: X | X77: =IFERROR(VLOOKUP(J76:J1968,[1]sheet1!$A:$K,11,0),"sin acuse") -> Acuse Recibo
A78: Factura electrónica | B78: 5ec8419a6e7b100861f3959d6009f9668d50908977b361a65fcc74add77e0fdcdc85e17c0fdc63f44e749206ba5482b4 | C78: 107664 | D78: =C78-C79 -> -1 | E78: FVE | F78: 02-03-2026 | G78: 02-03-2026 08:53:48 | H78: 900800595 | I78: Provexpress SAS | J78: 901487659 | K78: Rua Group CIB SAS | L78: 77834.45 | M78: 0 | N78: 487489.45 | O78: Aprobado con notificación | P78: Emitido | U78: X | X78: =IFERROR(VLOOKUP(J77:J1969,[1]sheet1!$A:$K,11,0),"sin acuse") -> sin acuse
A79: Factura electrónica | B79: 929e1f83231d66c253ef7a03dff65fbe38f8aef8cd2b3e459c72cdf421a82655a971184363dcf954004c5271ff51a34a | C79: 107665 | D79: =C79-C80 -> -1 | E79: FVE | F79: 02-03-2026 | G79: 02-03-2026 08:53:52 | H79: 900800595 | I79: Provexpress SAS | J79: 900237820 | K79: Quantum Data Processing De Colombia SAS | L79: 196460 | M79: 0 | N79: 1230460 | O79: Aprobado con notificación | P79: Emitido | U79: X | X79: =IFERROR(VLOOKUP(J78:J1970,[1]sheet1!$A:$K,11,0),"sin acuse") -> sin acuse
A80: Factura electrónica | B80: cc245b9f18bbb69813b98c753c5afa97fa232f3132c2159910031f2e1bdf076e54d8792670288b59d06f2dc64fe97ea7 | C80: 107666 | D80: =C80-C81 -> -1 | E80: FVE | F80: 02-03-2026 | G80: 02-03-2026 16:49:02 | H80: 900800595 | I80: Provexpress SAS | J80: 804003084 | K80: Inemec SAS | L80: 456295.87 | M80: 0 | N80: 4248960.9 | O80: Aprobado con notificación | P80: Emitido | U80: X | X80: =IFERROR(VLOOKUP(J79:J1971,[1]sheet1!$A:$K,11,0),"sin acuse") -> Aceptacion Expresa
A81: Factura electrónica | B81: 1242d945ed8276ad3b4dd57e1da76d29594faa9c1fcbd1f7208e581329de247226853a3b76f334e27c6ccdf66d53fa65 | C81: 107667 | D81: =C81-C82 -> -1 | E81: FVE | F81: 02-03-2026 | G81: 02-03-2026 09:09:01 | H81: 900800595 | I81: Provexpress SAS | J81: 830033494 | K81: Heel Colombia Ltda | L81: 61438.4 | M81: 0 | N81: 384798.4 | O81: Aprobado con notificación | P81: Emitido | Q81: X | X81: =IFERROR(VLOOKUP(J80:J1972,[1]sheet1!$A:$K,11,0),"sin acuse") -> Aceptacion Expresa
A82: Factura electrónica | B82: 9a4829cd8961ac759aaa116ab2d9718dfb46fadeecbcc3f67b552234c68bf155cbf1ff9685ae4894e5bc6850dde7094c | C82: 107668 | D82: =C82-C83 -> -1 | E82: FVE | F82: 02-03-2026 | G82: 02-03-2026 09:24:08 | H82: 900800595 | I82: Provexpress SAS | J82: 860508392 | K82: Servioptica SAS | L82: 91200 | M82: 0 | N82: 571200 | O82: Aprobado con notificación | P82: Emitido | U82: X | X82: =IFERROR(VLOOKUP(J81:J1973,[1]sheet1!$A:$K,11,0),"sin acuse") -> Aceptacion Expresa
A83: Factura electrónica | B83: 9c05570d4c32713464727c69713e6639ac6b9e625e6a9fe952c67aa6f67fc45a54ef0719c4140288064ee94017aa4640 | C83: 107669 | D83: =C83-C84 -> -1 | E83: FVE | F83: 02-03-2026 | G83: 02-03-2026 09:24:14 | H83: 900800595 | I83: Provexpress SAS | J83: 800024265 | K83: Editorial Santillana SAS | L83: 0 | M83: 0 | N83: 7666668 | O83: Aprobado con notificación | P83: Emitido | Q83: X | X83: =IFERROR(VLOOKUP(J82:J1974,[1]sheet1!$A:$K,11,0),"sin acuse") -> Acuse Recibo
A84: Factura electrónica | B84: 5c3c1a42c6c51f25034c4f832012e29b2f1f0627d6c58f1de38545f3897c77cb8f976d8268e5a2f81ae98944aaeebfbe | C84: 107670 | D84: =C84-C85 -> -1 | E84: FVE | F84: 02-03-2026 | G84: 02-03-2026 09:24:35 | H84: 900800595 | I84: Provexpress SAS | J84: 901662739 | K84: Improve Learning SAS | L84: 674500 | M84: 0 | N84: 4224500 | O84: Aprobado con notificación | P84: Emitido | Q84: X | X84: =IFERROR(VLOOKUP(J83:J1975,[1]sheet1!$A:$K,11,0),"sin acuse") -> Acuse Recibo
A85: Factura electrónica | B85: 17f078f50c6d068705a61d8853abbbf51d24f15e8d4aa16cd488d8f6b08abe3446fa4bacd3a5b6f1514b8493dea9279a | C85: 107671 | D85: =C85-C86 -> -1 | E85: FVE | F85: 02-03-2026 | G85: 02-03-2026 09:24:37 | H85: 900800595 | I85: Provexpress SAS | J85: 800251957 | K85: Agencia De Aduanas Siaco SAS Nivel 1 | L85: 231021 | M85: 0 | N85: 1446921 | O85: Aprobado con notificación | P85: Emitido | U85: X | X85: =IFERROR(VLOOKUP(J84:J1976,[1]sheet1!$A:$K,11,0),"sin acuse") -> Sin Evento
A86: Factura electrónica | B86: 1abfb44e181328536557f605ddc63bd75610fcc7989145d446b820aff6a8ca2905cf2598b8f424927efdf0b4a206128c | C86: 107672 | D86: =C86-C87 -> -1 | E86: FVE | F86: 02-03-2026 | G86: 02-03-2026 09:39:29 | H86: 900800595 | I86: Provexpress SAS | J86: 800125872 | K86: Keralty SAS | L86: 373204.65 | M86: 0 | N86: 2337439.6 | O86: Aprobado con notificación | P86: Emitido | S86: X | X86: =IFERROR(VLOOKUP(J85:J1977,[1]sheet1!$A:$K,11,0),"sin acuse") -> Aceptacion Expresa
A87: Factura electrónica | B87: 2c30f66867b06f8d4da0ed0454e28ff74367850aba628605666b34c7385a39059ad55c02af3a4ce2b7b5e4edf2902859 | C87: 107673 | D87: =C87-C88 -> -1 | E87: FVE | F87: 02-03-2026 | G87: 02-03-2026 09:39:33 | H87: 900800595 | I87: Provexpress SAS | J87: 860078828 | K87: Compañia De Medicina Prepagada Colsanitas SA | L87: 373204.65 | M87: 0 | N87: 2337439.6 | O87: Aprobado con notificación | P87: Emitido | S87: X | X87: =IFERROR(VLOOKUP(J86:J1978,[1]sheet1!$A:$K,11,0),"sin acuse") -> Aceptacion Expresa
A88: Factura electrónica | B88: bff04c123013c4a81d0a51838bc84d789445e810cb28c7e26b6f9c425a28ac31c42af69d0e1cb098915c97895e642848 | C88: 107674 | D88: =C88-C89 -> -1 | E88: FVE | F88: 02-03-2026 | G88: 02-03-2026 09:39:38 | H88: 900800595 | I88: Provexpress SAS | J88: 860078828 | K88: Compañia De Medicina Prepagada Colsanitas SA | L88: 657959.36 | M88: 0 | N88: 4120903.4 | O88: Aprobado con notificación | P88: Emitido | S88: X | X88: =IFERROR(VLOOKUP(J87:J1979,[1]sheet1!$A:$K,11,0),"sin acuse") -> Aceptacion Expresa
A89: Factura electrónica | B89: daded72f4eddd84444412e83db3c3fd81c02330a0f4677d1c454c99fd7df4ccbfbc9205eb877aee1cfe92a387887354b | C89: 107675 | D89: =C89-C90 -> -1 | E89: FVE | F89: 02-03-2026 | G89: 02-03-2026 09:39:43 | H89: 900800595 | I89: Provexpress SAS | J89: 901041691 | K89: Centros Medicos Colsanitas S A S | L89: 373204.65 | M89: 0 | N89: 2337439.6 | O89: Aprobado con notificación | P89: Emitido | S89: X | X89: =IFERROR(VLOOKUP(J88:J1980,[1]sheet1!$A:$K,11,0),"sin acuse") -> Aceptacion Expresa
A90: Factura electrónica | B90: 908addaf0285a383c097af9bef4f498008559c045d736224e9e022f142a83db0c6a0717ff3d314229c534db2e7cb53d5 | C90: 107676 | D90: =C90-C91 -> -1 | E90: FVE | F90: 02-03-2026 | G90: 02-03-2026 09:39:49 | H90: 900800595 | I90: Provexpress SAS | J90: 901041691 | K90: Centros Medicos Colsanitas S A S | L90: 746409.3 | M90: 0 | N90: 4674879.3 | O90: Aprobado con notificación | P90: Emitido | S90: X | X90: =IFERROR(VLOOKUP(J89:J1981,[1]sheet1!$A:$K,11,0),"sin acuse") -> Aceptacion Expresa
A91: Factura electrónica | B91: 3b36c620c60ef462d19f998fc7aee91d83c69c85525ffae70a552a3c47593dcbb848ebb4e15bfa0be38b57547f221eff | C91: 107677 | D91: =C91-C92 -> -1 | E91: FVE | F91: 02-03-2026 | G91: 02-03-2026 09:39:53 | H91: 900800595 | I91: Provexpress SAS | J91: 800149384 | K91: Clinica Colsanitas SA | L91: 373204.65 | M91: 0 | N91: 2337439.6 | O91: Aprobado con notificación | P91: Emitido | S91: X | X91: =IFERROR(VLOOKUP(J90:J1982,[1]sheet1!$A:$K,11,0),"sin acuse") -> Aceptacion Expresa
A92: Factura electrónica | B92: 2a3dc67c70882169f33298e6bf3d575cf2c361a9ce29b42b7bfd26b5902a883d34065e7c07c6d83f09b5d63292c627f6 | C92: 107678 | D92: =C92-C93 -> -1 | E92: FVE | F92: 02-03-2026 | G92: 02-03-2026 09:39:57 | H92: 900800595 | I92: Provexpress SAS | J92: 800149384 | K92: Clinica Colsanitas SA | L92: 373204.65 | M92: 0 | N92: 2337439.6 | O92: Aprobado con notificación | P92: Emitido | S92: X | X92: =IFERROR(VLOOKUP(J91:J1983,[1]sheet1!$A:$K,11,0),"sin acuse") -> Aceptacion Expresa
A93: Factura electrónica | B93: a61d3e02a1282f820b728a4993b422f9a770e5ee48095a17ad2794f2bbc4249185233e9133d24035cc4c1d8176f02762 | C93: 107679 | D93: =C93-C94 -> -1 | E93: FVE | F93: 02-03-2026 | G93: 02-03-2026 09:55:04 | H93: 900800595 | I93: Provexpress SAS | J93: 800149384 | K93: Clinica Colsanitas SA | L93: 373204.65 | M93: 0 | N93: 2337439.6 | O93: Aprobado con notificación | P93: Emitido | S93: X | X93: =IFERROR(VLOOKUP(J92:J1984,[1]sheet1!$A:$K,11,0),"sin acuse") -> Aceptacion Expresa
A94: Factura electrónica | B94: dd9f5d9ceee10f6761ebc00fdba1f41692598034a13d0d5f4178640223f8b7750e5637e38c0135f4817611393730ee8f | C94: 107680 | D94: =C94-C95 -> -1 | E94: FVE | F94: 02-03-2026 | G94: 02-03-2026 09:55:08 | H94: 900800595 | I94: Provexpress SAS | J94: 800149384 | K94: Clinica Colsanitas SA | L94: 508978.08 | M94: 0 | N94: 3187810.1 | O94: Aprobado con notificación | P94: Emitido | S94: X | X94: =IFERROR(VLOOKUP(J93:J1985,[1]sheet1!$A:$K,11,0),"sin acuse") -> Aceptacion Expresa
A95: Factura electrónica | B95: 6d5381ff1308e239ab0a591ab49c050d5c6e2e7a02a659b10fa7de3ca98cf691637dd0293956dee75a76832544fec8f1 | C95: 107681 | D95: =C95-C96 -> -1 | E95: FVE | F95: 02-03-2026 | G95: 02-03-2026 09:55:12 | H95: 900800595 | I95: Provexpress SAS | J95: 800149384 | K95: Clinica Colsanitas SA | L95: 508978.08 | M95: 0 | N95: 3187810.1 | O95: Aprobado con notificación | P95: Emitido | S95: X | X95: =IFERROR(VLOOKUP(J94:J1986,[1]sheet1!$A:$K,11,0),"sin acuse") -> Aceptacion Expresa
A96: Factura electrónica | B96: 5e11a454ac111d064b3dd16ee490c87ecb0c8f2ed3b22e26b03f36a9ef5d2f1175606e16922bf84368a7c2da43bdde09 | C96: 107682 | D96: =C96-C97 -> -1 | E96: FVE | F96: 02-03-2026 | G96: 02-03-2026 09:55:18 | H96: 900800595 | I96: Provexpress SAS | J96: 800149384 | K96: Clinica Colsanitas SA | L96: 508978.08 | M96: 0 | N96: 3187810.1 | O96: Aprobado con notificación | P96: Emitido | S96: X | X96: =IFERROR(VLOOKUP(J95:J1987,[1]sheet1!$A:$K,11,0),"sin acuse") -> Aceptacion Expresa
A97: Factura electrónica | B97: 27eed4d194a9b5e3b30da733fd23fd239d165f375df23181d3548f5ecb7d3850eeeb4e658057951b8f60059ab9d83686 | C97: 107683 | D97: =C97-C98 -> -1 | E97: FVE | F97: 02-03-2026 | G97: 02-03-2026 09:55:22 | H97: 900800595 | I97: Provexpress SAS | J97: 901469580 | K97: Compañia De Seguros Colsanitas SA | L97: 746409.3 | M97: 0 | N97: 4674879.3 | O97: Aprobado con notificación | P97: Emitido | S97: X | X97: =IFERROR(VLOOKUP(J96:J1988,[1]sheet1!$A:$K,11,0),"sin acuse") -> Aceptacion Expresa
A98: Factura electrónica | B98: 12f05672959f57776d4d9c2afe09b7a51880307eea8769ce809f9950f513e4ae4fc4400bae185025232237a4b14a0a11 | C98: 107684 | D98: =C98-C99 -> -1 | E98: FVE | F98: 02-03-2026 | G98: 02-03-2026 10:25:30 | H98: 900800595 | I98: Provexpress SAS | J98: 830113458 | K98: Fundacion Universitaria Sanitas | L98: 631629.16 | M98: 0 | N98: 3955993.2 | O98: Aprobado con notificación | P98: Emitido | S98: X | X98: =IFERROR(VLOOKUP(J97:J1989,[1]sheet1!$A:$K,11,0),"sin acuse") -> Aceptacion Expresa
A99: Factura electrónica | B99: 7f8e9e5f68706042b5825062286ca99ea913a99a8a093a8d57ed91c5c07c3e150dd5378ca8fe47d8e605e0788f2d58a2 | C99: 107685 | D99: =C99-C100 -> -1 | E99: FVE | F99: 02-03-2026 | G99: 02-03-2026 10:25:35 | H99: 900800595 | I99: Provexpress SAS | J99: 800149496 | K99: Colfondos SA Pensiones Y Cesantias | L99: 148563.85 | M99: 0 | N99: 930478.85 | O99: Aprobado con notificación | P99: Emitido | U99: X | X99: =IFERROR(VLOOKUP(J98:J1990,[1]sheet1!$A:$K,11,0),"sin acuse") -> Aceptacion Expresa
A100: Factura electrónica | B100: 09fa6485799a8b54812c63a9148f633a8bce102e8119fb63374534c203bf9135e2155dbbb7fd2c8c6355775866da0d2e | C100: 107686 | D100: =C100-C101 -> -1 | E100: FVE | F100: 02-03-2026 | G100: 02-03-2026 10:25:40 | H100: 900800595 | I100: Provexpress SAS | J100: 900468085 | K100: Andimoda SAS | L100: 33985.68 | M100: 0 | N100: 212857.68 | O100: Aprobado con notificación | P100: Emitido | U100: X | X100: =IFERROR(VLOOKUP(J99:J1991,[1]sheet1!$A:$K,11,0),"sin acuse") -> sin acuse
A101: Factura electrónica | B101: 04f2b085a77c856d0bc44a3e62889a351d1e83bcca6c592f0bd9907cb55fe97bb2f1eaadd9e32dd9ec4e29142509f905 | C101: 107687 | D101: =C101-C102 -> -1 | E101: FVE | F101: 02-03-2026 | G101: 02-03-2026 10:25:45 | H101: 900800595 | I101: Provexpress SAS | J101: 890903858 | K101: Industria Nacional De Gaseosas SA | L101: 44462614 | M101: 0 | N101: 2.7847637e+08 | O101: Aprobado con notificación | P101: Emitido | R101: X | X101: =IFERROR(VLOOKUP(J100:J1992,[1]sheet1!$A:$K,11,0),"sin acuse") -> Recibo Bien y/o Servicio
...

Sheet 1 ACUSE
A1: 1 ACUSE | B1: (Varios elementos)
A3: Nombre Receptor | B3: Folio | C3: Cuenta de 1 ACUSE | D3: Suma de Total
A4: Actual Colombia Inmobiliaria SAS | B4: 108057 | C4: 1 | D4: 1392300
A5: Total Actual Colombia Inmobiliaria SAS | C5: 1 | D5: 1392300
A6: Adecco Colombia S A | C6: 1 | D6: 433160
A7: Administradora Clinica La Colina S A S | B7: 108313 | C7: 1 | D7: 3525589.2
A8: Total Administradora Clinica La Colina S A S | C8: 1 | D8: 3525589.2
A9: Administradora Country SAS | B9: 107955 | C9: 1 | D9: 1155180.6
A10: Total Administradora Country SAS | C10: 1 | D10: 1155180.6
A11: Alimentos Balanceados Tequendama SA Albateq SA | B11: 108371 | C11: 1 | D11: 742443.38
A12: Total Alimentos Balanceados Tequendama SA Albateq SA | C12: 1 | D12: 742443.38
A13: Automundial SA | B13: 107608 | C13: 1 | D13: 89250
B14: 108373 | C14: 1 | D14: 92344
A15: Total Automundial SA | C15: 2 | D15: 181594
A16: Avidesa De Occidente SA | B16: 108158 | C16: 1 | D16: 119952
B17: 108249 | C17: 1 | D17: 139322.82
A18: Total Avidesa De Occidente SA | C18: 2 | D18: 259274.82
A19: Banco Mundo Mujer SA O Mundo Mujer El Banco De La Comunidad O Mundo Mujer | B19: 107630 | C19: 1 | D19: 362581.1
A20: Total Banco Mundo Mujer SA O Mundo Mujer El Banco De La Comunidad O Mundo Mujer | C20: 1 | D20: 362581.1
A21: Caja De Compensacion Familiar Compensar | B21: 108125 | C21: 1 | D21: 342720
A22: Total Caja De Compensacion Familiar Compensar | C22: 1 | D22: 342720
A23: Ceramica San Lorenzo Industrial De Colombia SA | B23: 107889 | C23: 1 | D23: 158508
A24: Total Ceramica San Lorenzo Industrial De Colombia SA | C24: 1 | D24: 158508
A25: Clinica Colsanitas SA | B25: 107906 | C25: 1 | D25: 15460624
A26: Total Clinica Colsanitas SA | C26: 1 | D26: 15460624
A27: Colinagro SA | B27: 108151 | C27: 1 | D27: 119000
A28: Total Colinagro SA | C28: 1 | D28: 119000
A29: Comercializadora Arturo Calle SAS | B29: 107800 | C29: 1 | D29: 116887.75
B30: 107920 | C30: 1 | D30: 124950
B31: 108766 | C31: 1 | D31: 1095038
A32: Total Comercializadora Arturo Calle SAS | C32: 3 | D32: 1336875.8
A33: Comercializadora Internacional Milpa SA | B33: 107611 | C33: 1 | D33: 574770
B34: 107694 | C34: 1 | D34: 238000
B35: 107892 | C35: 1 | D35: 18204620
B36: 108239 | C36: 1 | D36: 1581557.6
A37: Total Comercializadora Internacional Milpa SA | C37: 4 | D37: 20598948
A38: Compañia Colombiana De Seguridad Transbank LTDA | B38: 108114 | C38: 1 | D38: 678300
A39: Total Compañia Colombiana De Seguridad Transbank LTDA | C39: 1 | D39: 678300
A40: Confederacion Colombiana De Camaras De Comercio Confecamaras | B40: 108335 | C40: 1 | D40: 338068.29
B41: 108336 | C41: 1 | D41: 766360
B42: 108337 | C42: 1 | D42: 1065573.6
A43: Total Confederacion Colombiana De Camaras De Comercio Confecamaras | C43: 3 | D43: 2170001.9
A44: Constructora Las Galias S A S | B44: 107811 | C44: 1 | D44: 797478.5
A45: Total Constructora Las Galias S A S | C45: 1 | D45: 797478.5
A46: CYC Trading SAS | B46: 108278 | C46: 1 | D46: 135384.65
B47: 108279 | C47: 1 | D47: 299731.25
A48: Total CYC Trading SAS | C48: 2 | D48: 435115.9
A49: Distribuidora Y Editora Richmond SAS | B49: 107754 | C49: 1 | D49: 2314615.5
B50: 107756 | C50: 1 | D50: 2222219.1
B51: 107762 | C51: 1 | D51: 23796585
A52: Total Distribuidora Y Editora Richmond SAS | C52: 3 | D52: 28333420
A53: Don Maiz SAS | B53: 108329 | C53: 1 | D53: 727209
A54: Total Don Maiz SAS | C54: 1 | D54: 727209
A55: Editorial Santillana SAS | B55: 107669 | C55: 1 | D55: 7666668
B56: 107757 | C56: 1 | D56: 2314615.5
B57: 107758 | C57: 1 | D57: 1779799.7
B58: 107766 | C58: 1 | D58: 74998988
B59: 107767 | C59: 1 | D59: 10430170
B60: 107945 | C60: 1 | D60: 1689800
B61: 107946 | C61: 1 | D61: 1689800
B62: 108007 | C62: 1 | D62: 22134000
B63: 108038 | C63: 1 | D63: 7212934
B64: 108250 | C64: 1 | D64: 5303982.3
B65: 108253 | C65: 1 | D65: 69969483
B66: 108258 | C66: 1 | D66: 87966515
B67: 108259 | C67: 1 | D67: 46696941
... B74: 108368 | C74: 1 | D74: 15926670
A75: Total Editorial Santillana SAS | C75: 20 | D75: 7.0533418e+08
A76: Emermedica SA Servicios De Ambulancia Prepagados | B76: 108172 | C76: 1 | D76: 749700
A77: Total Emermedica SA Servicios De Ambulancia Prepagados | C77: 1 | D77: 749700
A78: Evertec Colombia SAS | B78: 108207 | C78: 1 | D78: 949217.78
A79: Total Evertec Colombia SAS | C79: 1 | D79: 949217.78
A80: Finanzauto SA BIC | B80: 108076 | C80: 1 | D80: 1644086.1
A81: Total Finanzauto SA BIC | C81: 1 | D81: 1644086.1
A82: Fundacion Colegio Anglo Colombiano | B82: 108322 | C82: 1 | D82: 1149266.3
A83: Total Fundacion Colegio Anglo Colombiano | C83: 1 | D83: 1149266.3
A84: Grupo Empresarial En Linea S.A. | B84: 107975 | C84: 1 | D84: 5145560
A85: Total Grupo Empresarial En Linea S.A. | C85: 1 | D85: 5145560
A86: Heel Colombia Ltda | B86: 107648 | C86: 1 | D86: 1187328.4
B87: 107649 | C87: 1 | D87: 3114702.6
B88: 107650 | C88: 1 | D88: 866760.3
B89: 107667 | C89: 1 | D89: 384798.4
B90: 108294 | C90: 1 | D90: 3004285.9
B91: 108295 | C91: 1 | D91: 2857785
B92: 108296 | C92: 1 | D92: 160650
A93: Total Heel Colombia Ltda | C93: 7 | D93: 11576311
A94: Hilton Worldwide Manage Branchco Limited | B94: 108110 | C94: 1 | D94: 220150
B95: 108111 | C95: 1 | D95: 10710000
B96: 108112 | C96: 1 | D96: 279650
B97: 108113 | C97: 1 | D97: 7361340
A98: Total Hilton Worldwide Manage Branchco Limited | C98: 4 | D98: 18571140
A99: IA4 SAS | B99: 107624 | C99: 1 | D99: 2177078.8
B100: 108306 | C100: 1 | D100: 112000.42
A101: Total IA4 SAS | C101: 2 | D101: 2289079.2
A102: Idom Consulting Engineering Architecture SAU | B102: 107869 | C102: 1 | D102: 2816105.2
B103: 107870 | C103: 1 | D103: 9458560.3
B104: 107872 | C104: 1 | D104: 2578628.9
B105: 107873 | C105: 1 | D105: 1719085.9
B106: 107874 | C106: 1 | D106: 2578628.9
B107: 107875 | C107: 1 | D107: 1719085.9
...

Sheet 2 ACUSES
A1: 2 ACUSE | B1: (Varios elementos)
A3: Nombre Receptor | B3: Folio | C3: Cuenta de 2 ACUSE | D3: Suma de Total
A4: Caja Colombiana De Subsidio Familiar Colsubsidio | B4: 108304 | C4: 1 | D4: 963543
A5: Total Caja Colombiana De Subsidio Familiar Colsubsidio | C5: 1 | D5: 963543
A6: Ferricentros SAS | B6: 107785 | C6: 1 | D6: 1387596.4
B7: 107832 | C7: 1 | D7: 2156624.4
B8: 107847 | C8: 1 | D8: 1661548
A9: Total Ferricentros SAS | C9: 3 | D9: 5205768.8
A10: Flota La Macarena SA | B10: 107959 | C10: 1 | D10: 1221073.2
A11: Total Flota La Macarena SA | C11: 1 | D11: 1221073.2
A12: Novasoft S A S | B12: 108230 | C12: 1 | D12: 4816663
A13: Total Novasoft S A S | C13: 1 | D13: 4816663
A14: Universidad De La Sabana | B14: 107765 | C14: 1 | D14: 1055000
A15: Total Universidad De La Sabana | C15: 1 | D15: 1055000
A16: Agroindustrial De Palma Aceitera SA Sucursal Colombia | B16: 107967 | C16: 1 | D16: 671160
A17: Total Agroindustrial De Palma Aceitera SA Sucursal Colombia | C17: 1 | D17: 671160
A18: Colombian Shared Services SAS | B18: 107896 | C18: 1 | D18: 905590
A19: Total Colombian Shared Services SAS | C19: 1 | D19: 905590
A20: Banco Jpmorgan Colombia SA | B20: 107653 | C20: 1 | D20: 720426
A21: Total Banco Jpmorgan Colombia SA | C21: 1 | D21: 720426
A22: Industria Nacional De Gaseosas SA | B22: 107687 | C22: 1 | D22: 2.7847637e+08
B23: 107760 | C23: 1 | D23: 8723594.9
B24: 107937 | C24: 1 | D24: 35257.32
A25: Total Industria Nacional De Gaseosas SA | C25: 3 | D25: 2.8723522e+08
A26: Palmas De Tumaco SAS | B26: 107704 | C26: 1 | D26: 890838.76
A27: Total Palmas De Tumaco SAS | C27: 1 | D27: 890838.76
A28: Hire Horatio Co S A S | B28: 107810 | C28: 1 | D28: 16213155
A29: Total Hire Horatio Co S A S | C29: 1 | D29: 16213155
A30: C I Union De Bananeros De Uraba SA Uniban | B30: 107752 | C30: 1 | D30: 3430216.6
B31: 107753 | C31: 1 | D31: 6120165.2
A32: Total C I Union De Bananeros De Uraba SA Uniban | C32: 2 | D32: 9550381.9
A33: Fundacion Universidad Del Norte | B33: 107827 | C33: 1 | D33: 437920
A34: Total Fundacion Universidad Del Norte | C34: 1 | D34: 437920
A35: Pc Quick SAS | B35: 108160 | C35: 1 | D35: 16207800
A36: Total Pc Quick SAS | C36: 1 | D36: 16207800
A37: Oftalmos SA | B37: 108196 | C37: 1 | D37: 1142400
B38: 108268 | C38: 1 | D38: 5126520
A39: Total Oftalmos SA | C39: 2 | D39: 6268920
A40: Total general | C40: 21 | D40: 3.5236346e+08

Sheet 3 ACUSES
A1: 3 ACUSE | B1: (Varios elementos)
A3: Nombre Receptor | B3: Folio | C3: Cuenta de 3 ACUSE | D3: Suma de Total
A4: Adecco Servicios Colombia S A | B4: 108019 | C4: 1 | D4: 387940
B5: 108140 | C5: 1 | D5: 3855600
A6: Total Adecco Servicios Colombia S A | C6: 2 | D6: 4243540
A7: Alambres Y Mallas SAS | B7: 108082 | C7: 1 | D7: 7681154.9
A8: Total Alambres Y Mallas SAS | C8: 1 | D8: 7681154.9
A9: Asociacion Para La Enseñanza Aspaen | B9: 108161 | C9: 1 | D9: 1141099.3
A10: Total Asociacion Para La Enseñanza Aspaen | C10: 1 | D10: 1141099.3
A11: Bmi Colombia Compañia De Seguros De Vida SA | B11: 107805 | C11: 1 | D11: 476000
A12: Total Bmi Colombia Compañia De Seguros De Vida SA | C12: 1 | D12: 476000
A13: Boydorr SAS | B13: 107835 | C13: 1 | D13: 428638
A14: Total Boydorr SAS | C14: 1 | D14: 428638
A15: Cadena Comercial Oxxo Colombia SAS | B15: 107891 | C15: 1 | D15: 802739
A16: Total Cadena Comercial Oxxo Colombia SAS | C16: 1 | D16: 802739
A17: Caja Colombiana De Subsidio Familiar Colsubsidio | B17: 107616 | C17: 1 | D17: 195914.46
B18: 107617 | C18: 1 | D18: 197116.36
B19: 107618 | C19: 1 | D19: 197116.36
B20: 107619 | C20: 1 | D20: 197116.36
B21: 107620 | C21: 1 | D21: 195914.46
B22: 107621 | C22: 1 | D22: 195914.46
B23: 107622 | C23: 1 | D23: 185937.5
B24: 107623 | C24: 1 | D24: 182515.06
B25: 107627 | C25: 1 | D25: 309995
B26: 107628 | C26: 1 | D26: 94724
B27: 107629 | C27: 1 | D27: 284172
B28: 107818 | C28: 1 | D28: 174216
B29: 107819 | C29: 1 | D29: 1046605
... B36: 108205 | C36: 1 | D36: 350752.5
A37: Total Caja Colombiana De Subsidio Familiar Colsubsidio | C37: 20 | D37: 4839763.3
A38: Centros Medicos Colsanitas S A S | B38: 107675 | C38: 1 | D38: 2337439.6
B39: 107676 | C39: 1 | D39: 4674879.3
A40: Total Centros Medicos Colsanitas S A S | C40: 2 | D40: 7012318.9
A41: Chevyplan SA Sociedad Administradora De Planes De Autofinanciamiento Comercial | B41: 107825 | C41: 1 | D41: 1650530
A42: Total Chevyplan SA Sociedad Administradora De Planes De Autofinanciamiento Comercial | C42: 1 | D42: 1650530
A43: Clinica Colsanitas SA | B43: 107677 | C43: 1 | D43: 2337439.6
B44: 107678 | C44: 1 | D44: 2337439.6
B45: 107679 | C45: 1 | D45: 2337439.6
B46: 107680 | C46: 1 | D46: 3187810.1
B47: 107681 | C47: 1 | D47: 3187810.1
B48: 107682 | C48: 1 | D48: 3187810.1
B49: 107690 | C49: 1 | D49: 1904000
B50: 107751 | C50: 1 | D50: 1945920.1
B51: 107769 | C51: 1 | D51: 3808000
B52: 107866 | C52: 1 | D52: 867783.7
B53: 107867 | C53: 1 | D53: 1204000.4
A54: Total Clinica Colsanitas SA | C54: 11 | D54: 26305453
A55: Colinagro SA | B55: 107848 | C55: 1 | D55: 1504993
B56: 107863 | C56: 1 | D56: 1132868
A57: Total Colinagro SA | C57: 2 | D57: 2637861
A58: Compañia De Medicina Prepagada Colsanitas SA | B58: 107673 | C58: 1 | D58: 2337439.6
B59: 107674 | C59: 1 | D59: 4120903.4
B60: 107868 | C60: 1 | D60: 297500
A61: Total Compañia De Medicina Prepagada Colsanitas SA | C61: 3 | D61: 6755843
A62: Compañia De Seguros Colsanitas SA | B62: 107683 | C62: 1 | D62: 4674879.3
A63: Total Compañia De Seguros Colsanitas SA | C63: 1 | D63: 4674879.3
A64: Confipetrol SAS | B64: 107794 | C64: 1 | D64: 13574568
A65: Total Confipetrol SAS | C65: 1 | D65: 13574568
A66: Ecologia Y Entorno SAS E.S.P Ecoentorno | B66: 107632 | C66: 1 | D66: 1008911.8
B67: 108015 | C67: 1 | D67: 1381252
A68: Total Ecologia Y Entorno SAS E.S.P Ecoentorno | C68: 2 | D68: 2390163.8
A69: Evertec Colombia SAS | B69: 107631 | C69: 1 | D69: 44625
A70: Total Evertec Colombia SAS | C70: 1 | D70: 44625
A71: Expreso Viajes Y Turismo Expreso SAS | B71: 108138 | C71: 1 | D71: 85680
A72: Total Expreso Viajes Y Turismo Expreso SAS | C72: 1 | D72: 85680
A73: Farmatodo Colombia SAS | B73: 107816 | C73: 1 | D73: 9212980
A74: Total Farmatodo Colombia SAS | C74: 1 | D74: 9212980
A75: Flota La Macarena SA | B75: 107784 | C75: 1 | D75: 806820
A76: Total Flota La Macarena SA | C76: 1 | D76: 806820
A77: Fundacion Universitaria Sanitas | B77: 107684 | C77: 1 | D77: 3955993.2
A78: Total Fundacion Universitaria Sanitas | C78: 1 | D78: 3955993.2
A79: Grupo Empresarial En Linea S.A. | B79: 107626 | C79: 1 | D79: 7778870
A80: Total Grupo Empresarial En Linea S.A. | C80: 1 | D80: 7778870
A81: Hino Motors Manufacturing Colombia SAS | B81: 107716 | C81: 1 | D81: 1190714
A82: Total Hino Motors Manufacturing Colombia SAS | C82: 1 | D82: 1190714
A83: IA4 SAS | B83: 108011 | C83: 1 | D83: 39315.22
A84: Total IA4 SAS | C84: 1 | D84: 39315.22
A85: Indra Colombia SAS | B85: 107735 | C85: 1 | D85: 214200
A86: Total Indra Colombia SAS | C86: 1 | D86: 214200
A87: Integral SA | B87: 108131 | C87: 1 | D87: 797504
A88: Total Integral SA | C88: 1 | D88: 797504
A89: Keralty SAS | B89: 107672 | C89: 1 | D89: 2337439.6
A90: Total Keralty SAS | C90: 1 | D90: 2337439.6
A91: Knauf De Colombia SAS | B91: 108115 | C91: 1 | D91: 735420
A92: Total Knauf De Colombia SAS | C92: 1 | D92: 735420
A93: LM Instruments SA | B93: 107647 | C93: 1 | D93: 309400
A94: Total LM Instruments SA | C94: 1 | D94: 309400
A95: Marketing Services De Colombia SAS | B95: 108233 | C95: 1 | D95: 316540
A96: Total Marketing Services De Colombia SAS | C96: 1 | D96: 316540
A97: Nardiplast SAS | B97: 107786 | C97: 1 | D97: 1100697
B98: 107831 | C98: 1 | D98: 80444
B99: 108061 | C99: 1 | D99: 11900
A100: Total Nardiplast SAS | C100: 3 | D100: 1193041
A101: Partequipos S A S | B101: 108157 | C101: 1 | D101: 2261000
A102: Total Partequipos S A S | C102: 1 | D102: 2261000
A103: Pcs For All SAS | B103: 107846 | C103: 1 | D103: 944229.3
A104: Total Pcs For All SAS | C104: 1 | D104: 944229.3
A105: Quad Graphics Colombia SAS | B105: 107778 | C105: 1 | D105: 459340
A106: Total Quad Graphics Colombia SAS | C106: 1 | D106: 459340
A107: Saenz Fety S A S | B107: 107662 | C107: 1 | D107: 1713600
...

Sheet RECHAZADAS
A1: RECHAZADA | B1: X
A3: Folio | B3: Nombre Receptor | C3: Suma de Total
A4: 107871 | B4: Idom Consulting Engineering Architecture SAU | C4: 107975.84
A5: Total 107871 | C5: 107975.84
A6: 108054 | B6: Salud Total Entidad Promotora De Salud Del Regimen Contributivo Y Del Regimen Subsidiado SA | C6: 829350.27
A7: Total 108054 | C7: 829350.27
A8: 108143 | B8: Indra Colombia SAS | C8: 321300
A9: Total 108143 | C9: 321300
A10: 108497 | B10: Caja Colombiana De Subsidio Familiar Colsubsidio | C10: 46199.37
A11: Total 108497 | C11: 46199.37
A12: Total general | C12: 1304825.5

Sheet SIN ACUSE
A1: SIN ACUSE | B1: (Varios elementos)
A3: Nombre Receptor | B3: Folio | C3: Cuenta de SIN ACUSE | D3: Suma de Total
A4: 24K Global Logistics SAS | B4: 108175 | C4: 1 | D4: 5408550
B5: 108503 | C5: 1 | D5: 522410
B6: 108623 | C6: 1 | D6: 190400
A7: Total 24K Global Logistics SAS | C7: 3 | D7: 6121360
A8: ACI Proyectos SAS | B8: 108806 | C8: 1 | D8: 166600
B9: 109005 | C9: 1 | D9: 135931320
B10: 109088 | C10: 1 | D10: 380359.7
B11: 109089 | C11: 1 | D11: 76517
A12: Total ACI Proyectos SAS | C12: 4 | D12: 1.365548e+08
A13: Adecco Colombia S A | B13: 108489 | C13: 1 | D13: 208250
A14: Total Adecco Colombia S A | C14: 1 | D14: 208250
A15: Adecco Servicios Colombia S A | B15: 108487 | C15: 1 | D15: 141610
B16: 108760 | C16: 1 | D16: 6090580
A17: Total Adecco Servicios Colombia S A | C17: 2 | D17: 6232190
A18: Administradora Country SAS | B18: 108883 | C18: 1 | D18: 285600
B19: 108968 | C19: 1 | D19: 10886333
B20: 109146 | C20: 1 | D20: 2482935
A21: Total Administradora Country SAS | C21: 3 | D21: 13654868
A22: Agencia De Aduanas Abc Repecev SAS Nivel 1 | B22: 109179 | C22: 1 | D22: 345100
B23: 109180 | C23: 1 | D23: 454580
B24: 109181 | C24: 1 | D24: 34510
B25: 109182 | C25: 1 | D25: 34510
A26: Total Agencia De Aduanas Abc Repecev SAS Nivel 1 | C26: 4 | D26: 868700
A27: Agricultura Y Servicios S A S | B27: 108671 | C27: 1 | D27: 14358540
B28: 108983 | C28: 1 | D28: 754460
A29: Total Agricultura Y Servicios S A S | C29: 2 | D29: 15113000
A30: Agrointegral Andina SAS | B30: 108670 | C30: 1 | D30: 14358540
B31: 108768 | C31: 1 | D31: 476000
B32: 108984 | C32: 1 | D32: 841330
A33: Total Agrointegral Andina SAS | C33: 3 | D33: 15675870
A34: Algranel SA | B34: 107703 | C34: 1 | D34: 535500
B35: 107712 | C35: 1 | D35: 3080435.2
B36: 107841 | C36: 1 | D36: 4270435.2
B37: 108032 | C37: 1 | D37: 428400
B38: 108129 | C38: 1 | D38: 982365.23
A39: Total Algranel SA | C39: 5 | D39: 9297135.6
A40: Alimentos Balanceados Tequendama SA Albateq SA | B40: 109220 | C40: 1 | D40: 1763118.3
A41: Total Alimentos Balanceados Tequendama SA Albateq SA | C41: 1 | D41: 1763118.3
A42: Alpopular Almacen General De Depositos SA Alpopular SA | B42: 107707 | C42: 1 | D42: 3170453.9
A43: Total Alpopular Almacen General De Depositos SA Alpopular SA | C43: 1 | D43: 3170453.9
A44: Apicom SAS | B44: 108646 | C44: 1 | D44: 7801473.4
A45: Total Apicom SAS | C45: 1 | D45: 7801473.4
A46: Applus Norcontrol Colombia Limitada | B46: 107727 | C46: 1 | D46: 42840000
B47: 107728 | C47: 1 | D47: 347480.96
B48: 107729 | C48: 1 | D48: 641410
B49: 107730 | C49: 1 | D49: 90678
B50: 107731 | C50: 1 | D50: 125176.1
B51: 107732 | C51: 1 | D51: 190038.24
B52: 107733 | C52: 1 | D52: 683060
B53: 107734 | C53: 1 | D53: 254660
B54: 107736 | C54: 1 | D54: 892500
B55: 107738 | C55: 1 | D55: 260312.5
B56: 107739 | C56: 1 | D56: 149437.82
B57: 107806 | C57: 1 | D57: 1484542.9
B58: 107807 | C58: 1 | D58: 83309.52
... B68: 108477 | C68: 1 | D68: 151463.2
B69: 108776 | C69: 1 | D69: 482431.62
B70: 108833 | C70: 1 | D70: 683060
B71: 108932 | C71: 1 | D71: 381990
B72: 108947 | C72: 1 | D72: 2903659.5
A73: Total Applus Norcontrol Colombia Limitada | C73: 27 | D73: 55944959
A74: Aquia SAS | B74: 108801 | C74: 1 | D74: 1428000
A75: Total Aquia SAS | C75: 1 | D75: 1428000
A76: Area Limpia Distrito Capital SAS E.S.P | B76: 108347 | C76: 1 | D76: 27896000
B77: 108826 | C77: 1 | D77: 684250
B78: 108827 | C78: 1 | D78: 3421250
A79: Total Area Limpia Distrito Capital SAS E.S.P | C79: 3 | D79: 32001500
A80: Asociacion De Egresados De La Universidad De Los Andes Uniandinos | B80: 108505 | C80: 1 | D80: 747882.87
A81: Total Asociacion De Egresados De La Universidad De Los Andes Uniandinos | C81: 1 | D81: 747882.87
A82: Asociacion Nacional De Comercio Exterior | B82: 108241 | C82: 1 | D82: 5716760
A83: Total Asociacion Nacional De Comercio Exterior | C83: 1 | D83: 5716760
A84: Asociacion Para La Enseñanza Aspaen | B84: 108310 | C84: 1 | D84: 135501.73
B85: 109147 | C85: 1 | D85: 1652910
B86: 109148 | C86: 1 | D86: 397448.1
A87: Total Asociacion Para La Enseñanza Aspaen | C87: 3 | D87: 2185859.8
A88: Astaf Auditores Y Consultores Contables SAS | B88: 108802 | C88: 1 | D88: 1071071.4
A89: Total Astaf Auditores Y Consultores Contables SAS | C89: 1 | D89: 1071071.4
A90: Atlas Copco Colombia Ltda | B90: 109100 | C90: 1 | D90: 6580360.8
B91: 109265 | C91: 1 | D91: 481019.42
A92: Total Atlas Copco Colombia Ltda | C92: 2 | D92: 7061380.3
A93: Atp Ingenieria SAS En Reorganizacion | B93: 108353 | C93: 1 | D93: 238000
B94: 108354 | C94: 1 | D94: 995000
B95: 108633 | C95: 1 | D95: 2025000
A96: Total Atp Ingenieria SAS En Reorganizacion | C96: 3 | D96: 3258000
A97: Automundial SA | B97: 108889 | C97: 1 | D97: 223720
A98: Total Automundial SA | C98: 1 | D98: 223720
A99: Avidesa De Occidente SA | B99: 108751 | C99: 1 | D99: 79254
A100: Total Avidesa De Occidente SA | C100: 1 | D100: 79254
A101: Awp Colombia SAS | B101: 108107 | C101: 1 | D101: 245140
A102: Total Awp Colombia SAS | C102: 1 | D102: 245140
A103: Axity Colombia Sociedad Por Acciones Simplificada | B103: 108584 | C103: 1 | D103: 3570000
A104: Total Axity Colombia Sociedad Por Acciones Simplificada | C104: 1 | D104: 3570000
A105: Axure Technologies SA | B105: 108694 | C105: 1 | D105: 2302602.4
A106: Total Axure Technologies SA | C106: 1 | D106: 2302602.4
A107: Basic Farm SAS | B107: 108265 | C107: 1 | D107: 3236800
A108: Total Basic Farm SAS | C108: 1 | D108: 3236800
A109: Bmi Colombia Compañia De Seguros De Vida SA | B109: 108439 | C109: 1 | D109: 2444703.9
A110: Total Bmi Colombia Compañia De Seguros De Vida SA | C110: 1 | D110: 2444703.9
...

Sheet PAGAS EN SISTEMA
A1: YA PAGA EN SISTEMA | B1: (en blanco)
A3: Nombre Receptor | B3: Folio | C3: Cuenta de YA PAGA EN SISTEMA | D3: Suma de Total
A4: 24K Global Logistics SAS | B4: 108175 | D4: 5408550
B5: 108503 | D5: 522410
B6: 108623 | D6: 190400
A7: Total 24K Global Logistics SAS | D7: 6121360
A8: ACI Proyectos SAS | B8: 108806 | D8: 166600
B9: 109005 | D9: 135931320
B10: 109088 | D10: 380359.7
B11: 109089 | D11: 76517
A12: Total ACI Proyectos SAS | D12: 1.365548e+08
A13: Actual Colombia Inmobiliaria SAS | B13: 108057 | D13: 1392300
A14: Total Actual Colombia Inmobiliaria SAS | D14: 1392300
A15: Adecco Colombia S A | B15: 108141 | D15: 433160
B16: 108489 | D16: 208250
A17: Total Adecco Colombia S A | D17: 641410
A18: Adecco Servicios Colombia S A | B18: 108019 | D18: 387940
B19: 108140 | D19: 3855600
B20: 108487 | D20: 141610
B21: 108760 | D21: 6090580
A22: Total Adecco Servicios Colombia S A | D22: 10475730
A23: Administradora Clinica La Colina S A S | B23: 108313 | D23: 3525589.2
A24: Total Administradora Clinica La Colina S A S | D24: 3525589.2
A25: Administradora Country SAS | B25: 107955 | D25: 1155180.6
B26: 108883 | D26: 285600
B27: 108968 | D27: 10886333
B28: 109146 | D28: 2482935
A29: Total Administradora Country SAS | D29: 14810049
A30: Agencia De Aduanas Abc Repecev SAS Nivel 1 | B30: 109179 | D30: 345100
B31: 109180 | D31: 454580
B32: 109181 | D32: 34510
B33: 109182 | D33: 34510
A34: Total Agencia De Aduanas Abc Repecev SAS Nivel 1 | D34: 868700
A35: Agricultura Y Servicios S A S | B35: 108671 | D35: 14358540
B36: 108983 | D36: 754460
A37: Total Agricultura Y Servicios S A S | D37: 15113000
A38: Agrointegral Andina SAS | B38: 108670 | D38: 14358540
B39: 108768 | D39: 476000
B40: 108984 | D40: 841330
A41: Total Agrointegral Andina SAS | D41: 15675870
A42: Alambres Y Mallas SAS | B42: 108082 | D42: 7681154.9
A43: Total Alambres Y Mallas SAS | D43: 7681154.9
A44: Algranel SA | B44: 107703 | D44: 535500
B45: 107712 | D45: 3080435.2
B46: 107841 | D46: 4270435.2
B47: 108032 | D47: 428400
B48: 108129 | D48: 982365.23
A49: Total Algranel SA | D49: 9297135.6
A50: Alimentos Balanceados Tequendama SA Albateq SA | B50: 108371 | D50: 742443.38
B51: 109220 | D51: 1763118.3
A52: Total Alimentos Balanceados Tequendama SA Albateq SA | D52: 2505561.7
A53: Alpopular Almacen General De Depositos SA Alpopular SA | B53: 107707 | D53: 3170453.9
A54: Total Alpopular Almacen General De Depositos SA Alpopular SA | D54: 3170453.9
A55: Apicom SAS | B55: 108646 | D55: 7801473.4
A56: Total Apicom SAS | D56: 7801473.4
A57: Applus Norcontrol Colombia Limitada | B57: 107727 | D57: 42840000
B58: 107728 | D58: 347480.96
B59: 107729 | D59: 641410
B60: 107730 | D60: 90678
B61: 107731 | D61: 125176.1
B62: 107732 | D62: 190038.24
B63: 107733 | D63: 683060
B64: 107734 | D64: 254660
B65: 107736 | D65: 892500
B66: 107738 | D66: 260312.5
B67: 107739 | D67: 149437.82
B68: 107806 | D68: 1484542.9
B69: 107807 | D69: 83309.52
... B79: 108477 | D79: 151463.2
B80: 108776 | D80: 482431.62
B81: 108833 | D81: 683060
B82: 108932 | D82: 381990
B83: 108947 | D83: 2903659.5
A84: Total Applus Norcontrol Colombia Limitada | D84: 55944959
A85: Aquia SAS | B85: 108801 | D85: 1428000
A86: Total Aquia SAS | D86: 1428000
A87: Area Limpia Distrito Capital SAS E.S.P | B87: 108347 | D87: 27896000
B88: 108826 | D88: 684250
B89: 108827 | D89: 3421250
A90: Total Area Limpia Distrito Capital SAS E.S.P | D90: 32001500
A91: Asociacion De Egresados De La Universidad De Los Andes Uniandinos | B91: 108505 | D91: 747882.87
A92: Total Asociacion De Egresados De La Universidad De Los Andes Uniandinos | D92: 747882.87
A93: Asociacion Nacional De Comercio Exterior | B93: 108241 | D93: 5716760
A94: Total Asociacion Nacional De Comercio Exterior | D94: 5716760
A95: Asociacion Para La Enseñanza Aspaen | B95: 108161 | D95: 1141099.3
B96: 108310 | D96: 135501.73
B97: 109147 | D97: 1652910
B98: 109148 | D98: 397448.1
A99: Total Asociacion Para La Enseñanza Aspaen | D99: 3326959.2
A100: Astaf Auditores Y Consultores Contables SAS | B100: 108802 | D100: 1071071.4
A101: Total Astaf Auditores Y Consultores Contables SAS | D101: 1071071.4
A102: Atlas Copco Colombia Ltda | B102: 109100 | D102: 6580360.8
B103: 109265 | D103: 481019.42
A104: Total Atlas Copco Colombia Ltda | D104: 7061380.3
A105: Atp Ingenieria SAS En Reorganizacion | B105: 108353 | D105: 238000
B106: 108354 | D106: 995000
B107: 108633 | D107: 2025000
A108: Total Atp Ingenieria SAS En Reorganizacion | D108: 3258000
A109: Automundial SA | B109: 107608 | D109: 89250
B110: 108373 | D110: 92344
...
